Workbook

Sheet LAVORAZIONI
A1: LAVORAZIONI — RADIOFARMACIA PAVIA — MASTER + RIPARTIZIONE % SAL
A2: CODICE LAVORAZIONE | B2: N° OCCORRENZA | C2: MACRO AREA | D2: TIPOLOGIA IMPIANTO | E2: CATEGORIA SAL | F2: DOCUMENTO DI PROVENIENZA | G2: N. VOCE | H2: STEP DI LAVORAZIONE | I2: AREA DI INTERVENTO | J2: TIPOLOGIA DI INTERVENTO | K2: DESCRIZIONE | L2: DETTAGLI TECNICI | M2: U.M. | N2: QUANTITÀ EDITEL | O2: VALORE UNITARIO EDITEL | P2: TOTALE EDITEL | Q2: QUANTITÀ EDITEL CONSUNTIVATA | R2: VALORE UNITARIO EDITEL CONSUNTIVATO | S2: TOTALE EDITEL CONSUNTIVATO | T2: VALORE PER SAL | U2: SAL 01 APRILE 2026 | W2: SAL 02 MAGGIO 2026 | Y2: SAL 03 GIUGNO 2026 | AA2: SAL 04 LUGLIO 2026 | AC2: SAL 05 AGOSTO 2026 | AE2: SAL 06 SETTEMBRE 2026 | AG2: SAL 07 OTTOBRE 2026 | AI2: TOTALE COMPLESSIVO AVANZAMENTO
U3: % | V3: TOTALE | W3: % | X3: TOTALE | Y3: % | Z3: TOTALE | AA3: % | AB3: TOTALE | AC3: % | AD3: TOTALE | AE3: % | AF3: TOTALE | AG3: % | AH3: TOTALE | AI3: % | AJ3: TOTALE
A4: LOM241.OC.EEA.C09.A6402.NA000.0000 | B4: 1/2 | C4: EDILE | D4: NON SPECIALE | E4: EDILI | F4: 1_2025.11.20_CME REV07.PDF | G4: 1 | H4: 10 - PREPARAZIONE | I4: NUOVI LABORATORI | J4: SCAVI E MOVIMENTI TERRA | K4: OPERA: SBANCAMENTO DI TERRENO GENERICO. INCLUSO: TROVANTI ROCCIOSI/RELITTI DI MURATURE FINO A 0.750 M³. ESCLUSO: ROCCIA. | L4: OPERA: SBANCAMENTO DI TERRENO GENERICO. INCLUSO: TROVANTI ROCCIOSI/RELITTI DI MURATURE FINO A 0.750 M³. ESCLUSO: ROCCIA. LAVORO: SCAVO. INCLUSO: SPIANAMENTO E CONFIGURAZIONE FONDO ANCHE A GRADONI; PROFILATURA DI PARETI E SCARPATE; CARICO, TRASPORTO ED ACCATASTAMENTO MATERIALE IN CANTIERE. ESCLUSO: ARMO DI SCAVO; OPERE DI SEGNALAZIONE E PROTEZIONE. SPECIFICHE TECNICHE: TERRENO DI MATERIALI DI NATURA E CONSISTENZA GENERICHE TERRENO ASCIUTTO/BAGNATO/MELMOSO, PROFONDITÀ GENERICA. COMPONENTI: OP1 OPERA: SBANCAMENTO DI TERRENO GENERICO. INCLUSO: TROVANTI ROCCIOSI/RELITTI DI MURATURE FINO A 0.750 M³. ESCLUSO: ROCCIA. SPECIFICHE TECNICHE: TERRENO DI MATERIALI DI NATURA E CONSISTENZA GENERICHE TERRENO ASCIUTTO/BAGNATO/MELMOSO. RM2 TERRENO DI TERRENO GENERICO LV1 LAVORO: SCAVO. INCLUSO: SPIANAMENTO E CONFIGURAZIONE FONDO ANCHE A GRADONI; PROFILATURA DI PARETI E SCARPATE; CARICO, TRASPORTO ED ACCATASTAMENTO MATERIALE IN CANTIERE. ESCLUSO: ARMO DI SCAVO; OPERE DI SEGNALAZIONE E PROTEZIONE. SPECIFICHE TECNICHE: PROFONDITÀ GENERICA. RP2 ESCAVATORE CINGOLATO; POTENZA [KW] ≤ 90; PESO [T] ≤ 19 SPECIFICHE TECNICHE: CRITERIO DI MISURAZIONE: ORE DI PRESENZA IN CANTIERE RP2 AUTOCARRO A CASSONE RIBALTABILE; PORTATA [T] ≤ 5,0 SPECIFICHE TECNICHE: CRITERIO DI MISURAZIONE: ORE DI PRESENZA IN CANTIERE | M4: M³ | N4: 440.7 | O4: 5.88 | P4: 2591.32 | S4: =IF(AND(Q4<>"",R4<>""),Q4*R4,"") | T4: =IF(S4="",P4,S4) | U4: 1 | V4: =$T4*U4 | W4: 0 | X4: =$T4*W4 | Y4: 0 | Z4: =$T4*Y4 | AA4: 0 | AB4: =$T4*AA4 | AC4: 0 | AD4: =$T4*AC4 | AE4: 0 | AF4: =$T4*AE4 | AG4: 0 | AH4: =$T4*AG4 | AI4: =U4+W4+Y4+AA4+AC4+AE4+AG4 | AJ4: =V4+X4+Z4+AB4+AD4+AF4+AH4
A5: LOM241.1U.04.110.0040.B | B5: 1/4 | C5: EDILE | D5: NON SPECIALE | E5: EDILI | F5: 1_2025.11.20_CME REV07.PDF | G5: 2 | H5: 10 - PREPARAZIONE | I5: NUOVI LABORATORI | J5: SCAVI E MOVIMENTI TERRA | K5: COMPATTAZIONE DEL PIANO DI POSA DELLA FONDAZIONE STRADALE, NEI TRATTI IN TRINCEA, FINO A RAGGIUNGERE IN OGNI PUNTO UN VALORE DELLA DENSITÀ NON MINORE DEL 95% DI QUELLA MASSIMA DELLA PROVA AASHO MODIFI | L5: COMPATTAZIONE DEL PIANO DI POSA DELLA FONDAZIONE STRADALE, NEI TRATTI IN TRINCEA, FINO A RAGGIUNGERE IN OGNI PUNTO UN VALORE DELLA DENSITÀ NON MINORE DEL 95% DI QUELLA MASSIMA DELLA PROVA AASHO MODIFICATA, ED UN VALORE DEL MODULO DI COMPRESSIBILITÀ ME NON MINORE DI 50 N/MM², COMPRESI GLI EVENTUALI INUMIDIMENTI O ESSICAMENTI NECESSARI NEI TRATTI IN TRINCEA: - SU STRATI DI TERRENO A4, A5, A2-6, A2-7, SENZA ASPORTAZIONE O SOSTITUZIONE, MA CON EVENTUALE CORREZIONE DEI MATERIALI IN SITO PER UNA PROFONDITÀ DI CM 20, CON TERRENI ARIDI DA CONTABILIZZARE A PARTE. | M5: M² | N5: 992 | O5: 1.76 | P5: 1745.92 | S5: =IF(AND(Q5<>"",R5<>""),Q5*R5,"") | T5: =IF(S5="",P5,S5) | U5: 1 | V5: =$T5*U5 | W5: 0 | X5: =$T5*W5 | Y5: 0 | Z5: =$T5*Y5 | AA5: 0 | AB5: =$T5*AA5 | AC5: 0 | AD5: =$T5*AC5 | AE5: 0 | AF5: =$T5*AE5 | AG5: 0 | AH5: =$T5*AG5 | AI5: =U5+W5+Y5+AA5+AC5+AE5+AG5 | AJ5: =V5+X5+Z5+AB5+AD5+AF5+AH5
A6: LOM241.NC.90.050.0100.C | B6: 1/2 | C6: EDILE | D6: NON SPECIALE | E6: EDILI | F6: 1_2025.11.20_CME REV07.PDF | G6: 3 | H6: 10 - PREPARAZIONE | I6: NUOVI LABORATORI | J6: SCAVI E MOVIMENTI TERRA | K6: CARICO CON MEZZO MECCANICO DI MATERIALI SFUSI (TERRE DI SCAVO, MACERIE, INERTI ECC.), TRASPORTO E SCARICO, ALLE SEGUENTI DISTANZE DAL CANTIERE: - DA 1,1 FINO A 5 KM. | L6: CARICO CON MEZZO MECCANICO DI MATERIALI SFUSI (TERRE DI SCAVO, MACERIE, INERTI ECC.), TRASPORTO E SCARICO, ALLE SEGUENTI DISTANZE DAL CANTIERE: - DA 1,1 FINO A 5 KM. | M6: M³ | N6: 440.7 | O6: 10.58 | P6: 4662.61 | S6: =IF(AND(Q6<>"",R6<>""),Q6*R6,"") | T6: =IF(S6="",P6,S6) | U6: 1 | V6: =$T6*U6 | W6: 0 | X6: =$T6*W6 | Y6: 0 | Z6: =$T6*Y6 | AA6: 0 | AB6: =$T6*AA6 | AC6: 0 | AD6: =$T6*AC6 | AE6: 0 | AF6: =$T6*AE6 | AG6: 0 | AH6: =$T6*AG6 | AI6: =U6+W6+Y6+AA6+AC6+AE6+AG6 | AJ6: =V6+X6+Z6+AB6+AD6+AF6+AH6
A7: LOM241.1C.27.050.0100.C | B7: 1/3 | C7: EDILE | D7: NON SPECIALE | E7: EDILI | F7: 1_2025.11.20_CME REV07.PDF | G7: 4 | H7: 10 - PREPARAZIONE | I7: NUOVI LABORATORI | J7: SCAVI E MOVIMENTI TERRA | K7: ONERI PER CONFERIMENTO IN IMPIANTI AUTORIZZATI DEI SEGUENTI RIFIUTI URBANI E SPECIALI NON PERICOLOSI: - TERRE E ROCCE NON CONTENENTI SOSTANZE PERICOLOSE (CER 170504), PRESSO IMPIANTO DI RECUPERO AUTOR | L7: ONERI PER CONFERIMENTO IN IMPIANTI AUTORIZZATI DEI SEGUENTI RIFIUTI URBANI E SPECIALI NON PERICOLOSI: - TERRE E ROCCE NON CONTENENTI SOSTANZE PERICOLOSE (CER 170504), PRESSO IMPIANTO DI RECUPERO AUTORIZZATO, SECONDO IL GIUDIZIO DI AMMISSIBILITÀ IN DISCARICA RILASCIATO DAL LABORATORIO DI ANALISI AI SENSI DEL D.M. 27/09/2010 | M7: 100 KG | N7: -3439.8 | O7: 0.82 | P7: -2820.64 | S7: =IF(AND(Q7<>"",R7<>""),Q7*R7,"") | T7: =IF(S7="",P7,S7) | U7: 1 | V7: =$T7*U7 | W7: 0 | X7: =$T7*W7 | Y7: 0 | Z7: =$T7*Y7 | AA7: 0 | AB7: =$T7*AA7 | AC7: 0 | AD7: =$T7*AC7 | AE7: 0 | AF7: =$T7*AE7 | AG7: 0 | AH7: =$T7*AG7 | AI7: =U7+W7+Y7+AA7+AC7+AE7+AG7 | AJ7: =V7+X7+Z7+AB7+AD7+AF7+AH7
A8: LOM241.OC.EEA.C09.A6402.NA000.0000 | B8: 2/2 | C8: EDILE | D8: NON SPECIALE | E8: EDILI | F8: 1_2025.11.20_CME REV07.PDF | G8: 5 | H8: 10 - PREPARAZIONE | I8: NUOVI LABORATORI | J8: SCAVI E MOVIMENTI TERRA | K8: OPERA: SBANCAMENTO DI TERRENO GENERICO. INCLUSO: TROVANTI ROCCIOSI/RELITTI DI MURATURE FINO A 0.750 M³. ESCLUSO: ROCCIA. | L8: OPERA: SBANCAMENTO DI TERRENO GENERICO. INCLUSO: TROVANTI ROCCIOSI/RELITTI DI MURATURE FINO A 0.750 M³. ESCLUSO: ROCCIA. LAVORO: SCAVO. INCLUSO: SPIANAMENTO E CONFIGURAZIONE FONDO ANCHE A GRADONI; PROFILATURA DI PARETI E SCARPATE; CARICO, TRASPORTO ED ACCATASTAMENTO MATERIALE IN CANTIERE. ESCLUSO: ARMO DI SCAVO; OPERE DI SEGNALAZIONE E PROTEZIONE. SPECIFICHE TECNICHE: TERRENO DI MATERIALI DI NATURA E CONSISTENZA GENERICHE TERRENO ASCIUTTO/BAGNATO/MELMOSO, PROFONDITÀ GENERICA. COMPONENTI: OP1 OPERA: SBANCAMENTO DI TERRENO GENERICO. INCLUSO: TROVANTI ROCCIOSI/RELITTI DI MURATURE FINO A 0.750 M³. ESCLUSO: ROCCIA. SPECIFICHE TECNICHE: TERRENO DI MATERIALI DI NATURA E CONSISTENZA GENERICHE TERRENO ASCIUTTO/BAGNATO/MELMOSO. RM2 TERRENO DI TERRENO GENERICO LV1 LAVORO: SCAVO. INCLUSO: SPIANAMENTO E CONFIGURAZIONE FONDO ANCHE A GRADONI; PROFILATURA DI PARETI E SCARPATE; CARICO, TRASPORTO ED ACCATASTAMENTO MATERIALE IN CANTIERE. ESCLUSO: ARMO DI SCAVO; OPERE DI SEGNALAZIONE E PROTEZIONE. SPECIFICHE TECNICHE: PROFONDITÀ GENERICA. RP2 ESCAVATORE CINGOLATO; POTENZA [KW] ≤ 90; PESO [T] ≤ 19 SPECIFICHE TECNICHE: CRITERIO DI MISURAZIONE: ORE DI PRESENZA IN CANTIERE RP2 AUTOCARRO A CASSONE RIBALTABILE; PORTATA [T] ≤ 5,0 SPECIFICHE TECNICHE: CRITERIO DI MISURAZIONE: ORE DI PRESENZA IN CANTIERE | M8: M³ | N8: 877.5 | O8: 5.88 | P8: 5159.7 | S8: =IF(AND(Q8<>"",R8<>""),Q8*R8,"") | T8: =IF(S8="",P8,S8) | U8: 0 | V8: =$T8*U8 | W8: 0.75 | X8: =$T8*W8 | Y8: 0 | Z8: =$T8*Y8 | AA8: 0 | AB8: =$T8*AA8 | AC8: 0 | AD8: =$T8*AC8 | AE8: 0 | AF8: =$T8*AE8 | AG8: 0 | AH8: =$T8*AG8 | AI8: =U8+W8+Y8+AA8+AC8+AE8+AG8 | AJ8: =V8+X8+Z8+AB8+AD8+AF8+AH8
A9: LOM241.1U.04.110.0040.B | B9: 2/4 | C9: EDILE | D9: NON SPECIALE | E9: EDILI | F9: 1_2025.11.20_CME REV07.PDF | G9: 6 | H9: 10 - PREPARAZIONE | I9: NUOVI LABORATORI | J9: SCAVI E MOVIMENTI TERRA | K9: COMPATTAZIONE DEL PIANO DI POSA DELLA FONDAZIONE STRADALE, NEI TRATTI IN TRINCEA, FINO A RAGGIUNGERE IN OGNI PUNTO UN VALORE DELLA DENSITÀ NON MINORE DEL 95% DI QUELLA MASSIMA DELLA PROVA AASHO MODIFI | L9: COMPATTAZIONE DEL PIANO DI POSA DELLA FONDAZIONE STRADALE, NEI TRATTI IN TRINCEA, FINO A RAGGIUNGERE IN OGNI PUNTO UN VALORE DELLA DENSITÀ NON MINORE DEL 95% DI QUELLA MASSIMA DELLA PROVA AASHO MODIFICATA, ED UN VALORE DEL MODULO DI COMPRESSIBILITÀ ME NON MINORE DI 50 N/MM², COMPRESI GLI EVENTUALI INUMIDIMENTI O ESSICAMENTI NECESSARI NEI TRATTI IN TRINCEA: - SU STRATI DI TERRENO A4, A5, A2-6, A2-7, SENZA ASPORTAZIONE O SOSTITUZIONE, MA CON EVENTUALE CORREZIONE DEI MATERIALI IN SITO PER UNA PROFONDITÀ DI CM 20, CON TERRENI ARIDI DA CONTABILIZZARE A PARTE. | M9: M² | N9: 150 | O9: 1.76 | P9: 264 | S9: =IF(AND(Q9<>"",R9<>""),Q9*R9,"") | T9: =IF(S9="",P9,S9) | U9: 0 | V9: =$T9*U9 | W9: 0 | X9: =$T9*W9 | Y9: 0 | Z9: =$T9*Y9 | AA9: 0 | AB9: =$T9*AA9 | AC9: 0 | AD9: =$T9*AC9 | AE9: 0 | AF9: =$T9*AE9 | AG9: 0 | AH9: =$T9*AG9 | AI9: =U9+W9+Y9+AA9+AC9+AE9+AG9 | AJ9: =V9+X9+Z9+AB9+AD9+AF9+AH9
A10: LOM241.NC.90.050.0100.C | B10: 2/2 | C10: EDILE | D10: NON SPECIALE | E10: EDILI | F10: 1_2025.11.20_CME REV07.PDF | G10: 7 | H10: 10 - PREPARAZIONE | I10: NUOVI LABORATORI | J10: SCAVI E MOVIMENTI TERRA | K10: CARICO CON MEZZO MECCANICO DI MATERIALI SFUSI (TERRE DI SCAVO, MACERIE, INERTI ECC.), TRASPORTO E SCARICO, ALLE SEGUENTI DISTANZE DAL CANTIERE: - DA 1,1 FINO A 5 KM. | L10: CARICO CON MEZZO MECCANICO DI MATERIALI SFUSI (TERRE DI SCAVO, MACERIE, INERTI ECC.), TRASPORTO E SCARICO, ALLE SEGUENTI DISTANZE DAL CANTIERE: - DA 1,1 FINO A 5 KM. | M10: M³ | N10: 877.5 | O10: 10.58 | P10: 9283.95 | S10: =IF(AND(Q10<>"",R10<>""),Q10*R10,"") | T10: =IF(S10="",P10,S10) | U10: 0 | V10: =$T10*U10 | W10: 0.75 | X10: =$T10*W10 | Y10: 0 | Z10: =$T10*Y10 | AA10: 0 | AB10: =$T10*AA10 | AC10: 0 | AD10: =$T10*AC10 | AE10: 0 | AF10: =$T10*AE10 | AG10: 0 | AH10: =$T10*AG10 | AI10: =U10+W10+Y10+AA10+AC10+AE10+AG10 | AJ10: =V10+X10+Z10+AB10+AD10+AF10+AH10
A11: LOM241.1C.27.050.0100.C | B11: 2/3 | C11: EDILE | D11: NON SPECIALE | E11: EDILI | F11: 1_2025.11.20_CME REV07.PDF | G11: 8 | H11: 10 - PREPARAZIONE | I11: NUOVI LABORATORI | J11: SCAVI E MOVIMENTI TERRA | K11: ONERI PER CONFERIMENTO IN IMPIANTI AUTORIZZATI DEI SEGUENTI RIFIUTI URBANI E SPECIALI NON PERICOLOSI: - TERRE E ROCCE NON CONTENENTI SOSTANZE PERICOLOSE (CER 170504), PRESSO IMPIANTO DI RECUPERO AUTOR | L11: ONERI PER CONFERIMENTO IN IMPIANTI AUTORIZZATI DEI SEGUENTI RIFIUTI URBANI E SPECIALI NON PERICOLOSI: - TERRE E ROCCE NON CONTENENTI SOSTANZE PERICOLOSE (CER 170504), PRESSO IMPIANTO DI RECUPERO AUTORIZZATO, SECONDO IL GIUDIZIO DI AMMISSIBILITÀ IN DISCARICA RILASCIATO DAL LABORATORIO DI ANALISI AI SENSI DEL D.M. 27/09/2010 | M11: 100 KG | N11: 15795 | O11: 0.82 | P11: 12951.9 | S11: =IF(AND(Q11<>"",R11<>""),Q11*R11,"") | T11: =IF(S11="",P11,S11) | U11: 0 | V11: =$T11*U11 | W11: 0.75 | X11: =$T11*W11 | Y11: 0 | Z11: =$T11*Y11 | AA11: 0 | AB11: =$T11*AA11 | AC11: 0 | AD11: =$T11*AC11 | AE11: 0 | AF11: =$T11*AE11 | AG11: 0 | AH11: =$T11*AG11 | AI11: =U11+W11+Y11+AA11+AC11+AE11+AG11 | AJ11: =V11+X11+Z11+AB11+AD11+AF11+AH11
A12: LOM241.1C.27.050.0100.C | B12: 3/3 | C12: EDILE | D12: NON SPECIALE | E12: EDILI | F12: 1_2025.11.20_CME REV07.PDF | G12: 9 | H12: 10 - PREPARAZIONE | I12: NUOVI LABORATORI | J12: SCAVI E MOVIMENTI TERRA | K12: ONERI PER CONFERIMENTO IN IMPIANTI AUTORIZZATI DEI SEGUENTI RIFIUTI URBANI E SPECIALI NON PERICOLOSI: - TERRE E ROCCE NON CONTENENTI SOSTANZE PERICOLOSE (CER 170504), PRESSO IMPIANTO DI RECUPERO AUTOR | L12: ONERI PER CONFERIMENTO IN IMPIANTI AUTORIZZATI DEI SEGUENTI RIFIUTI URBANI E SPECIALI NON PERICOLOSI: - TERRE E ROCCE NON CONTENENTI SOSTANZE PERICOLOSE (CER 170504), PRESSO IMPIANTO DI RECUPERO AUTORIZZATO, SECONDO IL GIUDIZIO DI AMMISSIBILITÀ IN DISCARICA RILASCIATO DAL LABORATORIO DI ANALISI AI SENSI DEL D.M. 27/09/2010 | M12: 100 KG | N12: 15795 | O12: 0.82 | P12: 12951.9 | S12: =IF(AND(Q12<>"",R12<>""),Q12*R12,"") | T12: =IF(S12="",P12,S12) | U12: 0 | V12: =$T12*U12 | W12: 0.75 | X12: =$T12*W12 | Y12: 0 | Z12: =$T12*Y12 | AA12: 0 | AB12: =$T12*AA12 | AC12: 0 | AD12: =$T12*AC12 | AE12: 0 | AF12: =$T12*AE12 | AG12: 0 | AH12: =$T12*AG12 | AI12: =U12+W12+Y12+AA12+AC12+AE12+AG12 | AJ12: =V12+X12+Z12+AB12+AD12+AF12+AH12
A13: LOM241.OC.EEA.C09.A6400.NA000.0000.B | B13: 1/2 | C13: EDILE | D13: NON SPECIALE | E13: EDILI | F13: 1_2025.11.20_CME REV07.PDF | G13: 28 | H13: 10 - PREPARAZIONE | I13: NUOVI LABORATORI | J13: SCAVI E MOVIMENTI TERRA | K13: OPERA: SCOTICO DI TERRENO GENERICO. | L13: OPERA: SCOTICO DI TERRENO GENERICO. LAVORO: SCAVO CON MEZZI MECCANICI. INCLUSO: ESTIRPAZIONE ERBA, ARBUSTI, ALBERI DI PICCOLE DIMENSIONI; DEMOLIZIONE E RIMOZIONE RECINZIONI; CARICO E TRASPORTO TERRE AD IMPIANTO DI STOCCAGGIO, DI RECUPERO. SPECIFICHE TECNICHE: TERRENO DI NATURA GENERICA. COMPONENTI: OP1 OPERA: SCOTICO DI TERRENO GENERICO. SPECIFICHE TECNICHE: TERRENO DI NATURA GENERICA. RM2 TERRENO DI TERRENO GENERICO LV1 LAVORO: SCAVO CON MEZZI MECCANICI. INCLUSO: ESTIRPAZIONE ERBA, ARBUSTI, ALBERI DI PICCOLE DIMENSIONI; DEMOLIZIONE E RIMOZIONE RECINZIONI; CARICO E TRASPORTO TERRE AD IMPIANTO DI STOCCAGGIO, DI RECUPERO. RP2 AUTOCARRO A CASSONE RIBALTABILE; PORTATA [T] ≤ 1,5 SPECIFICHE TECNICHE: CRITERIO DI MISURAZIONE: ORE DI PRESENZA IN CANTIERE | M13: M³ | N13: 117.6 | O13: 11.76 | P13: 1382.98 | S13: =IF(AND(Q13<>"",R13<>""),Q13*R13,"") | T13: =IF(S13="",P13,S13) | U13: 0 | V13: =$T13*U13 | W13: 0.75 | X13: =$T13*W13 | Y13: 0 | Z13: =$T13*Y13 | AA13: 0 | AB13: =$T13*AA13 | AC13: 0 | AD13: =$T13*AC13 | AE13: 0 | AF13: =$T13*AE13 | AG13: 0 | AH13: =$T13*AG13 | AI13: =U13+W13+Y13+AA13+AC13+AE13+AG13 | AJ13: =V13+X13+Z13+AB13+AD13+AF13+AH13
A14: LOM241.1U.04.110.0040.B | B14: 3/4 | C14: EDILE | D14: NON SPECIALE | E14: EDILI | F14: 1_2025.11.20_CME REV07.PDF | G14: 30 | H14: 10 - PREPARAZIONE | I14: NUOVI LABORATORI | J14: SCAVI E MOVIMENTI TERRA | K14: COMPATTAZIONE DEL PIANO DI POSA DELLA FONDAZIONE STRADALE, NEI TRATTI IN TRINCEA, FINO A RAGGIUNGERE IN OGNI PUNTO UN VALORE DELLA DENSITÀ NON MINORE DEL 95% DI QUELLA MASSIMA DELLA PROVA AASHO MODIFI | L14: COMPATTAZIONE DEL PIANO DI POSA DELLA FONDAZIONE STRADALE, NEI TRATTI IN TRINCEA, FINO A RAGGIUNGERE IN OGNI PUNTO UN VALORE DELLA DENSITÀ NON MINORE DEL 95% DI QUELLA MASSIMA DELLA PROVA AASHO MODIFICATA, ED UN VALORE DEL MODULO DI COMPRESSIBILITÀ ME NON MINORE DI 50 N/MM², COMPRESI GLI EVENTUALI INUMIDIMENTI O ESSICAMENTI NECESSARI NEI TRATTI IN TRINCEA: - SU STRATI DI TERRENO A4, A5, A2-6, A2-7, SENZA ASPORTAZIONE O SOSTITUZIONE, MA CON EVENTUALE CORREZIONE DEI MATERIALI IN SITO PER UNA PROFONDITÀ DI CM 20, CON TERRENI ARIDI DA CONTABILIZZARE A PARTE. | M14: M² | N14: 395 | O14: 1.76 | P14: 695.2 | S14: =IF(AND(Q14<>"",R14<>""),Q14*R14,"") | T14: =IF(S14="",P14,S14) | U14: 0 | V14: =$T14*U14 | W14: 0 | X14: =$T14*W14 | Y14: 0 | Z14: =$T14*Y14 | AA14: 0 | AB14: =$T14*AA14 | AC14: 0 | AD14: =$T14*AC14 | AE14: 0 | AF14: =$T14*AE14 | AG14: 0 | AH14: =$T14*AG14 | AI14: =U14+W14+Y14+AA14+AC14+AE14+AG14 | AJ14: =V14+X14+Z14+AB14+AD14+AF14+AH14
A15: LOM241.OC.EEA.C09.A6400.NA000.0000.B | B15: 2/2 | C15: EDILE | D15: NON SPECIALE | E15: EDILI | F15: 1_2025.11.20_CME REV07.PDF | G15: 33 | H15: 10 - PREPARAZIONE | I15: NUOVI LABORATORI | J15: SCAVI E MOVIMENTI TERRA | K15: OPERA: SCOTICO DI TERRENO GENERICO. | L15: OPERA: SCOTICO DI TERRENO GENERICO. LAVORO: SCAVO CON MEZZI MECCANICI. INCLUSO: ESTIRPAZIONE ERBA, ARBUSTI, ALBERI DI PICCOLE DIMENSIONI; DEMOLIZIONE E RIMOZIONE RECINZIONI; CARICO E TRASPORTO TERRE AD IMPIANTO DI STOCCAGGIO, DI RECUPERO. SPECIFICHE TECNICHE: TERRENO DI NATURA GENERICA. COMPONENTI: OP1 OPERA: SCOTICO DI TERRENO GENERICO. SPECIFICHE TECNICHE: TERRENO DI NATURA GENERICA. RM2 TERRENO DI TERRENO GENERICO LV1 LAVORO: SCAVO CON MEZZI MECCANICI. INCLUSO: ESTIRPAZIONE ERBA, ARBUSTI, ALBERI DI PICCOLE DIMENSIONI; DEMOLIZIONE E RIMOZIONE RECINZIONI; CARICO E TRASPORTO TERRE AD IMPIANTO DI STOCCAGGIO, DI RECUPERO. RP2 AUTOCARRO A CASSONE RIBALTABILE; PORTATA [T] ≤ 1,5 SPECIFICHE TECNICHE: CRITERIO DI MISURAZIONE: ORE DI PRESENZA IN CANTIERE | M15: M³ | N15: 72 | O15: 11.76 | P15: 846.72 | S15: =IF(AND(Q15<>"",R15<>""),Q15*R15,"") | T15: =IF(S15="",P15,S15) | U15: 0 | V15: =$T15*U15 | W15: 0 | X15: =$T15*W15 | Y15: 0 | Z15: =$T15*Y15 | AA15: 0 | AB15: =$T15*AA15 | AC15: 0 | AD15: =$T15*AC15 | AE15: 0 | AF15: =$T15*AE15 | AG15: 0 | AH15: =$T15*AG15 | AI15: =U15+W15+Y15+AA15+AC15+AE15+AG15 | AJ15: =V15+X15+Z15+AB15+AD15+AF15+AH15
... A238: LOM251.OC.EEA.PA15.I7822.D0010.0750.J | B238: 1/2 | C238: IMPIANTO MECCANICO | D238: NON SPECIALE | E238: MECCANICHE | F238: 2_CME_TOTALE MECCANICI RADIOFARMACIA PAVIA.PDF | G238: 216/216 | H238: 40 - IMPIANTISTICO | I238: PIANO TERRA | J238: IMPIANTO IIS E FOGNA | K238: OPERA: TUBAZIONE DI SCARICO DI PLASTICA POLIETILENE AD ALTA DENSITÀ (HDPE/PEAD); FUNZIONE: SCARICO; DIAMETRO ESTERNO (Ø) [MM] = 160. | L238: OPERA: TUBAZIONE DI SCARICO DI PLASTICA POLIETILENE AD ALTA DENSITÀ (HDPE/PEAD); FUNZIONE: SCARICO; DIAMETRO ESTERNO (Ø) [MM] = 160. LAVORO: SALDATURA DI TESTA. INCLUSO: OPERAZIONI DI PREPARAZIONE DI ELEMENTI DA SALDARE; NOLO SALDATRICE; CONSUMI. SPECIFICHE TECNICHE: PEAD MALLEABILIZZATO. OP TUBAZIONE DI SCARICO DI PLASTICA POLIETILENE AD ALTA DENSITÀ (HDPE/PEAD); FUNZIONE: SCARICO; DIAMETRO ESTERNO (Ø) [MM] = 160. SPECIFICHE TECNICHE: PEAD MALLEABILIZZATO. RM TUBO DI PLASTICA POLIETILENE (PE); FINITURA: COLORE NERO; GEOMETRIA: MALLEABILIZZATO; FUNZIONE: SCARICO ACQUE; IMPIEGO: IMPIANTO CIVILE | INDUSTRIALE; DIAMETRO ESTERNO (Ø) [MM] = 160 | SPESSORE [MM] = 6,2. ESCLUSO: RACCORDI SPECIFICHE TECNICHE: DA GIUNTARE CON: SALDATURA DI TESTA, MANICOTTO ELETTRICO O MANICOTTO DI DILATAZIONE LV SALDATURA DI TESTA. INCLUSO: OPERAZIONI DI PREPARAZIONE DI ELEMENTI DA SALDARE; NOLO SALDATRICE; CONSUMI. RP SALDATRICE TESTA-TESTA; DIAMETRO OPERATIVO [MM] = 75 ÷ 250. INCLUSO: ACCESSORI (ES. FRESA SPIANATRICE, TERMOELEMENTO, CENTRALINA, TERMOSTATO, ANELLI DI RIDUZIONE). DA CONTEGGIARE A PARTE: SPESE DI ESERCIZIO (RP.01.20.00.1020.B) | M238: M | N238: 8 | O238: 67.68 | P238: 541.44 | S238: =IF(AND(Q238<>"",R238<>""),Q238*R238,"") | T238: =IF(S238="",P238,S238) | U238: 0 | V238: =$T238*U238 | W238: 0.75 | X238: =$T238*W238 | Y238: 0 | Z238: =$T238*Y238 | AA238: 0 | AB238: =$T238*AA238 | AC238: 0 | AD238: =$T238*AC238 | AE238: 0 | AF238: =$T238*AE238 | AG238: 0 | AH238: =$T238*AG238 | AI238: =U238+W238+Y238+AA238+AC238+AE238+AG238 | AJ238: =V238+X238+Z238+AB238+AD238+AF238+AH238
A239: LOM251.OC.EEA.PA02.I7816.SB030.0000 | B239: 1/1 | C239: IMPIANTO MECCANICO | D239: NON SPECIALE | E239: MECCANICHE | F239: 2_CME_TOTALE MECCANICI RADIOFARMACIA PAVIA.PDF | G239: 217/217 | H239: 40 - IMPIANTISTICO | J239: IMPIANTO ACQUE METEORICHE | K239: OPERA: PLUVIALE, TERMINALE DI LEGA FERROSA GHISA GENERICO. INCLUSO: ACCESSORI DI FISSAGGIO. | L239: OPERA: PLUVIALE, TERMINALE DI LEGA FERROSA GHISA GENERICO. INCLUSO: ACCESSORI DI FISSAGGIO. LAVORO: POSA. INCLUSO: ASSISTENZE MURARIE. OP PLUVIALE, TERMINALE DI LEGA FERROSA GHISA GENERICO. INCLUSO: ACCESSORI DI FISSAGGIO. RM TUBO TERMINALE PLUVIALE DI LEGA FERROSA GHISA GENERICO; GEOMETRIA: DRITTO; IMPIEGO: PLUVIALI; DIAMETRO (Ø) [MM] = 80 | LUNGHEZZA [M] = 1,5 LV POSA. INCLUSO: ASSISTENZE MURARIE. | M239: CAD | N239: 9 | O239: 147.84 | P239: 1330.56 | S239: =IF(AND(Q239<>"",R239<>""),Q239*R239,"") | T239: =IF(S239="",P239,S239) | U239: 0 | V239: =$T239*U239 | W239: 0.5 | X239: =$T239*W239 | Y239: 0 | Z239: =$T239*Y239 | AA239: 0 | AB239: =$T239*AA239 | AC239: 0 | AD239: =$T239*AC239 | AE239: 0 | AF239: =$T239*AE239 | AG239: 0 | AH239: =$T239*AG239 | AI239: =U239+W239+Y239+AA239+AC239+AE239+AG239 | AJ239: =V239+X239+Z239+AB239+AD239+AF239+AH239
A240: LOM251.OC.EEA.PA02.I7836.D0019.0020 | B240: 1/1 | C240: IMPIANTO MECCANICO | D240: NON SPECIALE | E240: MECCANICHE | F240: 2_CME_TOTALE MECCANICI RADIOFARMACIA PAVIA.PDF | G240: 218/218 | H240: 40 - IMPIANTISTICO | J240: IMPIANTO ACQUE METEORICHE | K240: OPERA: TUBAZIONE DI VENTILAZIONE, A BICCHIERE AD INCOLLAGGIO DI PLASTICA POLIVINCLORURO NON PLASTIFICATO (PVC-U); FINITURA: COLORE AVORIO | COLORE GRIGIO | COLORE MARRONE; IMPIEGO: VENTILAZIONE E PLUV | L240: OPERA: TUBAZIONE DI VENTILAZIONE, A BICCHIERE AD INCOLLAGGIO DI PLASTICA POLIVINCLORURO NON PLASTIFICATO (PVC-U); FINITURA: COLORE AVORIO | COLORE GRIGIO | COLORE MARRONE; IMPIEGO: VENTILAZIONE E PLUVIALI; DIAMETRO ESTERNO (Ø) [MM] = 80 | SPESSORE [MM] = 1,5. LAVORO: POSA. INCLUSO: ONERI DI FISSAGGIO A PARETE; ONERI DI FISSAGGIO A SOFFITTI; ONERI ATTRAVERSAMENTI DELLE STRUTTURE. SPECIFICHE TECNICHE: COLORE GRIGIO (RAL 7037); COLORE MARRONE (RAL 8017). OP TUBAZIONE DI VENTILAZIONE, A BICCHIERE AD INCOLLAGGIO DI PLASTICA POLIVINCLORURO NON PLASTIFICATO (PVC-U); FINITURA: COLORE AVORIO | COLORE GRIGIO | COLORE MARRONE; IMPIEGO: VENTILAZIONE E PLUVIALI; DIAMETRO ESTERNO (Ø) [MM] = 80 | SPESSORE [MM] = 1,5. SPECIFICHE TECNICHE: COLORE GRIGIO (RAL 7037); COLORE MARRONE (RAL 8017). RM TUBO A BICCHIERE AD INCOLLAGGIO DI PLASTICA POLIVINCLORURO NON PLASTIFICATO (PVC-U); FINITURA: COLORE AVORIO | COLORE GRIGIO | COLORE MARRONE; IMPIEGO: CONDOTTE DI VENTILAZIONE | PLUVIALI; DIAMETRO ESTERNO (Ø) [MM] = 80 | SPESSORE [MM] = 1,5 SPECIFICHE TECNICHE: COLORI RAL 7037 E RAL 8017 RM SISTEMA DI FISSAGGIO DI PLASTICA POLIVINILCLORURO (PVC); FUNZIONE: VENTILAZIONE | PLUVIALI; IMPIEGO: TUBO DI DIAMETRO ESTERNO [MM] = 80; SPESSORE [MM] = 1,5 LV POSA. INCLUSO: ONERI DI FISSAGGIO A PARETE; ONERI DI FISSAGGIO A SOFFITTI; ONERI ATTRAVERSAMENTI DELLE STRUTTURE. | M240: M | N240: 55 | O240: 30.36 | P240: 1669.8 | S240: =IF(AND(Q240<>"",R240<>""),Q240*R240,"") | T240: =IF(S240="",P240,S240) | U240: 0 | V240: =$T240*U240 | W240: 0.5 | X240: =$T240*W240 | Y240: 0 | Z240: =$T240*Y240 | AA240: 0 | AB240: =$T240*AA240 | AC240: 0 | AD240: =$T240*AC240 | AE240: 0 | AF240: =$T240*AE240 | AG240: 0 | AH240: =$T240*AG240 | AI240: =U240+W240+Y240+AA240+AC240+AE240+AG240 | AJ240: =V240+X240+Z240+AB240+AD240+AF240+AH240
A241: LOM251.OC.EEA.PA02.I7836.D0019.0025 | B241: 1/1 | C241: IMPIANTO MECCANICO | D241: NON SPECIALE | E241: MECCANICHE | F241: 2_CME_TOTALE MECCANICI RADIOFARMACIA PAVIA.PDF | G241: 219/219 | H241: 40 - IMPIANTISTICO | J241: IMPIANTO ACQUE METEORICHE | K241: OPERA: TUBAZIONE DI VENTILAZIONE, A BICCHIERE AD INCOLLAGGIO DI PLASTICA POLIVINCLORURO NON PLASTIFICATO (PVC-U); FINITURA: COLORE AVORIO | COLORE GRIGIO | COLORE MARRONE; IMPIEGO: VENTILAZIONE E PLUV | L241: OPERA: TUBAZIONE DI VENTILAZIONE, A BICCHIERE AD INCOLLAGGIO DI PLASTICA POLIVINCLORURO NON PLASTIFICATO (PVC-U); FINITURA: COLORE AVORIO | COLORE GRIGIO | COLORE MARRONE; IMPIEGO: VENTILAZIONE E PLUVIALI; DIAMETRO ESTERNO (Ø) [MM] = 100 | SPESSORE [MM] = 1,7. LAVORO: POSA. INCLUSO: ONERI DI FISSAGGIO A PARETE; ONERI DI FISSAGGIO A SOFFITTI; ONERI ATTRAVERSAMENTI DELLE STRUTTURE. SPECIFICHE TECNICHE: COLORE GRIGIO (RAL 7037); COLORE MARRONE (RAL 8017). OP TUBAZIONE DI VENTILAZIONE, A BICCHIERE AD INCOLLAGGIO DI PLASTICA POLIVINCLORURO NON PLASTIFICATO (PVC-U); FINITURA: COLORE AVORIO | COLORE GRIGIO | COLORE MARRONE; IMPIEGO: VENTILAZIONE E PLUVIALI; DIAMETRO ESTERNO (Ø) [MM] = 100 | SPESSORE [MM] = 1,7. SPECIFICHE TECNICHE: COLORE GRIGIO (RAL 7037); COLORE MARRONE (RAL 8017). RM TUBO A BICCHIERE AD INCOLLAGGIO DI PLASTICA POLIVINCLORURO NON PLASTIFICATO (PVC-U); FINITURA: COLORE AVORIO | COLORE GRIGIO | COLORE MARRONE; IMPIEGO: CONDOTTE DI VENTILAZIONE | PLUVIALI; DIAMETRO ESTERNO (Ø) [MM] = 100 | SPESSORE [MM] = 1,7 SPECIFICHE TECNICHE: COLORI RAL 7037 E RAL 8017 RM SISTEMA DI FISSAGGIO DI PLASTICA POLIVINILCLORURO (PVC); FUNZIONE: VENTILAZIONE | PLUVIALI; IMPIEGO: TUBO DI DIAMETRO ESTERNO [MM] = 100; SPESSORE [MM] = 1,7 LV POSA. INCLUSO: ONERI DI FISSAGGIO A PARETE; ONERI DI FISSAGGIO A SOFFITTI; ONERI ATTRAVERSAMENTI DELLE STRUTTURE. | M241: M | N241: 15 | O241: 36.37 | P241: 545.55 | S241: =IF(AND(Q241<>"",R241<>""),Q241*R241,"") | T241: =IF(S241="",P241,S241) | U241: 0 | V241: =$T241*U241 | W241: 0.5 | X241: =$T241*W241 | Y241: 0 | Z241: =$T241*Y241 | AA241: 0 | AB241: =$T241*AA241 | AC241: 0 | AD241: =$T241*AC241 | AE241: 0 | AF241: =$T241*AE241 | AG241: 0 | AH241: =$T241*AG241 | AI241: =U241+W241+Y241+AA241+AC241+AE241+AG241 | AJ241: =V241+X241+Z241+AB241+AD241+AF241+AH241
A242: LOM251.OC.EEA.PA02.I7836.D0019.0030 | B242: 1/1 | C242: IMPIANTO MECCANICO | D242: NON SPECIALE | E242: MECCANICHE | F242: 2_CME_TOTALE MECCANICI RADIOFARMACIA PAVIA.PDF | G242: 220/220 | H242: 40 - IMPIANTISTICO | J242: IMPIANTO ACQUE METEORICHE | K242: OPERA: TUBAZIONE DI VENTILAZIONE, A BICCHIERE AD INCOLLAGGIO DI PLASTICA POLIVINCLORURO NON PLASTIFICATO (PVC-U); FINITURA: COLORE AVORIO | COLORE GRIGIO | COLORE MARRONE; IMPIEGO: VENTILAZIONE E PLUV | L242: OPERA: TUBAZIONE DI VENTILAZIONE, A BICCHIERE AD INCOLLAGGIO DI PLASTICA POLIVINCLORURO NON PLASTIFICATO (PVC-U); FINITURA: COLORE AVORIO | COLORE GRIGIO | COLORE MARRONE; IMPIEGO: VENTILAZIONE E PLUVIALI; DIAMETRO ESTERNO (Ø) [MM] = 125 | SPESSORE [MM] = 2. LAVORO: POSA. INCLUSO: ONERI DI FISSAGGIO A PARETE; ONERI DI FISSAGGIO A SOFFITTI; ONERI ATTRAVERSAMENTI DELLE STRUTTURE. SPECIFICHE TECNICHE: COLORE GRIGIO (RAL 7037); COLORE MARRONE (RAL 8017). OP TUBAZIONE DI VENTILAZIONE, A BICCHIERE AD INCOLLAGGIO DI PLASTICA POLIVINCLORURO NON PLASTIFICATO (PVC-U); FINITURA: COLORE AVORIO | COLORE GRIGIO | COLORE MARRONE; IMPIEGO: VENTILAZIONE E PLUVIALI; DIAMETRO ESTERNO (Ø) [MM] = 125 | SPESSORE [MM] = 2. SPECIFICHE TECNICHE: COLORE GRIGIO (RAL 7037); COLORE MARRONE (RAL 8017). RM TUBO A BICCHIERE AD INCOLLAGGIO DI PLASTICA POLIVINCLORURO NON PLASTIFICATO (PVC-U); FINITURA: COLORE AVORIO | COLORE GRIGIO | COLORE MARRONE; IMPIEGO: CONDOTTE DI VENTILAZIONE | PLUVIALI; DIAMETRO ESTERNO (Ø) [MM] = 110 | SPESSORE [MM] = 2 SPECIFICHE TECNICHE: COLORI RAL 7037 E RAL 8017 RM SISTEMA DI FISSAGGIO DI PLASTICA POLIVINILCLORURO (PVC); FUNZIONE: VENTILAZIONE | PLUVIALI; IMPIEGO: TUBO DI DIAMETRO ESTERNO [MM] = 125; SPESSORE [MM] = 2 LV POSA. INCLUSO: ONERI DI FISSAGGIO A PARETE; ONERI DI FISSAGGIO A SOFFITTI; ONERI ATTRAVERSAMENTI DELLE STRUTTURE. | M242: M | N242: 25 | O242: 44.41 | P242: 1110.25 | S242: =IF(AND(Q242<>"",R242<>""),Q242*R242,"") | T242: =IF(S242="",P242,S242) | U242: 0 | V242: =$T242*U242 | W242: 0.5 | X242: =$T242*W242 | Y242: 0 | Z242: =$T242*Y242 | AA242: 0 | AB242: =$T242*AA242 | AC242: 0 | AD242: =$T242*AC242 | AE242: 0 | AF242: =$T242*AE242 | AG242: 0 | AH242: =$T242*AG242 | AI242: =U242+W242+Y242+AA242+AC242+AE242+AG242 | AJ242: =V242+X242+Z242+AB242+AD242+AF242+AH242
A243: LOM251.OC.EEA.PA02.I7836.D0019.0035 | B243: 1/1 | C243: IMPIANTO MECCANICO | D243: NON SPECIALE | E243: MECCANICHE | F243: 2_CME_TOTALE MECCANICI RADIOFARMACIA PAVIA.PDF | G243: 221/221 | H243: 40 - IMPIANTISTICO | J243: IMPIANTO ACQUE METEORICHE | K243: OPERA: TUBAZIONE DI VENTILAZIONE, A BICCHIERE AD INCOLLAGGIO DI PLASTICA POLIVINCLORURO NON PLASTIFICATO (PVC-U); FINITURA: COLORE AVORIO | COLORE GRIGIO | COLORE MARRONE; IMPIEGO: VENTILAZIONE E PLUV | L243: OPERA: TUBAZIONE DI VENTILAZIONE, A BICCHIERE AD INCOLLAGGIO DI PLASTICA POLIVINCLORURO NON PLASTIFICATO (PVC-U); FINITURA: COLORE AVORIO | COLORE GRIGIO | COLORE MARRONE; IMPIEGO: VENTILAZIONE E PLUVIALI; DIAMETRO ESTERNO (Ø) [MM] = 140 | SPESSORE [MM] = 2,3. LAVORO: POSA. INCLUSO: ONERI DI FISSAGGIO A PARETE; ONERI DI FISSAGGIO A SOFFITTI; ONERI ATTRAVERSAMENTI DELLE STRUTTURE. SPECIFICHE TECNICHE: COLORE GRIGIO (RAL 7037); COLORE MARRONE (RAL 8017). OP TUBAZIONE DI VENTILAZIONE, A BICCHIERE AD INCOLLAGGIO DI PLASTICA POLIVINCLORURO NON PLASTIFICATO (PVC-U); FINITURA: COLORE AVORIO | COLORE GRIGIO | COLORE MARRONE; IMPIEGO: VENTILAZIONE E PLUVIALI; DIAMETRO ESTERNO (Ø) [MM] = 140 | SPESSORE [MM] = 2,3. SPECIFICHE TECNICHE: COLORE GRIGIO (RAL 7037); COLORE MARRONE (RAL 8017). RM TUBO A BICCHIERE AD INCOLLAGGIO DI PLASTICA POLIVINCLORURO NON PLASTIFICATO (PVC-U); FINITURA: COLORE AVORIO | COLORE GRIGIO | COLORE MARRONE; IMPIEGO: CONDOTTE DI VENTILAZIONE | PLUVIALI; DIAMETRO ESTERNO (Ø) [MM] = 140 | SPESSORE [MM] = 2,3 SPECIFICHE TECNICHE: COLORI RAL 7037 E RAL 8017 RM SISTEMA DI FISSAGGIO DI PLASTICA POLIVINILCLORURO (PVC); FUNZIONE: VENTILAZIONE | PLUVIALI; IMPIEGO: TUBO DI DIAMETRO ESTERNO [MM] = 140; SPESSORE [MM] = 2,3 LV POSA. INCLUSO: ONERI DI FISSAGGIO A PARETE; ONERI DI FISSAGGIO A SOFFITTI; ONERI ATTRAVERSAMENTI DELLE STRUTTURE. | M243: M | N243: 40 | O243: 58.76 | P243: 2350.4 | S243: =IF(AND(Q243<>"",R243<>""),Q243*R243,"") | T243: =IF(S243="",P243,S243) | U243: 0 | V243: =$T243*U243 | W243: 0.5 | X243: =$T243*W243 | Y243: 0 | Z243: =$T243*Y243 | AA243: 0 | AB243: =$T243*AA243 | AC243: 0 | AD243: =$T243*AC243 | AE243: 0 | AF243: =$T243*AE243 | AG243: 0 | AH243: =$T243*AG243 | AI243: =U243+W243+Y243+AA243+AC243+AE243+AG243 | AJ243: =V243+X243+Z243+AB243+AD243+AF243+AH243
A244: LOM251.OC.EEA.PA02.I7836.D0019.0045 | B244: 1/1 | C244: IMPIANTO MECCANICO | D244: NON SPECIALE | E244: MECCANICHE | F244: 2_CME_TOTALE MECCANICI RADIOFARMACIA PAVIA.PDF | G244: 222/222 | H244: 40 - IMPIANTISTICO | J244: IMPIANTO ACQUE METEORICHE | K244: OPERA: TUBAZIONE DI VENTILAZIONE, A BICCHIERE AD INCOLLAGGIO DI PLASTICA POLIVINCLORURO NON PLASTIFICATO (PVC-U); FINITURA: COLORE AVORIO | COLORE GRIGIO | COLORE MARRONE; IMPIEGO: VENTILAZIONE E PLUV | L244: OPERA: TUBAZIONE DI VENTILAZIONE, A BICCHIERE AD INCOLLAGGIO DI PLASTICA POLIVINCLORURO NON PLASTIFICATO (PVC-U); FINITURA: COLORE AVORIO | COLORE GRIGIO | COLORE MARRONE; IMPIEGO: VENTILAZIONE E PLUVIALI; DIAMETRO ESTERNO (Ø) [MM] = 200 | SPESSORE [MM] = 3,2. LAVORO: POSA. INCLUSO: ONERI DI FISSAGGIO A PARETE; ONERI DI FISSAGGIO A SOFFITTI; ONERI ATTRAVERSAMENTI DELLE STRUTTURE. SPECIFICHE TECNICHE: COLORE GRIGIO (RAL 7037); COLORE MARRONE (RAL 8017). OP TUBAZIONE DI VENTILAZIONE, A BICCHIERE AD INCOLLAGGIO DI PLASTICA POLIVINCLORURO NON PLASTIFICATO (PVC-U); FINITURA: COLORE AVORIO | COLORE GRIGIO | COLORE MARRONE; IMPIEGO: VENTILAZIONE E PLUVIALI; DIAMETRO ESTERNO (Ø) [MM] = 200 | SPESSORE [MM] = 3,2. SPECIFICHE TECNICHE: COLORE GRIGIO (RAL 7037); COLORE MARRONE (RAL 8017). RM TUBO A BICCHIERE AD INCOLLAGGIO DI PLASTICA POLIVINCLORURO NON PLASTIFICATO (PVC-U); FINITURA: COLORE AVORIO | COLORE GRIGIO | COLORE MARRONE; IMPIEGO: CONDOTTE DI VENTILAZIONE | PLUVIALI; DIAMETRO ESTERNO (Ø) [MM] = 200 | SPESSORE [MM] = 3,2 SPECIFICHE TECNICHE: COLORI RAL 7037 E RAL 8017 RM SISTEMA DI FISSAGGIO DI PLASTICA POLIVINILCLORURO (PVC); FUNZIONE: VENTILAZIONE | PLUVIALI; IMPIEGO: TUBO DI DIAMETRO ESTERNO [MM] = 200; SPESSORE [MM] = 3,2 LV POSA. INCLUSO: ONERI DI FISSAGGIO A PARETE; ONERI DI FISSAGGIO A SOFFITTI; ONERI ATTRAVERSAMENTI DELLE STRUTTURE. | M244: M | N244: 150 | O244: 73.5 | P244: 11025 | S244: =IF(AND(Q244<>"",R244<>""),Q244*R244,"") | T244: =IF(S244="",P244,S244) | U244: 0 | V244: =$T244*U244 | W244: 0.5 | X244: =$T244*W244 | Y244: 0 | Z244: =$T244*Y244 | AA244: 0 | AB244: =$T244*AA244 | AC244: 0 | AD244: =$T244*AC244 | AE244: 0 | AF244: =$T244*AE244 | AG244: 0 | AH244: =$T244*AG244 | AI244: =U244+W244+Y244+AA244+AC244+AE244+AG244 | AJ244: =V244+X244+Z244+AB244+AD244+AF244+AH244
A245: LOM251.OC.EEA.PA02.I9730.J0001.0010 | B245: 1/1 | C245: IMPIANTO MECCANICO | D245: NON SPECIALE | E245: MECCANICHE | F245: 2_CME_TOTALE MECCANICI RADIOFARMACIA PAVIA.PDF | G245: 223/223 | H245: 40 - IMPIANTISTICO | J245: IMPIANTO ACQUE METEORICHE | K245: OPERA: POZZETTO DI CONGLOMERATO CEMENTIZIO; FUNZIONE: PER IMMISSIONE PLUVIALI; IMPIEGO: POZZETTO. INCLUSO: CALCESTRUZZO DI SOTTOFONDO, RACCORDO DELLE TUBAZIONI. | L245: OPERA: POZZETTO DI CONGLOMERATO CEMENTIZIO; FUNZIONE: PER IMMISSIONE PLUVIALI; IMPIEGO: POZZETTO. INCLUSO: CALCESTRUZZO DI SOTTOFONDO, RACCORDO DELLE TUBAZIONI. LAVORO: POSA. ESCLUSO: SCAVO; REINTERRO. OP POZZETTO DI CONGLOMERATO CEMENTIZIO; FUNZIONE: PER IMMISSIONE PLUVIALI; IMPIEGO: POZZETTO. INCLUSO: CALCESTRUZZO DI SOTTOFONDO, RACCORDO DELLE TUBAZIONI. RM POZZETTO DI CONGLOMERATO CEMENTIZIO; FUNZIONE: IMMISSIONE PLUVIALI; DIMENSIONE INTERNA X [CM] = 30 | DIMENSIONE INTERNA Y [CM] = 30 | DIMENSIONE ESTERNA X [CM] = 38 | DIMENSIONE ESTERNA Y [CM] = 54 | ALTEZZA [CM] = 40; PESO [KG] = 63 SPECIFICHE TECNICHE: POZZETTO CON CHIUSURA RM IMPASTO PRECONFEZIONATO DI CONGLOMERATO CEMENTIZIO; GEOMETRIA: SFUSO; FUNZIONE: STRUTTURALE | NON STRUTTURALE | DRENANTE; CLASSE DI CONSISTENZA [CLASSE] = S3 | CLASSE DI RESISTENZA [CLASSE] = C12/15 | CLASSE DI ESPOSIZIONE [CLASSE] = X0. COMPONENTI: LEGANTE IDRAULICO, AGGREGATO, LEGANTE IDRAULICO RICICLATO SPECIFICHE TECNICHE: UTILIZZATO IN STRUTTURE ORDINARIE E MANUFATTI NON STRUTTURALI LV POSA. ESCLUSO: SCAVO; REINTERRO. | M245: CAD | N245: 9 | O245: 308 | P245: 2772 | S245: =IF(AND(Q245<>"",R245<>""),Q245*R245,"") | T245: =IF(S245="",P245,S245) | U245: 0 | V245: =$T245*U245 | W245: 0.5 | X245: =$T245*W245 | Y245: 0 | Z245: =$T245*Y245 | AA245: 0 | AB245: =$T245*AA245 | AC245: 0 | AD245: =$T245*AC245 | AE245: 0 | AF245: =$T245*AE245 | AG245: 0 | AH245: =$T245*AG245 | AI245: =U245+W245+Y245+AA245+AC245+AE245+AG245 | AJ245: =V245+X245+Z245+AB245+AD245+AF245+AH245
A246: LOM251.OC.EEA.PA02.I9740.J0001.0010 | B246: 1/1 | C246: IMPIANTO MECCANICO | D246: NON SPECIALE | E246: MECCANICHE | F246: 2_CME_TOTALE MECCANICI RADIOFARMACIA PAVIA.PDF | G246: 224/224 | H246: 40 - IMPIANTISTICO | J246: IMPIANTO ACQUE METEORICHE | K246: OPERA: CHIUSINO DI CONGLOMERATO CEMENTIZIO; IMPIEGO: POZZETTI; LUCE INTERNA X [CM] = 45 | LUCE INTERNA Y [CM] = 45 | SPESSORE [CM] = 12; PESO [KG] = 50. | L246: OPERA: CHIUSINO DI CONGLOMERATO CEMENTIZIO; IMPIEGO: POZZETTI; LUCE INTERNA X [CM] = 45 | LUCE INTERNA Y [CM] = 45 | SPESSORE [CM] = 12; PESO [KG] = 50. LAVORO: POSA. OP CHIUSINO DI CONGLOMERATO CEMENTIZIO; IMPIEGO: POZZETTI; LUCE INTERNA X [CM] = 45 | LUCE INTERNA Y [CM] = 45 | SPESSORE [CM] = 12; PESO [KG] = 50. RM CHIUSINO DI CONGLOMERATO CEMENTIZIO; FUNZIONE: CHIUSURA; IMPIEGO: POZZETTI; LUCE INTERNA X [CM] = 45 | LUCE INTERNA Y [CM] = 45 | SPESSORE [CM] = 12; PESO [KG] = 90 SPECIFICHE TECNICHE: COMPLETO DI TELAIO RM PREMISCELATO MALTA DA INGHISAGGIO; FUNZIONE: ANTIRITIRO | PRESA RAPIDA | FISSAGGIO; IMPIEGO: ZANCHE | CHIUSINI | INFISSI | INFERRIATE; DENSITÀ [KG/M³] = 2000 SPECIFICHE TECNICHE: A BASE DI CEMENTO, INERTI SELEZIONATI, ADDITIVI; UTILIZZABILE SU TUTTI I SUPPORTI RESISTENTI LV POSA. RP AUTOCARRO CON GRU; PORTATA [T] ≤ 3. INCLUSO: ACCESSORI DI SOLLEVAMENTO. DA CONTEGGIARE A PARTE: SPESE DI ESERCIZIO (RP.00.40.15.1020.A) | M246: CAD | N246: 9 | O246: 61.6 | P246: 554.4 | S246: =IF(AND(Q246<>"",R246<>""),Q246*R246,"") | T246: =IF(S246="",P246,S246) | U246: 0 | V246: =$T246*U246 | W246: 0 | X246: =$T246*W246 | Y246: 0 | Z246: =$T246*Y246 | AA246: 0 | AB246: =$T246*AA246 | AC246: 0 | AD246: =$T246*AC246 | AE246: 0 | AF246: =$T246*AE246 | AG246: 0 | AH246: =$T246*AG246 | AI246: =U246+W246+Y246+AA246+AC246+AE246+AG246 | AJ246: =V246+X246+Z246+AB246+AD246+AF246+AH246
A247: LOM251.OC.EEA.MC09.A6401.NA000.0000.A | B247: 1/1 | C247: IMPIANTO MECCANICO | D247: NON SPECIALE | E247: MECCANICHE | F247: 2_CME_TOTALE MECCANICI RADIOFARMACIA PAVIA.PDF | G247: 225/225 | H247: 40 - IMPIANTISTICO | J247: IMPIANTO ACQUE METEORICHE | K247: OPERA: TRINCEA DI TERRA GENERICO; IMPIEGO: TUBAZIONI | COLLETTORI; PROFONDITÀ [M] ≤ 1,5. | L247: OPERA: TRINCEA DI TERRA GENERICO; IMPIEGO: TUBAZIONI | COLLETTORI; PROFONDITÀ [M] ≤ 1,5. LAVORO: SCAVO CON MEZZO MECCANICO. INCLUSO: DEPOSITO MATERIALE A BORDO SCAVO. ESCLUSO: ARMO DI SCAVO; OPERE PROVVISIONALI DI SEGNALETICA E PROTEZIONE; CARICO E TRASPORTO; ONERI DI SMALTIMENTO. SPECIFICHE TECNICHE: NON ARMATO. OP TRINCEA DI TERRA GENERICO; IMPIEGO: TUBAZIONI | COLLETTORI; PROFONDITÀ [M] ≤ 1,5. SPECIFICHE TECNICHE: NON ARMATO. RM TERRENO DI TERRA GENERICO LV SCAVO CON MEZZO MECCANICO. INCLUSO: DEPOSITO MATERIALE A BORDO SCAVO. ESCLUSO: ARMO DI SCAVO; OPERE PROVVISIONALI DI SEGNALETICA E PROTEZIONE; CARICO E TRASPORTO; ONERI DI SMALTIMENTO. RP ESCAVATORE CINGOLATO; POTENZA [KW] ≤ 90; PESO [T] = 19. DA CONTEGGIARE A PARTE: SPESE DI ESERCIZIO (RP.00.00.00.1020.D) | M247: M³ | N247: 60 | O247: 18.48 | P247: 1108.8 | S247: =IF(AND(Q247<>"",R247<>""),Q247*R247,"") | T247: =IF(S247="",P247,S247) | U247: 0 | V247: =$T247*U247 | W247: 0 | X247: =$T247*W247 | Y247: 0 | Z247: =$T247*Y247 | AA247: 0 | AB247: =$T247*AA247 | AC247: 0 | AD247: =$T247*AC247 | AE247: 0 | AF247: =$T247*AE247 | AG247: 0 | AH247: =$T247*AG247 | AI247: =U247+W247+Y247+AA247+AC247+AE247+AG247 | AJ247: =V247+X247+Z247+AB247+AD247+AF247+AH247
A248: LOM251.OC.EEA.PA04.A6600.NA000.0015 | B248: 1/1 | C248: IMPIANTO MECCANICO | D248: NON SPECIALE | E248: MECCANICHE | F248: 2_CME_TOTALE MECCANICI RADIOFARMACIA PAVIA.PDF | G248: 226/226 | H248: 40 - IMPIANTISTICO | J248: IMPIANTO ACQUE METEORICHE | K248: OPERA: REINTERRO DI TERRA GENERICO. | L248: OPERA: REINTERRO DI TERRA GENERICO. LAVORO: FORMAZIONE. INCLUSO: CARICO, TRASPORTO E SCARICO A LUOGO D'IMPIEGO; SPIANAMENTI E COSTIPAZIONE A STRATI NON SUPERIORI A 50 CM; BAGNATURA; RICARICHI. OP REINTERRO DI TERRA GENERICO. RM AGGREGATO MISTO GRANULARE DI ROCCIA NATURALE MINERALE; PESO SPECIFICO MEDIO [KG/M³] = 1800 SPECIFICHE TECNICHE: DI SABBIA E GHIAIA LV FORMAZIONE. INCLUSO: CARICO, TRASPORTO E SCARICO A LUOGO D'IMPIEGO; SPIANAMENTI E COSTIPAZIONE A STRATI NON SUPERIORI A 50 CM; BAGNATURA; RICARICHI. RP MINI ESCAVATORE CINGOLATO; POTENZA [KW] ≤ 50; PESO [T] = 9. DA CONTEGGIARE A PARTE: SPESE DI ESERCIZIO (RP.00.00.00.1010.G) RP PALA CINGOLATA; POTENZA [KW] ≤ 55. DA CONTEGGIARE A PARTE: SPESE DI ESERCIZIO (RP.00.00.05.1030.A) RP RULLO COMPRESSORE; PESO [T] = 6. ESCLUSO: TRATTORE. DA CONTEGGIARE A PARTE: SPESE DI ESERCIZIO (RP.00.10.05.1010.D) SPECIFICHE TECNICHE: TRAINATO. RP AUTOCARRO A CASSONE RIBALTABILE; PORTATA [T] = 5,01 ÷ 13,5. DA CONTEGGIARE A PARTE: SPESE DI ESERCIZIO (RP.00.50.00.1030.D) | M248: M³ | N248: 60 | O248: 9.86 | P248: 591.6 | S248: =IF(AND(Q248<>"",R248<>""),Q248*R248,"") | T248: =IF(S248="",P248,S248) | U248: 0 | V248: =$T248*U248 | W248: 0 | X248: =$T248*W248 | Y248: 0 | Z248: =$T248*Y248 | AA248: 0 | AB248: =$T248*AA248 | AC248: 0 | AD248: =$T248*AC248 | AE248: 0 | AF248: =$T248*AE248 | AG248: 0 | AH248: =$T248*AG248 | AI248: =U248+W248+Y248+AA248+AC248+AE248+AG248 | AJ248: =V248+X248+Z248+AB248+AD248+AF248+AH248
A249: DEI_IT_035316F | B249: 1/2 | C249: IMPIANTO MECCANICO | D249: NON SPECIALE | E249: MECCANICHE | F249: 2_CME_TOTALE MECCANICI RADIOFARMACIA PAVIA.PDF | G249: 121/121 | H249: 50 - INSTALLAZIONE | I249: P. TERRA - UFFICI | J249: IMPIANTO HVAC | K249: RECUPERATORE DI CALORE CENTRALIZZATO INSTALLATO A PARETE INTERNA O SOFFITTO, CON SCAMBIATORE A FLUSSI INCROCIATI IN CONTROCORRENTE, COMPLETO DI FILTRI SINTETICI POSIZIONATI SULL'ASPIRAZIONE DELL'ARIA | L249: RECUPERATORE DI CALORE CENTRALIZZATO INSTALLATO A PARETE INTERNA O SOFFITTO, CON SCAMBIATORE A FLUSSI INCROCIATI IN CONTROCORRENTE, COMPLETO DI FILTRI SINTETICI POSIZIONATI SULL'ASPIRAZIONE DELL'ARIA ESPULSA E SULLA PRESA D'ARIA ESTERNA, MOTORE CON ALIMENTAZIONE ELETTRICA 230 V-1-50 HZ, IN OPERA COMPRESI ACCESSORI ED ESCLUSI COLLEGAMENTI ELETTRICI: SCAMBIATORE DI CALORE SENSIBILE, DELLE SEGUENTI PORTATE NOMINALI: 600 MC/H | M249: CAD | N249: 1 | O249: 2703.76 | P249: 2703.76 | S249: =IF(AND(Q249<>"",R249<>""),Q249*R249,"") | T249: =IF(S249="",P249,S249) | U249: 0.5 | V249: =$T249*U249 | W249: 0.2 | X249: =$T249*W249 | Y249: 0 | Z249: =$T249*Y249 | AA249: 0 | AB249: =$T249*AA249 | AC249: 0 | AD249: =$T249*AC249 | AE249: 0 | AF249: =$T249*AE249 | AG249: 0 | AH249: =$T249*AG249 | AI249: =U249+W249+Y249+AA249+AC249+AE249+AG249 | AJ249: =V249+X249+Z249+AB249+AD249+AF249+AH249
A250: DEI_IT_035316F | B250: 2/2 | C250: IMPIANTO MECCANICO | D250: NON SPECIALE | E250: MECCANICHE | F250: 2_CME_TOTALE MECCANICI RADIOFARMACIA PAVIA.PDF | G250: 135/135 | H250: 50 - INSTALLAZIONE | I250: P. PRIMO - UFFICI | J250: IMPIANTO HVAC | K250: RECUPERATORE DI CALORE CENTRALIZZATO INSTALLATO A PARETE INTERNA O SOFFITTO, CON SCAMBIATORE A FLUSSI INCROCIATI IN CONTROCORRENTE, COMPLETO DI FILTRI SINTETICI POSIZIONATI SULL'ASPIRAZIONE DELL'ARIA | L250: RECUPERATORE DI CALORE CENTRALIZZATO INSTALLATO A PARETE INTERNA O SOFFITTO, CON SCAMBIATORE A FLUSSI INCROCIATI IN CONTROCORRENTE, COMPLETO DI FILTRI SINTETICI POSIZIONATI SULL'ASPIRAZIONE DELL'ARIA ESPULSA E SULLA PRESA D'ARIA ESTERNA, MOTORE CON ALIMENTAZIONE ELETTRICA 230 V-1-50 HZ, IN OPERA COMPRESI ACCESSORI ED ESCLUSI COLLEGAMENTI ELETTRICI: SCAMBIATORE DI CALORE SENSIBILE, DELLE SEGUENTI PORTATE NOMINALI: 600 MC/H | M250: CAD | N250: 1 | O250: 2745.01 | P250: 2745.01 | S250: =IF(AND(Q250<>"",R250<>""),Q250*R250,"") | T250: =IF(S250="",P250,S250) | U250: 0 | V250: =$T250*U250 | W250: 0.7 | X250: =$T250*W250 | Y250: 0 | Z250: =$T250*Y250 | AA250: 0 | AB250: =$T250*AA250 | AC250: 0 | AD250: =$T250*AC250 | AE250: 0 | AF250: =$T250*AE250 | AG250: 0 | AH250: =$T250*AG250 | AI250: =U250+W250+Y250+AA250+AC250+AE250+AG250 | AJ250: =V250+X250+Z250+AB250+AD250+AF250+AH250
A251: NP.IM.01 | B251: 1/2 | C251: IMPIANTO MECCANICO | D251: NON SPECIALE | E251: MECCANICHE | F251: 2_CME_TOTALE MECCANICI RADIOFARMACIA PAVIA.PDF | G251: 176/176 | H251: 50 - INSTALLAZIONE | I251: CENTRALE | J251: IMPIANTO HVAC | K251: FORNITURA E POSA IN OPERA DI POMPS DI CALORE POLIVALENTE CON CONDENSAZIONE AD ARIA, CERTIFICATO EUROVENT, COSTRUITO SECONDO STANDARD DI QUALITÀ ISO 9001, PER INSTALLAZIONE ESTERNA | L251: FORNITURA E POSA IN OPERA DI POMPS DI CALORE POLIVALENTE CON CONDENSAZIONE AD ARIA, CERTIFICATO EUROVENT, COSTRUITO SECONDO STANDARD DI QUALITÀ ISO 9001, PER INSTALLAZIONE ESTERNA CONDIZIONI DI LAVORO: ARIA INGRESSO SCAMBIATORE ESTERNO: +35°C - ACQUA: +7°/+12°C POTENZIALITÀ FRIGORIFERA: 250 KW ARIA INGRESSO SCAMBIATORE ESTERNO: +7°C - ACQUA: +45°/+40°C POTENZIALITÀ TERMICA: 250 KW | M251: CADAUNO | N251: 0.1 | O251: 95343.27 | P251: 9534.33 | S251: =IF(AND(Q251<>"",R251<>""),Q251*R251,"") | T251: =IF(S251="",P251,S251) | U251: 0 | V251: =$T251*U251 | W251: 0.5 | X251: =$T251*W251 | Y251: 0 | Z251: =$T251*Y251 | AA251: 0 | AB251: =$T251*AA251 | AC251: 0 | AD251: =$T251*AC251 | AE251: 0 | AF251: =$T251*AE251 | AG251: 0 | AH251: =$T251*AG251 | AI251: =U251+W251+Y251+AA251+AC251+AE251+AG251 | AJ251: =V251+X251+Z251+AB251+AD251+AF251+AH251
A252: DEI_IT_025264B | B252: 1/2 | C252: IMPIANTO MECCANICO | D252: NON SPECIALE | E252: MECCANICHE | F252: 2_CME_TOTALE MECCANICI RADIOFARMACIA PAVIA.PDF | G252: 177/177 | H252: 50 - INSTALLAZIONE | I252: CENTRALE | J252: IMPIANTO HVAC | K252: POMPA DI CIRCOLAZIONE IN-LINE A MOTORE VENTILATO A 4 POLI AD ALTO RENDIMENTO (IE3), ATTACCHI FLANGIATI, CORPO IN GHISA, PER IL CONVOGLIAMENTO DI ACQUA FREDDA E CALDA (TEMPERATURA LIQUIDO -20 °C ÷ +120 | L252: POMPA DI CIRCOLAZIONE IN-LINE A MOTORE VENTILATO A 4 POLI AD ALTO RENDIMENTO (IE3), ATTACCHI FLANGIATI, CORPO IN GHISA, PER IL CONVOGLIAMENTO DI ACQUA FREDDA E CALDA (TEMPERATURA LIQUIDO -20 °C ÷ +120 °C), PN 10, GRADO DI PROTEZIONE IP 55, CLASSE DI ISOLAMENTO F, ALIMENTAZIONE ELETTRICA 230/400 V, COMPRESI ACCESSORI DI MONTAGGIO, ESCLUSO IL COLLEGAMENTO ELETTRICO: POTENZA ELETTRICA 1,1 KW, Ø ATTACCO 80 MM | M252: CAD | N252: 4 | O252: 2669.15 | P252: 10676.6 | S252: =IF(AND(Q252<>"",R252<>""),Q252*R252,"") | T252: =IF(S252="",P252,S252) | U252: 0.5 | V252: =$T252*U252 | W252: 0.1 | X252: =$T252*W252 | Y252: 0 | Z252: =$T252*Y252 | AA252: 0 | AB252: =$T252*AA252 | AC252: 0 | AD252: =$T252*AC252 | AE252: 0 | AF252: =$T252*AE252 | AG252: 0 | AH252: =$T252*AG252 | AI252: =U252+W252+Y252+AA252+AC252+AE252+AG252 | AJ252: =V252+X252+Z252+AB252+AD252+AF252+AH252
A253: LOM251.OC.EEA.PA01.I8000.SB038.0055 | B253: 1/2 | C253: IMPIANTO MECCANICO | D253: NON SPECIALE | E253: MECCANICHE | F253: 2_CME_TOTALE MECCANICI RADIOFARMACIA PAVIA.PDF | G253: 178/178 | H253: 50 - INSTALLAZIONE | I253: CENTRALE | J253: IMPIANTO HVAC | K253: OPERA: SERBATOIO, INERZIALE DI LEGA FERROSA ACCIAIO NERO; FINITURA: VERNICIATO | ANTIRUGGINE; GEOMETRIA: VERTICALE; FUNZIONE: ACCUMULO ACQUA REFRIGERATA; IMPIEGO: CENTRALE IDRICA; PRESSIONE MASSIMA DI | L253: OPERA: SERBATOIO, INERZIALE DI LEGA FERROSA ACCIAIO NERO; FINITURA: VERNICIATO | ANTIRUGGINE; GEOMETRIA: VERTICALE; FUNZIONE: ACCUMULO ACQUA REFRIGERATA; IMPIEGO: CENTRALE IDRICA; PRESSIONE MASSIMA DI ESERCIZIO [BAR] = 6; CAPACITÀ [L] = 1500. LAVORO: INSTALLAZIONE. SPECIFICHE TECNICHE: SERBATOIO CON VERNICIATURA ESTERNA ANTIRUGGINE. OP SERBATOIO, INERZIALE DI LEGA FERROSA ACCIAIO NERO; FINITURA: VERNICIATO | ANTIRUGGINE; GEOMETRIA: VERTICALE; FUNZIONE: ACCUMULO ACQUA REFRIGERATA; IMPIEGO: CENTRALE IDRICA; PRESSIONE MASSIMA DI ESERCIZIO [BAR] = 6; CAPACITÀ [L] = 1500. SPECIFICHE TECNICHE: SERBATOIO CON VERNICIATURA ESTERNA ANTIRUGGINE. RM SERBATOIO INERZIALE DI LEGA FERROSA ACCIAIO NERO; FINITURA: VERNICIATO | ANTIRUGGINE; GEOMETRIA: VERTICALE; FUNZIONE: ACCUMULO ACQUA REFRIGERATA; IMPIEGO: CENTRALE IDRICA; PRESSIONE MASSIMA DI ESERCIZIO [BAR] = 6; CAPACITÀ [L] = 1500. COMPONENTE: LASTRA, SPECIFICHE TECNICHE: SERBATOIO CON VERNICIATURA ESTERNA ANTIRUGGINE LV INSTALLAZIONE. | M253: CAD | N253: 0.2 | O253: 1897.38 | P253: 379.48 | S253: =IF(AND(Q253<>"",R253<>""),Q253*R253,"") | T253: =IF(S253="",P253,S253) | U253: 0 | V253: =$T253*U253 | W253: 0.5 | X253: =$T253*W253 | Y253: 0 | Z253: =$T253*Y253 | AA253: 0 | AB253: =$T253*AA253 | AC253: 0 | AD253: =$T253*AC253 | AE253: 0 | AF253: =$T253*AE253 | AG253: 0 | AH253: =$T253*AG253 | AI253: =U253+W253+Y253+AA253+AC253+AE253+AG253 | AJ253: =V253+X253+Z253+AB253+AD253+AF253+AH253
A254: LOM251.OC.EEA.PA01.I8000.SB038.0015 | B254: 1/2 | C254: IMPIANTO MECCANICO | D254: NON SPECIALE | E254: MECCANICHE | F254: 2_CME_TOTALE MECCANICI RADIOFARMACIA PAVIA.PDF | G254: 179/179 | H254: 50 - INSTALLAZIONE | I254: CENTRALE | J254: IMPIANTO HVAC | K254: OPERA: SERBATOIO, INERZIALE DI LEGA FERROSA ACCIAIO NERO; FINITURA: VERNICIATO | ANTIRUGGINE; GEOMETRIA: VERTICALE; FUNZIONE: ACCUMULO ACQUA CALDA; IMPIEGO: CENTRALE IDRICA; PRESSIONE DI BOLLO [BAR] = | L254: OPERA: SERBATOIO, INERZIALE DI LEGA FERROSA ACCIAIO NERO; FINITURA: VERNICIATO | ANTIRUGGINE; GEOMETRIA: VERTICALE; FUNZIONE: ACCUMULO ACQUA CALDA; IMPIEGO: CENTRALE IDRICA; PRESSIONE DI BOLLO [BAR] = 12; CAPACITÀ [L] = 1500. LAVORO: INSTALLAZIONE. SPECIFICHE TECNICHE: SERBATOIO CON VERNICIATURA ESTERNA ANTIRUGGINE; TEMPERATURA MASSIMA DI ESERCIZIO [°C] = 99. OP SERBATOIO, INERZIALE DI LEGA FERROSA ACCIAIO NERO; FINITURA: VERNICIATO | ANTIRUGGINE; GEOMETRIA: VERTICALE; FUNZIONE: ACCUMULO ACQUA CALDA; IMPIEGO: CENTRALE IDRICA; PRESSIONE DI BOLLO [BAR] = 12; CAPACITÀ [L] = 1500. SPECIFICHE TECNICHE: SERBATOIO CON VERNICIATURA ESTERNA ANTIRUGGINE; TEMPERATURA MASSIMA DI ESERCIZIO [°C] = 99. RM SERBATOIO INERZIALE DI LEGA FERROSA ACCIAIO NERO; FINITURA: VERNICIATO | ANTIRUGGINE; GEOMETRIA: VERTICALE; FUNZIONE: ACCUMULO ACQUA CALDA; IMPIEGO: CENTRALE IDRICA; PRESSIONE MASSIMA DI ESERCIZIO [BAR] = 6; CAPACITÀ [L] = 1500. COMPONENTE: LASTRA, SPECIFICHE TECNICHE: SERBATOIO CON VERNICIATURA ESTERNA ANTIRUGGINE; TEMPERATURA MASSIMA DI ESERCIZIO [°C] = 99 LV INSTALLAZIONE. | M254: CAD | N254: 0.2 | O254: 1897.38 | P254: 379.48 | S254: =IF(AND(Q254<>"",R254<>""),Q254*R254,"") | T254: =IF(S254="",P254,S254) | U254: 0 | V254: =$T254*U254 | W254: 0.5 | X254: =$T254*W254 | Y254: 0 | Z254: =$T254*Y254 | AA254: 0 | AB254: =$T254*AA254 | AC254: 0 | AD254: =$T254*AC254 | AE254: 0 | AF254: =$T254*AE254 | AG254: 0 | AH254: =$T254*AG254 | AI254: =U254+W254+Y254+AA254+AC254+AE254+AG254 | AJ254: =V254+X254+Z254+AB254+AD254+AF254+AH254
A255: LOM251.OC.EEA.PA02.I9762.SB001.0965 | B255: 1/2 | C255: IMPIANTO MECCANICO | D255: NON SPECIALE | E255: MECCANICHE | F255: 2_CME_TOTALE MECCANICI RADIOFARMACIA PAVIA.PDF | G255: 185/185 | H255: 50 - INSTALLAZIONE | I255: CENTRALE | J255: IMPIANTO HVAC | K255: OPERA: VALVOLA DI LEGA FERROSA ACCIAIO GENERICO; GEOMETRIA: A DISCO | TIPO WAFER; FUNZIONE: DI RITEGNO; DIAMETRO NOMINALE (Ø) [MM] = 40; PRESSIONE NOMINALE [BAR] = 10 ÷ 40. INCLUSO: MOLLA DI LEGA FERR | L255: OPERA: VALVOLA DI LEGA FERROSA ACCIAIO GENERICO; GEOMETRIA: A DISCO | TIPO WAFER; FUNZIONE: DI RITEGNO; DIAMETRO NOMINALE (Ø) [MM] = 40; PRESSIONE NOMINALE [BAR] = 10 ÷ 40. INCLUSO: MOLLA DI LEGA FERROSA ACCIAIO INOX;. LAVORO: POSA. SPECIFICHE TECNICHE: VALVOLA CON: CORPO DI LEGA FERROSA ACCIAIO GALVANIZZATO, DISCO DI LEGA FERROSA ACCIAIO INOX, ANELLO SEDE DI TENUTA VALVOLA DI LEGA FERROSA ACCIAIO INOX. OP VALVOLA DI LEGA FERROSA ACCIAIO GENERICO; GEOMETRIA: A DISCO | TIPO WAFER; FUNZIONE: DI RITEGNO; DIAMETRO NOMINALE (Ø) [MM] = 40; PRESSIONE NOMINALE [BAR] = 10 ÷ 40. INCLUSO: MOLLA DI LEGA FERROSA ACCIAIO INOX;. SPECIFICHE TECNICHE: VALVOLA CON: CORPO DI LEGA FERROSA ACCIAIO GALVANIZZATO, DISCO DI LEGA FERROSA ACCIAIO INOX, ANELLO SEDE DI TENUTA VALVOLA DI LEGA FERROSA ACCIAIO INOX. RM VALVOLA DI LEGA FERROSA ACCIAIO GENERICO; GEOMETRIA: A DISCO | TIPO WAFER; FUNZIONE: DI RITEGNO; DIAMETRO NOMINALE (Ø) [MM] = 40; PRESSIONE NOMINALE [BAR] = 10 ÷ 40. INCLUSO: MOLLA DI LEGA FERROSA ACCIAIO INOX; SPECIFICHE TECNICHE: VALVOLA CON: CORPO DI LEGA FERROSA ACCIAIO GALVANIZZATO, DISCO DI LEGA FERROSA ACCIAIO INOX, ANELLO SEDE DI TENUTA VALVOLA DI LEGA FERROSA ACCIAIO INOX LV POSA. | M255: CAD | N255: 1 | O255: 82.86 | P255: 82.86 | S255: =IF(AND(Q255<>"",R255<>""),Q255*R255,"") | T255: =IF(S255="",P255,S255) | U255: 0 | V255: =$T255*U255 | W255: 0 | X255: =$T255*W255 | Y255: 0 | Z255: =$T255*Y255 | AA255: 0 | AB255: =$T255*AA255 | AC255: 0 | AD255: =$T255*AC255 | AE255: 0 | AF255: =$T255*AE255 | AG255: 0 | AH255: =$T255*AG255 | AI255: =U255+W255+Y255+AA255+AC255+AE255+AG255 | AJ255: =V255+X255+Z255+AB255+AD255+AF255+AH255
A256: DEI_IT_015091A | B256: 1/1 | C256: IMPIANTO MECCANICO | D256: NON SPECIALE | E256: MECCANICHE | F256: 2_CME_TOTALE MECCANICI RADIOFARMACIA PAVIA.PDF | G256: 193/193 | H256: 50 - INSTALLAZIONE | I256: CENTRALE | J256: IMPIANTO IIS E FOGNA | K256: SCALDA ACQUA A POMPA DI CALORE ARIA-ACQUA PER LA PRODUZIONE DI ACQUA CALDA SANITARIA, IN ACCIAIO INOX, PER INSTALLAZIONE A BASAMENTO (CLASSE A+ DI EFFICIENZA ENERGETICA SECONDO ERP), CON COIBENTAZIONE | L256: SCALDA ACQUA A POMPA DI CALORE ARIA-ACQUA PER LA PRODUZIONE DI ACQUA CALDA SANITARIA, IN ACCIAIO INOX, PER INSTALLAZIONE A BASAMENTO (CLASSE A+ DI EFFICIENZA ENERGETICA SECONDO ERP), CON COIBENTAZIONE IN POLIURETANO ESPANSO, ALIMENTAZIONE ELETTRICA 230 V - 50 HZ, POSTO IN OPERA ALLACCIATO ALLA RETE IDRICA CON ESCLUSIONE DEI COLLEGAMENTI ELETTRICI: SENZA SERPENTINO DI INTEGRAZIONE, DELLA CAPACITÀ DI: 200 L | M256: CAD | N256: 1 | O256: 2229.42 | P256: 2229.42 | S256: =IF(AND(Q256<>"",R256<>""),Q256*R256,"") | T256: =IF(S256="",P256,S256) | U256: 0.5 | V256: =$T256*U256 | W256: 0.1 | X256: =$T256*W256 | Y256: 0 | Z256: =$T256*Y256 | AA256: 0 | AB256: =$T256*AA256 | AC256: 0 | AD256: =$T256*AC256 | AE256: 0 | AF256: =$T256*AE256 | AG256: 0 | AH256: =$T256*AG256 | AI256: =U256+W256+Y256+AA256+AC256+AE256+AG256 | AJ256: =V256+X256+Z256+AB256+AD256+AF256+AH256
A257: LOM251.OC.EEA.PA01.I7450.ZA001.0010 | B257: 1/1 | C257: IMPIANTO MECCANICO | D257: SPECIALE | E257: MECCANICHE SPECIALI | F257: 2_CME_TOTALE MECCANICI RADIOFARMACIA PAVIA.PDF | G257: 6/6 | H257: 40 - IMPIANTISTICO | I257: CENTRALE | J257: IMPIANTO HVAC | K257: OPERA: CIRCOLATORE, GEMELLARE; FUNZIONE: DISTRIBUZIONE ACQUA; IMPIEGO: CENTRALE IDRICA; PRESSIONE NOMINALE [BAR] = 6 | PREVALENZA [KPA] = 40,1 ÷ 80 | PORTATA [M³/H] ≤ 4. | L257: OPERA: CIRCOLATORE, GEMELLARE; FUNZIONE: DISTRIBUZIONE ACQUA; IMPIEGO: CENTRALE IDRICA; PRESSIONE NOMINALE [BAR] = 6 | PREVALENZA [KPA] = 40,1 ÷ 80 | PORTATA [M³/H] ≤ 4. LAVORO: INSTALLAZIONE. SPECIFICHE TECNICHE: PRESTAZIONI MISURATE A VELOCITÀ MASSIMA. OP CIRCOLATORE, GEMELLARE; FUNZIONE: DISTRIBUZIONE ACQUA; IMPIEGO: CENTRALE IDRICA; PRESSIONE NOMINALE [BAR] = 6 | PREVALENZA [KPA] = 40,1 ÷ 80 | PORTATA [M³/H] ≤ 4. SPECIFICHE TECNICHE: PRESTAZIONI MISURATE A VELOCITÀ MASSIMA. RM CIRCOLATORE GEMELLARE; FUNZIONE: DISTRIBUZIONE ACQUA; IMPIEGO: CENTRALE IDRICA; PRESSIONE NOMINALE [BAR] = 6 | PREVALENZA [KPA] = 40,1 ÷ 80 | PORTATA [M³/H] ≤ 4. COMPONENTE: MOTORE TRIFASE (3F), SPECIFICHE TECNICHE: PRESTAZIONI MISURATE A VELOCITÀ MASSIMA LV INSTALLAZIONE. | M257: CAD | N257: 1 | O257: 2146.41 | P257: 2146.41 | S257: =IF(AND(Q257<>"",R257<>""),Q257*R257,"") | T257: =IF(S257="",P257,S257) | U257: 0 | V257: =$T257*U257 | W257: 0.7 | X257: =$T257*W257 | Y257: 0 | Z257: =$T257*Y257 | AA257: 0 | AB257: =$T257*AA257 | AC257: 0 | AD257: =$T257*AC257 | AE257: 0 | AF257: =$T257*AE257 | AG257: 0 | AH257: =$T257*AG257 | AI257: =U257+W257+Y257+AA257+AC257+AE257+AG257 | AJ257: =V257+X257+Z257+AB257+AD257+AF257+AH257
A258: LOM251.OC.EEA.PA02.I7407.SB038.0255 | B258: 3/3 | C258: IMPIANTO MECCANICO | D258: SPECIALE | E258: MECCANICHE SPECIALI | F258: 2_CME_TOTALE MECCANICI RADIOFARMACIA PAVIA.PDF | G258: 10/10 | H258: 40 - IMPIANTISTICO | I258: CENTRALE | J258: IMPIANTO HVAC | K258: OPERA: TUBAZIONE DI LEGA FERROSA ACCIAIO NERO; GEOMETRIA: FILETTATO | SERIE LEGGERA; FUNZIONE: DISTRIBUZIONE ACQUA; IMPIEGO: RETE IDRICA; DIAMETRO NOMINALE (Ø) [MM] = 20 | SPESSORE [MM] = 2,3. | L258: OPERA: TUBAZIONE DI LEGA FERROSA ACCIAIO NERO; GEOMETRIA: FILETTATO | SERIE LEGGERA; FUNZIONE: DISTRIBUZIONE ACQUA; IMPIEGO: RETE IDRICA; DIAMETRO NOMINALE (Ø) [MM] = 20 | SPESSORE [MM] = 2,3. LAVORO: POSA. SPECIFICHE TECNICHE: TUBO SENZA SALDATURA. OP TUBAZIONE DI LEGA FERROSA ACCIAIO NERO; GEOMETRIA: FILETTATO | SERIE LEGGERA; FUNZIONE: DISTRIBUZIONE ACQUA; IMPIEGO: RETE IDRICA; DIAMETRO NOMINALE (Ø) [MM] = 20 | SPESSORE [MM] = 2,3. SPECIFICHE TECNICHE: TUBO SENZA SALDATURA. RM TUBO DI LEGA FERROSA ACCIAIO NERO; GEOMETRIA: FILETTATO | SERIE LEGGERA; FUNZIONE: DISTRIBUZIONE ACQUA; IMPIEGO: RETE IDRICA; DIAMETRO NOMINALE (Ø) [MM] = 20 | SPESSORE [MM] = 2,3 SPECIFICHE TECNICHE: TUBO SENZA SALDATURA LV POSA. | M258: M | N258: 45 | O258: 24.52 | P258: 1103.4 | S258: =IF(AND(Q258<>"",R258<>""),Q258*R258,"") | T258: =IF(S258="",P258,S258) | U258: 0 | V258: =$T258*U258 | W258: 0.25 | X258: =$T258*W258 | Y258: 0 | Z258: =$T258*Y258 | AA258: 0 | AB258: =$T258*AA258 | AC258: 0 | AD258: =$T258*AC258 | AE258: 0 | AF258: =$T258*AE258 | AG258: 0 | AH258: =$T258*AG258 | AI258: =U258+W258+Y258+AA258+AC258+AE258+AG258 | AJ258: =V258+X258+Z258+AB258+AD258+AF258+AH258
A259: LOM251.OC.EEA.PA02.I7407.SB038.0295 | B259: 2/2 | C259: IMPIANTO MECCANICO | D259: SPECIALE | E259: MECCANICHE SPECIALI | F259: 2_CME_TOTALE MECCANICI RADIOFARMACIA PAVIA.PDF | G259: 11/11 | H259: 40 - IMPIANTISTICO | I259: CENTRALE | J259: IMPIANTO HVAC | K259: OPERA: TUBAZIONE DI LEGA FERROSA ACCIAIO NERO; FUNZIONE: DISTRIBUZIONE ACQUA; IMPIEGO: RETE IDRICA; DIAMETRO NOMINALE (Ø) [MM] = 25 | SPESSORE [MM] = 2,3. | L259: OPERA: TUBAZIONE DI LEGA FERROSA ACCIAIO NERO; FUNZIONE: DISTRIBUZIONE ACQUA; IMPIEGO: RETE IDRICA; DIAMETRO NOMINALE (Ø) [MM] = 25 | SPESSORE [MM] = 2,3. LAVORO: POSA. SPECIFICHE TECNICHE: TUBO SENZA SALDATURA. OP TUBAZIONE DI LEGA FERROSA ACCIAIO NERO; FUNZIONE: DISTRIBUZIONE ACQUA; IMPIEGO: RETE IDRICA; DIAMETRO NOMINALE (Ø) [MM] = 25 | SPESSORE [MM] = 2,3. SPECIFICHE TECNICHE: TUBO SENZA SALDATURA. RM TUBO DI LEGA FERROSA ACCIAIO NERO; FUNZIONE: DISTRIBUZIONE ACQUA; IMPIEGO: RETE IDRICA; DIAMETRO NOMINALE (Ø) [MM] = 25 | SPESSORE [MM] = 2,3 SPECIFICHE TECNICHE: TUBO SENZA SALDATURA LV POSA. | M259: M | N259: 15 | O259: 27.97 | P259: 419.55 | S259: =IF(AND(Q259<>"",R259<>""),Q259*R259,"") | T259: =IF(S259="",P259,S259) | U259: 0 | V259: =$T259*U259 | W259: 0.25 | X259: =$T259*W259 | Y259: 0 | Z259: =$T259*Y259 | AA259: 0 | AB259: =$T259*AA259 | AC259: 0 | AD259: =$T259*AC259 | AE259: 0 | AF259: =$T259*AE259 | AG259: 0 | AH259: =$T259*AG259 | AI259: =U259+W259+Y259+AA259+AC259+AE259+AG259 | AJ259: =V259+X259+Z259+AB259+AD259+AF259+AH259
A260: LOM251.OC.EEA.PA02.I7407.SB038.0300 | B260: 1/1 | C260: IMPIANTO MECCANICO | D260: SPECIALE | E260: MECCANICHE SPECIALI | F260: 2_CME_TOTALE MECCANICI RADIOFARMACIA PAVIA.PDF | G260: 12/12 | H260: 40 - IMPIANTISTICO | I260: CENTRALE | J260: IMPIANTO HVAC | K260: OPERA: TUBAZIONE DI LEGA FERROSA ACCIAIO NERO; FUNZIONE: DISTRIBUZIONE ACQUA; IMPIEGO: RETE IDRICA; DIAMETRO NOMINALE (Ø) [MM] = 32 | SPESSORE [MM] = 2,6. | L260: OPERA: TUBAZIONE DI LEGA FERROSA ACCIAIO NERO; FUNZIONE: DISTRIBUZIONE ACQUA; IMPIEGO: RETE IDRICA; DIAMETRO NOMINALE (Ø) [MM] = 32 | SPESSORE [MM] = 2,6. LAVORO: POSA. SPECIFICHE TECNICHE: TUBO SENZA SALDATURA. OP TUBAZIONE DI LEGA FERROSA ACCIAIO NERO; FUNZIONE: DISTRIBUZIONE ACQUA; IMPIEGO: RETE IDRICA; DIAMETRO NOMINALE (Ø) [MM] = 32 | SPESSORE [MM] = 2,6. SPECIFICHE TECNICHE: TUBO SENZA SALDATURA. RM TUBO DI LEGA FERROSA ACCIAIO NERO; FUNZIONE: DISTRIBUZIONE ACQUA; IMPIEGO: RETE IDRICA; DIAMETRO NOMINALE (Ø) [MM] = 32 | SPESSORE [MM] = 2,6 SPECIFICHE TECNICHE: TUBO SENZA SALDATURA LV POSA. | M260: M | N260: 50 | O260: 31.42 | P260: 1571 | S260: =IF(AND(Q260<>"",R260<>""),Q260*R260,"") | T260: =IF(S260="",P260,S260) | U260: 0 | V260: =$T260*U260 | W260: 0.25 | X260: =$T260*W260 | Y260: 0 | Z260: =$T260*Y260 | AA260: 0 | AB260: =$T260*AA260 | AC260: 0 | AD260: =$T260*AC260 | AE260: 0 | AF260: =$T260*AE260 | AG260: 0 | AH260: =$T260*AG260 | AI260: =U260+W260+Y260+AA260+AC260+AE260+AG260 | AJ260: =V260+X260+Z260+AB260+AD260+AF260+AH260
... A608: IE_NP_UPS | B608: 1/1 | C608: IMPIANTO ELETTRICO | D608: SPECIALE | E608: ELETTRICHE SPECIALI | F608: 3_CME IE RADIOFARMACIA PAVIA - REV02 VARIANTE ESECUTIVA.PDF | G608: 21/21 | H608: 50 - INSTALLAZIONE | I608: CABINA BT | J608: QUADRI ELETTRICI BT E UPS | K608: GRUPPO STATICO DI CONTINUITÀ MODULARE TRIFASE/TRIFASE ON-LINE A DOPPIA CONVERSIONE AD ALTO RENDIMENTO COMPOSTO DA: INVOLUCRO PREDISPOSTO PER ALLOGGIAMENTO DEI MODULI, MODULI DI POTENZA 50KVA, BYPASS S | L608: GRUPPO STATICO DI CONTINUITÀ MODULARE TRIFASE/TRIFASE ON-LINE A DOPPIA CONVERSIONE AD ALTO RENDIMENTO COMPOSTO DA: INVOLUCRO PREDISPOSTO PER ALLOGGIAMENTO DEI MODULI, MODULI DI POTENZA 50KVA, BYPASS STATICO IBRIDO E BYPASS MANUALE DI MANUTENZIONE DI PIENA POTENZA E AVENTE LE SEGUENTI CARATTERISTICHE: TENSIONE DI INGRESSO NOMINALE RADDRIZZATORE: 400 V TRIFASE CON NEUTRO (-15/+20%). FREQUENZA NOMINALE INGRESSO 50/60HZ (± 10%). TENSIONE DI INGRESSO NOMINALE BYPASS: 400 V TRIFASE CON NEUTRO (± 15%). FATTORE DI POTENZA IN INGRESSO > 0,99 AL 100% DELLA POTENZA NOMINALE, THDI A MONTE < 3% ALLA PN. POTENZA ATTIVA NOMINALE A PF1 (KVA=KW). PRESTAZIONI VERIFICATE DA UN ORGANISMO INDIPENDENTE ACCREDITATO. TENSIONE DI USCITA NOMINALE SELEZIONABILE: 380/400/415 V TRIFASE CON NEUTRO. THDU IN USCITA SU CARICO LINEARE: < 1% . THDU IN USCITA SU CARICO NON LINEARE CONFORME A VFI-SS-111. SOVRACCARICO DA INVERTER AMMESSO: 150% PER 1 MIN E 125% PER 10 MIN. FREQUENZA DI USCITA: 50 HZ / 60 HZ +/-0,1%. RENDIMENTO IN MODALITÀ ON-LINE (DOPPIA CONVERSIONE) PARI A 96,5%. RENDIMENTO IN MODALITÀ ECO-MODE PARI A 99,3%. EFFICIENZA VERIFICATA E CERTIFICATA DA UN ORGANISMO INDIPENDENTE ACCREDITATO. POSSIBILITÀ DI ALIMENTAZIONE DA GRUPPO ELETTROGENO CON AVVIAMENTO A RAMPA (POWER WALK-IN) CONFIGURABILE IN TEMPO E AMPIEZZA. I MODULI DI POTENZA CON MTBF MAGGIORE DI 1.000.000 ORE IN CONFORMITÀ CON LA NORMA IEC/EN62830 CALCOLATO E VERIFICATO DA UN ORGANISMO INDIPENDENTE ACCREDITATO. MODULO DI POTENZA IN UN INVOLUCRO MECCANICAMENTE SEGREGATO ED INDIPENDENTE CONTENENTE: RADDRIZZATORE, INVERTER, CONTROLLORE, ALIMENTAZIONE, CARICABATTERIA E SEGNALAZIONE LUMINOSA DI STATO PER GARANTIRE LA COMPLETA AUTOSUFFICIENZA DEI MODULI. MODULI CON ESTRAIBILITÀ A CALDO CON IL SISTEMA IN MODALITÀ “ON-LINE DOPPIA CONVERSIONE” SENZA RICHIEDERE LO SPEGNIMENTO MANUALE DEL MODULO, LA COMMUTAZIONE IN MODALITÀ DI BYPASS O PASSAGGIO SU BYPASS MANUALE. MODULI IN GRADO DI AGGIORNARE IL FIRMWARE SENZA ALCUN INTERVENTO DELL’ OPERATORE E SENZA PERTURBARE LO STATO DELL’ UPS IN CASO DI INSERIMENTO A CALDO IN UN SISTEMA IN ESERCIZIO. CIRCUITO DI RILEVAZIONE DEL RITORNO DI ENERGIA VERSO RETE (BACKFEED) E SEGNALE DI COMANDO PER BOBINA ESTERNA INCLUSO. COMPONENTE DI BYPASS STATICO DI SISTEMA ESTRAIBILE A CALDO CON IL SISTEMA FUNZIONANTE IN MODALITÀ “ON-LINE DOPPIA CONVERSIONE” SENZA RICHIEDERE LO SPEGNIMENTO DEL SISTEMA O LA COMMUTAZIONE SU BYPASS MANUALE. UPS IN GRADO DI FUNZIONARE CON I SEGUENTI TIPI DI ACCUMULATORI: AL PIOMBO ERMETICO (VRLA) / PIOMBO A VASO APERTO / NICD / IONI DI LITIO. L'INTERFACCIA UTENTE DELL'UPS DEVE ESSERE COSTITUITA DA UN DISPLAY GRAFICO A COLORI TOUCH-SCREEN. UPS COMPLETO DI SCHEDA CONTATTI AUSILIARI LIBERI DA POTENZIALE CON PORTA DI COMUNICAZIONE SERIALE RS485 OPTOISOLATA (ADC) E CONTATTO DI SPEGNIMENTO E.P.O. SOLUZIONE COMPLETA DI SCHEDA DI COMUNICAZIONE ETHERNET IOT READY (NETVISION) CON COLLEGAMENTO ETHERNET CON I SEGUENTI PROTOCOLLI DI COMUNICAZIONE: SNMP V1 / V3, MODBUS SU TCP/IP, HTTP, SMTP, PROFIBUS, PROFINET. SCHEDA IN GRADO DI COLLEGARE L’ UPS AD UN CLOUD REMOTO PER GESTIONE NOTIFICHE TRAMITE APP (SOLIVE) PER DISPOSITIVI MOBILI. GRADO DI PROTEZIONE IP 20; COLORE RAL7016. CONFORMITÀ ALLE NORME EN62040-1, EN62040-2, EN62040-3. IL COSTRUTTORE DELLE APPARECCHIATURE DEVE ESSERE CERTIFICATO ISO9001 E ISO14001 E DEVE POTER FORNIRE UN CERTIFICATO DI ORIGINE DICHIARANTE CHE L'UPS È STATO PROGETTATO, PRODOTTO E TESTATO ALL'INTERNO DELLA COMUNITÀ EUROPEA. DIMENSIONI INDICATIVE UPS (LXPXH): 600X890X1990 MM. PRIMA ACCENSIONE DELLA MACCHINA DA PARTE DI TECNICO SPECIALIZZATO DEL COSTRUTTORE. L'OPERA S'INTENDE COMPRENSIVA DI OGNI ONERE ANNESSO E CONNESSO PER RENDERLA PERFETTAMENTE FUNZIONANTE E REALIZZATA A REGOLA D'ARTE. UPS CON MODULI DI POTENZA PER 250 KVA TIPO SOCOMEC MODULYS XM 300KVA O EQUIVALENTE; AUTONOMIA 13 MIN. CON CARICO APPLICATO PARI A 200 KW - SISTEMA RIDONDANTE N+1 (200KW + 50KW DI RIDONDANZA) INCLUSO ARMADIO BATTERIE MONOLITICO AVENTE LE SEGUENTI CARATTERISTICHE: ARMADIO CON GRADO DI PROTEZIONE IP 20 ADATTO AD ALLOGGIARE BATTERIE AGM-VRLA CON VITA ATTESA 10 ANNI (TIPOLOGIA LONG LIFE (LL) SECONDO EUROBAT). IDONEO ALL' INSTALLAZIONE INDOOR IN AMBIENTI PRIVO DI POLVERI CONDUTTORI, INFIAMMABILI, ESPLOSIVI O CORROSIVI E CON LIVELLO DI INQUINAMENTO INFERIORE AL GRADO 2 SECONDO NORMA IEC 60664-1. L'ARMADIO BATTERIE DEVE ESSERE COMPATIBILE CON UPS EQUIPAGGIATI CON CARICA BATTERIE CON FUNZIONAMENTO A 3 FILI CON NEUTRO CENTRALE (A+/N/A-). ARMADIO COMPLETO DI PROTEZIONE (SEZIONATORE A FUSIBILI O INTERRUTTORE MAGNETOTERMICO) E COMPLETO DEGLI ACCESSORI PER LA CONNESSIONE TRA MONOBLOCCHI E PROTEZIONE. MASSIMA POTENZA IN SCARICA 125KW/ARMADIO. ALMENO UN ARMADIO OGNI 5 MODULI DI POTENZA. COLLEGAMENTO CAVI DAL BASSO FRONTALMENTE. GRADO DI PROTEZIONE IP 20; COLORE RAL7012.SOLUZIONE IN SINGOLO ARMADIO CON BATTERIE PRE-ASSEMBLATE PRIMA DELL' INVIO. CAVI DI CONNESSIONE CON L' UPS FORNITI DI SERIE PER INSTALLAZIONE AFFIANCATA.DIMENSIONI INDICATIVE ARMADIO BATTERIE (LXPXH): 810X890X1990 MM. PRIMA ACCENSIONE DELLA MACCHINA DA PARTE DI TECNICO SPECIALIZZATO DEL COSTRUTTORE. L'OPERA S'INTENDE COMPRENSIVA DI OGNI ONERE ANNESSO E CONNESSO PER RENDERLA PERFETTAMENTE FUNZIONANTE E REALIZZATA A REGOLA D'ARTE. ARMADIO BATTERIE TIPO SOCOMEC O EQUIVALENTE. N.2 ARMADI BATTERIE | M608: A CORPO | N608: 1 | O608: 65696.73 | P608: 65696.73 | S608: =IF(AND(Q608<>"",R608<>""),Q608*R608,"") | T608: =IF(S608="",P608,S608) | U608: 0.5 | V608: =$T608*U608 | W608: 0.1 | X608: =$T608*W608 | Y608: 0 | Z608: =$T608*Y608 | AA608: 0 | AB608: =$T608*AA608 | AC608: 0 | AD608: =$T608*AC608 | AE608: 0 | AF608: =$T608*AE608 | AG608: 0 | AH608: =$T608*AG608 | AI608: =U608+W608+Y608+AA608+AC608+AE608+AG608 | AJ608: =V608+X608+Z608+AB608+AD608+AF608+AH608

Sheet EDILI
B2: DETTAGLIO SAL — OPERE EDILI
B3: Nr.Ord. | C3: TARIFFA | D3: DESIGNAZIONE | E3: STEP | F3: U.M. | G3: Q.tà PREV | H3: VAL.UNIT PREV | I3: TOTALE PREV | J3: Q.tà CONS | K3: VAL.UNIT CONS | L3: TOTALE CONS | M3: VALORE PER SAL | O3: SAL 01 APRILE | Q3: SAL 02 MAGGIO | S3: SAL 03 GIUGNO | U3: SAL 04 LUGLIO | W3: SAL 05 AGOSTO | Y3: SAL 06 SETTEMBRE | AA3: SAL 07 OTTOBRE | AC3: TOTALE COMPL.
O4: % | P4: TOTALE | Q4: % | R4: TOTALE | S4: % | T4: TOTALE | U4: % | V4: TOTALE | W4: % | X4: TOTALE | Y4: % | Z4: TOTALE | AA4: % | AB4: TOTALE | AC4: % | AD4: TOTALE
B5: =LAVORAZIONI!G4 | C5: =LAVORAZIONI!A4 | D5: =LAVORAZIONI!K4 | E5: =LAVORAZIONI!H4 | F5: =LAVORAZIONI!M4 | G5: =LAVORAZIONI!N4 | H5: =LAVORAZIONI!O4 | I5: =LAVORAZIONI!P4 | J5: =IF(LAVORAZIONI!Q4="","",LAVORAZIONI!Q4) | K5: =IF(LAVORAZIONI!R4="","",LAVORAZIONI!R4) | L5: =IF(LAVORAZIONI!S4="","",LAVORAZIONI!S4) | M5: =LAVORAZIONI!T4 | O5: =LAVORAZIONI!U4 | P5: =LAVORAZIONI!V4 | Q5: =LAVORAZIONI!W4 | R5: =LAVORAZIONI!X4 | S5: =LAVORAZIONI!Y4 | T5: =LAVORAZIONI!Z4 | U5: =LAVORAZIONI!AA4 | V5: =LAVORAZIONI!AB4 | ... AD5: =LAVORAZIONI!AJ4
B6: =LAVORAZIONI!G5 | C6: =LAVORAZIONI!A5 | D6: =LAVORAZIONI!K5 | E6: =LAVORAZIONI!H5 | F6: =LAVORAZIONI!M5 | G6: =LAVORAZIONI!N5 | H6: =LAVORAZIONI!O5 | I6: =LAVORAZIONI!P5 | J6: =IF(LAVORAZIONI!Q5="","",LAVORAZIONI!Q5) | K6: =IF(LAVORAZIONI!R5="","",LAVORAZIONI!R5) | L6: =IF(LAVORAZIONI!S5="","",LAVORAZIONI!S5) | M6: =LAVORAZIONI!T5 | O6: =LAVORAZIONI!U5 | P6: =LAVORAZIONI!V5 | Q6: =LAVORAZIONI!W5 | R6: =LAVORAZIONI!X5 | S6: =LAVORAZIONI!Y5 | T6: =LAVORAZIONI!Z5 | U6: =LAVORAZIONI!AA5 | V6: =LAVORAZIONI!AB5 | ... AD6: =LAVORAZIONI!AJ5
B7: =LAVORAZIONI!G6 | C7: =LAVORAZIONI!A6 | D7: =LAVORAZIONI!K6 | E7: =LAVORAZIONI!H6 | F7: =LAVORAZIONI!M6 | G7: =LAVORAZIONI!N6 | H7: =LAVORAZIONI!O6 | I7: =LAVORAZIONI!P6 | J7: =IF(LAVORAZIONI!Q6="","",LAVORAZIONI!Q6) | K7: =IF(LAVORAZIONI!R6="","",LAVORAZIONI!R6) | L7: =IF(LAVORAZIONI!S6="","",LAVORAZIONI!S6) | M7: =LAVORAZIONI!T6 | O7: =LAVORAZIONI!U6 | P7: =LAVORAZIONI!V6 | Q7: =LAVORAZIONI!W6 | R7: =LAVORAZIONI!X6 | S7: =LAVORAZIONI!Y6 | T7: =LAVORAZIONI!Z6 | U7: =LAVORAZIONI!AA6 | V7: =LAVORAZIONI!AB6 | ... AD7: =LAVORAZIONI!AJ6
B8: =LAVORAZIONI!G7 | C8: =LAVORAZIONI!A7 | D8: =LAVORAZIONI!K7 | E8: =LAVORAZIONI!H7 | F8: =LAVORAZIONI!M7 | G8: =LAVORAZIONI!N7 | H8: =LAVORAZIONI!O7 | I8: =LAVORAZIONI!P7 | J8: =IF(LAVORAZIONI!Q7="","",LAVORAZIONI!Q7) | K8: =IF(LAVORAZIONI!R7="","",LAVORAZIONI!R7) | L8: =IF(LAVORAZIONI!S7="","",LAVORAZIONI!S7) | M8: =LAVORAZIONI!T7 | O8: =LAVORAZIONI!U7 | P8: =LAVORAZIONI!V7 | Q8: =LAVORAZIONI!W7 | R8: =LAVORAZIONI!X7 | S8: =LAVORAZIONI!Y7 | T8: =LAVORAZIONI!Z7 | U8: =LAVORAZIONI!AA7 | V8: =LAVORAZIONI!AB7 | ... AD8: =LAVORAZIONI!AJ7
B9: =LAVORAZIONI!G8 | C9: =LAVORAZIONI!A8 | D9: =LAVORAZIONI!K8 | E9: =LAVORAZIONI!H8 | F9: =LAVORAZIONI!M8 | G9: =LAVORAZIONI!N8 | H9: =LAVORAZIONI!O8 | I9: =LAVORAZIONI!P8 | J9: =IF(LAVORAZIONI!Q8="","",LAVORAZIONI!Q8) | K9: =IF(LAVORAZIONI!R8="","",LAVORAZIONI!R8) | L9: =IF(LAVORAZIONI!S8="","",LAVORAZIONI!S8) | M9: =LAVORAZIONI!T8 | O9: =LAVORAZIONI!U8 | P9: =LAVORAZIONI!V8 | Q9: =LAVORAZIONI!W8 | R9: =LAVORAZIONI!X8 | S9: =LAVORAZIONI!Y8 | T9: =LAVORAZIONI!Z8 | U9: =LAVORAZIONI!AA8 | V9: =LAVORAZIONI!AB8 | ... AD9: =LAVORAZIONI!AJ8
B10: =LAVORAZIONI!G9 | C10: =LAVORAZIONI!A9 | D10: =LAVORAZIONI!K9 | E10: =LAVORAZIONI!H9 | F10: =LAVORAZIONI!M9 | G10: =LAVORAZIONI!N9 | H10: =LAVORAZIONI!O9 | I10: =LAVORAZIONI!P9 | J10: =IF(LAVORAZIONI!Q9="","",LAVORAZIONI!Q9) | K10: =IF(LAVORAZIONI!R9="","",LAVORAZIONI!R9) | L10: =IF(LAVORAZIONI!S9="","",LAVORAZIONI!S9) | M10: =LAVORAZIONI!T9 | O10: =LAVORAZIONI!U9 | P10: =LAVORAZIONI!V9 | Q10: =LAVORAZIONI!W9 | R10: =LAVORAZIONI!X9 | S10: =LAVORAZIONI!Y9 | T10: =LAVORAZIONI!Z9 | U10: =LAVORAZIONI!AA9 | V10: =LAVORAZIONI!AB9 | ... AD10: =LAVORAZIONI!AJ9
B11: =LAVORAZIONI!G10 | C11: =LAVORAZIONI!A10 | D11: =LAVORAZIONI!K10 | E11: =LAVORAZIONI!H10 | F11: =LAVORAZIONI!M10 | G11: =LAVORAZIONI!N10 | H11: =LAVORAZIONI!O10 | I11: =LAVORAZIONI!P10 | J11: =IF(LAVORAZIONI!Q10="","",LAVORAZIONI!Q10) | K11: =IF(LAVORAZIONI!R10="","",LAVORAZIONI!R10) | L11: =IF(LAVORAZIONI!S10="","",LAVORAZIONI!S10) | M11: =LAVORAZIONI!T10 | O11: =LAVORAZIONI!U10 | P11: =LAVORAZIONI!V10 | Q11: =LAVORAZIONI!W10 | R11: =LAVORAZIONI!X10 | S11: =LAVORAZIONI!Y10 | T11: =LAVORAZIONI!Z10 | U11: =LAVORAZIONI!AA10 | V11: =LAVORAZIONI!AB10 | ... AD11: =LAVORAZIONI!AJ10
B12: =LAVORAZIONI!G11 | C12: =LAVORAZIONI!A11 | D12: =LAVORAZIONI!K11 | E12: =LAVORAZIONI!H11 | F12: =LAVORAZIONI!M11 | G12: =LAVORAZIONI!N11 | H12: =LAVORAZIONI!O11 | I12: =LAVORAZIONI!P11 | J12: =IF(LAVORAZIONI!Q11="","",LAVORAZIONI!Q11) | K12: =IF(LAVORAZIONI!R11="","",LAVORAZIONI!R11) | L12: =IF(LAVORAZIONI!S11="","",LAVORAZIONI!S11) | M12: =LAVORAZIONI!T11 | O12: =LAVORAZIONI!U11 | P12: =LAVORAZIONI!V11 | Q12: =LAVORAZIONI!W11 | R12: =LAVORAZIONI!X11 | S12: =LAVORAZIONI!Y11 | T12: =LAVORAZIONI!Z11 | U12: =LAVORAZIONI!AA11 | V12: =LAVORAZIONI!AB11 | ... AD12: =LAVORAZIONI!AJ11
B13: =LAVORAZIONI!G12 | C13: =LAVORAZIONI!A12 | D13: =LAVORAZIONI!K12 | E13: =LAVORAZIONI!H12 | F13: =LAVORAZIONI!M12 | G13: =LAVORAZIONI!N12 | H13: =LAVORAZIONI!O12 | I13: =LAVORAZIONI!P12 | J13: =IF(LAVORAZIONI!Q12="","",LAVORAZIONI!Q12) | K13: =IF(LAVORAZIONI!R12="","",LAVORAZIONI!R12) | L13: =IF(LAVORAZIONI!S12="","",LAVORAZIONI!S12) | M13: =LAVORAZIONI!T12 | O13: =LAVORAZIONI!U12 | P13: =LAVORAZIONI!V12 | Q13: =LAVORAZIONI!W12 | R13: =LAVORAZIONI!X12 | S13: =LAVORAZIONI!Y12 | T13: =LAVORAZIONI!Z12 | U13: =LAVORAZIONI!AA12 | V13: =LAVORAZIONI!AB12 | ... AD13: =LAVORAZIONI!AJ12
B14: =LAVORAZIONI!G13 | C14: =LAVORAZIONI!A13 | D14: =LAVORAZIONI!K13 | E14: =LAVORAZIONI!H13 | F14: =LAVORAZIONI!M13 | G14: =LAVORAZIONI!N13 | H14: =LAVORAZIONI!O13 | I14: =LAVORAZIONI!P13 | J14: =IF(LAVORAZIONI!Q13="","",LAVORAZIONI!Q13) | K14: =IF(LAVORAZIONI!R13="","",LAVORAZIONI!R13) | L14: =IF(LAVORAZIONI!S13="","",LAVORAZIONI!S13) | M14: =LAVORAZIONI!T13 | O14: =LAVORAZIONI!U13 | P14: =LAVORAZIONI!V13 | Q14: =LAVORAZIONI!W13 | R14: =LAVORAZIONI!X13 | S14: =LAVORAZIONI!Y13 | T14: =LAVORAZIONI!Z13 | U14: =LAVORAZIONI!AA13 | V14: =LAVORAZIONI!AB13 | ... AD14: =LAVORAZIONI!AJ13
B15: =LAVORAZIONI!G14 | C15: =LAVORAZIONI!A14 | D15: =LAVORAZIONI!K14 | E15: =LAVORAZIONI!H14 | F15: =LAVORAZIONI!M14 | G15: =LAVORAZIONI!N14 | H15: =LAVORAZIONI!O14 | I15: =LAVORAZIONI!P14 | J15: =IF(LAVORAZIONI!Q14="","",LAVORAZIONI!Q14) | K15: =IF(LAVORAZIONI!R14="","",LAVORAZIONI!R14) | L15: =IF(LAVORAZIONI!S14="","",LAVORAZIONI!S14) | M15: =LAVORAZIONI!T14 | O15: =LAVORAZIONI!U14 | P15: =LAVORAZIONI!V14 | Q15: =LAVORAZIONI!W14 | R15: =LAVORAZIONI!X14 | S15: =LAVORAZIONI!Y14 | T15: =LAVORAZIONI!Z14 | U15: =LAVORAZIONI!AA14 | V15: =LAVORAZIONI!AB14 | ... AD15: =LAVORAZIONI!AJ14
B16: =LAVORAZIONI!G15 | C16: =LAVORAZIONI!A15 | D16: =LAVORAZIONI!K15 | E16: =LAVORAZIONI!H15 | F16: =LAVORAZIONI!M15 | G16: =LAVORAZIONI!N15 | H16: =LAVORAZIONI!O15 | I16: =LAVORAZIONI!P15 | J16: =IF(LAVORAZIONI!Q15="","",LAVORAZIONI!Q15) | K16: =IF(LAVORAZIONI!R15="","",LAVORAZIONI!R15) | L16: =IF(LAVORAZIONI!S15="","",LAVORAZIONI!S15) | M16: =LAVORAZIONI!T15 | O16: =LAVORAZIONI!U15 | P16: =LAVORAZIONI!V15 | Q16: =LAVORAZIONI!W15 | R16: =LAVORAZIONI!X15 | S16: =LAVORAZIONI!Y15 | T16: =LAVORAZIONI!Z15 | U16: =LAVORAZIONI!AA15 | V16: =LAVORAZIONI!AB15 | ... AD16: =LAVORAZIONI!AJ15
... B125: =LAVORAZIONI!G124 | C125: =LAVORAZIONI!A124 | D125: =LAVORAZIONI!K124 | E125: =LAVORAZIONI!H124 | F125: =LAVORAZIONI!M124 | G125: =LAVORAZIONI!N124 | H125: =LAVORAZIONI!O124 | I125: =LAVORAZIONI!P124 | J125: =IF(LAVORAZIONI!Q124="","",LAVORAZIONI!Q124) | K125: =IF(LAVORAZIONI!R124="","",LAVORAZIONI!R124) | L125: =IF(LAVORAZIONI!S124="","",LAVORAZIONI!S124) | M125: =LAVORAZIONI!T124 | O125: =LAVORAZIONI!U124 | P125: =LAVORAZIONI!V124 | Q125: =LAVORAZIONI!W124 | R125: =LAVORAZIONI!X124 | S125: =LAVORAZIONI!Y124 | T125: =LAVORAZIONI!Z124 | U125: =LAVORAZIONI!AA124 | V125: =LAVORAZIONI!AB124 | ... AD125: =LAVORAZIONI!AJ124
D126: TOTALE EDILI | I126: =SUM(I5:I125) | L126: =SUM(L5:L125) | M126: =SUM(M5:M125) | P126: =SUM(P5:P125) | R126: =SUM(R5:R125) | T126: =SUM(T5:T125) | V126: =SUM(V5:V125) | X126: =SUM(X5:X125) | Z126: =SUM(Z5:Z125) | AB126: =SUM(AB5:AB125) | AD126: =SUM(AD5:AD125)

Sheet EDILI SPECIALI
B1: DETTAGLIO SAL — EDILI SPECIALI
B2: Nr.Ord. | C2: TARIFFA | D2: DESIGNAZIONE | E2: STEP | F2: U.M. | G2: Q.tà PREV | H2: VAL.UNIT PREV | I2: TOTALE PREV | J2: Q.tà CONS | K2: VAL.UNIT CONS | L2: TOTALE CONS | M2: VALORE PER SAL | O2: SAL 01 APRILE | Q2: SAL 02 MAGGIO | S2: SAL 03 GIUGNO | U2: SAL 04 LUGLIO | W2: SAL 05 AGOSTO | Y2: SAL 06 SETTEMBRE | AA2: SAL 07 OTTOBRE | AC2: TOTALE COMPL.
O3: % | P3: TOTALE | Q3: % | R3: TOTALE | S3: % | T3: TOTALE | U3: % | V3: TOTALE | W3: % | X3: TOTALE | Y3: % | Z3: TOTALE | AA3: % | AB3: TOTALE | AC3: % | AD3: TOTALE
B4: =LAVORAZIONI!G125 | C4: =LAVORAZIONI!A125 | D4: =LAVORAZIONI!K125 | E4: =LAVORAZIONI!H125 | F4: =LAVORAZIONI!M125 | G4: =LAVORAZIONI!N125 | H4: =LAVORAZIONI!O125 | I4: =LAVORAZIONI!P125 | J4: =IF(LAVORAZIONI!Q125="","",LAVORAZIONI!Q125) | K4: =IF(LAVORAZIONI!R125="","",LAVORAZIONI!R125) | L4: =IF(LAVORAZIONI!S125="","",LAVORAZIONI!S125) | M4: =LAVORAZIONI!T125 | O4: =LAVORAZIONI!U125 | P4: =LAVORAZIONI!V125 | Q4: =LAVORAZIONI!W125 | R4: =LAVORAZIONI!X125 | S4: =LAVORAZIONI!Y125 | T4: =LAVORAZIONI!Z125 | U4: =LAVORAZIONI!AA125 | V4: =LAVORAZIONI!AB125 | ... AD4: =LAVORAZIONI!AJ125
B5: =LAVORAZIONI!G126 | C5: =LAVORAZIONI!A126 | D5: =LAVORAZIONI!K126 | E5: =LAVORAZIONI!H126 | F5: =LAVORAZIONI!M126 | G5: =LAVORAZIONI!N126 | H5: =LAVORAZIONI!O126 | I5: =LAVORAZIONI!P126 | J5: =IF(LAVORAZIONI!Q126="","",LAVORAZIONI!Q126) | K5: =IF(LAVORAZIONI!R126="","",LAVORAZIONI!R126) | L5: =IF(LAVORAZIONI!S126="","",LAVORAZIONI!S126) | M5: =LAVORAZIONI!T126 | O5: =LAVORAZIONI!U126 | P5: =LAVORAZIONI!V126 | Q5: =LAVORAZIONI!W126 | R5: =LAVORAZIONI!X126 | S5: =LAVORAZIONI!Y126 | T5: =LAVORAZIONI!Z126 | U5: =LAVORAZIONI!AA126 | V5: =LAVORAZIONI!AB126 | ... AD5: =LAVORAZIONI!AJ126
B6: =LAVORAZIONI!G127 | C6: =LAVORAZIONI!A127 | D6: =LAVORAZIONI!K127 | E6: =LAVORAZIONI!H127 | F6: =LAVORAZIONI!M127 | G6: =LAVORAZIONI!N127 | H6: =LAVORAZIONI!O127 | I6: =LAVORAZIONI!P127 | J6: =IF(LAVORAZIONI!Q127="","",LAVORAZIONI!Q127) | K6: =IF(LAVORAZIONI!R127="","",LAVORAZIONI!R127) | L6: =IF(LAVORAZIONI!S127="","",LAVORAZIONI!S127) | M6: =LAVORAZIONI!T127 | O6: =LAVORAZIONI!U127 | P6: =LAVORAZIONI!V127 | Q6: =LAVORAZIONI!W127 | R6: =LAVORAZIONI!X127 | S6: =LAVORAZIONI!Y127 | T6: =LAVORAZIONI!Z127 | U6: =LAVORAZIONI!AA127 | V6: =LAVORAZIONI!AB127 | ... AD6: =LAVORAZIONI!AJ127
B7: =LAVORAZIONI!G128 | C7: =LAVORAZIONI!A128 | D7: =LAVORAZIONI!K128 | E7: =LAVORAZIONI!H128 | F7: =LAVORAZIONI!M128 | G7: =LAVORAZIONI!N128 | H7: =LAVORAZIONI!O128 | I7: =LAVORAZIONI!P128 | J7: =IF(LAVORAZIONI!Q128="","",LAVORAZIONI!Q128) | K7: =IF(LAVORAZIONI!R128="","",LAVORAZIONI!R128) | L7: =IF(LAVORAZIONI!S128="","",LAVORAZIONI!S128) | M7: =LAVORAZIONI!T128 | O7: =LAVORAZIONI!U128 | P7: =LAVORAZIONI!V128 | Q7: =LAVORAZIONI!W128 | R7: =LAVORAZIONI!X128 | S7: =LAVORAZIONI!Y128 | T7: =LAVORAZIONI!Z128 | U7: =LAVORAZIONI!AA128 | V7: =LAVORAZIONI!AB128 | ... AD7: =LAVORAZIONI!AJ128
B8: =LAVORAZIONI!G129 | C8: =LAVORAZIONI!A129 | D8: =LAVORAZIONI!K129 | E8: =LAVORAZIONI!H129 | F8: =LAVORAZIONI!M129 | G8: =LAVORAZIONI!N129 | H8: =LAVORAZIONI!O129 | I8: =LAVORAZIONI!P129 | J8: =IF(LAVORAZIONI!Q129="","",LAVORAZIONI!Q129) | K8: =IF(LAVORAZIONI!R129="","",LAVORAZIONI!R129) | L8: =IF(LAVORAZIONI!S129="","",LAVORAZIONI!S129) | M8: =LAVORAZIONI!T129 | O8: =LAVORAZIONI!U129 | P8: =LAVORAZIONI!V129 | Q8: =LAVORAZIONI!W129 | R8: =LAVORAZIONI!X129 | S8: =LAVORAZIONI!Y129 | T8: =LAVORAZIONI!Z129 | U8: =LAVORAZIONI!AA129 | V8: =LAVORAZIONI!AB129 | ... AD8: =LAVORAZIONI!AJ129
B9: =LAVORAZIONI!G130 | C9: =LAVORAZIONI!A130 | D9: =LAVORAZIONI!K130 | E9: =LAVORAZIONI!H130 | F9: =LAVORAZIONI!M130 | G9: =LAVORAZIONI!N130 | H9: =LAVORAZIONI!O130 | I9: =LAVORAZIONI!P130 | J9: =IF(LAVORAZIONI!Q130="","",LAVORAZIONI!Q130) | K9: =IF(LAVORAZIONI!R130="","",LAVORAZIONI!R130) | L9: =IF(LAVORAZIONI!S130="","",LAVORAZIONI!S130) | M9: =LAVORAZIONI!T130 | O9: =LAVORAZIONI!U130 | P9: =LAVORAZIONI!V130 | Q9: =LAVORAZIONI!W130 | R9: =LAVORAZIONI!X130 | S9: =LAVORAZIONI!Y130 | T9: =LAVORAZIONI!Z130 | U9: =LAVORAZIONI!AA130 | V9: =LAVORAZIONI!AB130 | ... AD9: =LAVORAZIONI!AJ130
B10: =LAVORAZIONI!G131 | C10: =LAVORAZIONI!A131 | D10: =LAVORAZIONI!K131 | E10: =LAVORAZIONI!H131 | F10: =LAVORAZIONI!M131 | G10: =LAVORAZIONI!N131 | H10: =LAVORAZIONI!O131 | I10: =LAVORAZIONI!P131 | J10: =IF(LAVORAZIONI!Q131="","",LAVORAZIONI!Q131) | K10: =IF(LAVORAZIONI!R131="","",LAVORAZIONI!R131) | L10: =IF(LAVORAZIONI!S131="","",LAVORAZIONI!S131) | M10: =LAVORAZIONI!T131 | O10: =LAVORAZIONI!U131 | P10: =LAVORAZIONI!V131 | Q10: =LAVORAZIONI!W131 | R10: =LAVORAZIONI!X131 | S10: =LAVORAZIONI!Y131 | T10: =LAVORAZIONI!Z131 | U10: =LAVORAZIONI!AA131 | V10: =LAVORAZIONI!AB131 | ... AD10: =LAVORAZIONI!AJ131
B11: =LAVORAZIONI!G132 | C11: =LAVORAZIONI!A132 | D11: =LAVORAZIONI!K132 | E11: =LAVORAZIONI!H132 | F11: =LAVORAZIONI!M132 | G11: =LAVORAZIONI!N132 | H11: =LAVORAZIONI!O132 | I11: =LAVORAZIONI!P132 | J11: =IF(LAVORAZIONI!Q132="","",LAVORAZIONI!Q132) | K11: =IF(LAVORAZIONI!R132="","",LAVORAZIONI!R132) | L11: =IF(LAVORAZIONI!S132="","",LAVORAZIONI!S132) | M11: =LAVORAZIONI!T132 | O11: =LAVORAZIONI!U132 | P11: =LAVORAZIONI!V132 | Q11: =LAVORAZIONI!W132 | R11: =LAVORAZIONI!X132 | S11: =LAVORAZIONI!Y132 | T11: =LAVORAZIONI!Z132 | U11: =LAVORAZIONI!AA132 | V11: =LAVORAZIONI!AB132 | ... AD11: =LAVORAZIONI!AJ132
B12: =LAVORAZIONI!G133 | C12: =LAVORAZIONI!A133 | D12: =LAVORAZIONI!K133 | E12: =LAVORAZIONI!H133 | F12: =LAVORAZIONI!M133 | G12: =LAVORAZIONI!N133 | H12: =LAVORAZIONI!O133 | I12: =LAVORAZIONI!P133 | J12: =IF(LAVORAZIONI!Q133="","",LAVORAZIONI!Q133) | K12: =IF(LAVORAZIONI!R133="","",LAVORAZIONI!R133) | L12: =IF(LAVORAZIONI!S133="","",LAVORAZIONI!S133) | M12: =LAVORAZIONI!T133 | O12: =LAVORAZIONI!U133 | P12: =LAVORAZIONI!V133 | Q12: =LAVORAZIONI!W133 | R12: =LAVORAZIONI!X133 | S12: =LAVORAZIONI!Y133 | T12: =LAVORAZIONI!Z133 | U12: =LAVORAZIONI!AA133 | V12: =LAVORAZIONI!AB133 | ... AD12: =LAVORAZIONI!AJ133
B13: =LAVORAZIONI!G134 | C13: =LAVORAZIONI!A134 | D13: =LAVORAZIONI!K134 | E13: =LAVORAZIONI!H134 | F13: =LAVORAZIONI!M134 | G13: =LAVORAZIONI!N134 | H13: =LAVORAZIONI!O134 | I13: =LAVORAZIONI!P134 | J13: =IF(LAVORAZIONI!Q134="","",LAVORAZIONI!Q134) | K13: =IF(LAVORAZIONI!R134="","",LAVORAZIONI!R134) | L13: =IF(LAVORAZIONI!S134="","",LAVORAZIONI!S134) | M13: =LAVORAZIONI!T134 | O13: =LAVORAZIONI!U134 | P13: =LAVORAZIONI!V134 | Q13: =LAVORAZIONI!W134 | R13: =LAVORAZIONI!X134 | S13: =LAVORAZIONI!Y134 | T13: =LAVORAZIONI!Z134 | U13: =LAVORAZIONI!AA134 | V13: =LAVORAZIONI!AB134 | ... AD13: =LAVORAZIONI!AJ134
B14: =LAVORAZIONI!G135 | C14: =LAVORAZIONI!A135 | D14: =LAVORAZIONI!K135 | E14: =LAVORAZIONI!H135 | F14: =LAVORAZIONI!M135 | G14: =LAVORAZIONI!N135 | H14: =LAVORAZIONI!O135 | I14: =LAVORAZIONI!P135 | J14: =IF(LAVORAZIONI!Q135="","",LAVORAZIONI!Q135) | K14: =IF(LAVORAZIONI!R135="","",LAVORAZIONI!R135) | L14: =IF(LAVORAZIONI!S135="","",LAVORAZIONI!S135) | M14: =LAVORAZIONI!T135 | O14: =LAVORAZIONI!U135 | P14: =LAVORAZIONI!V135 | Q14: =LAVORAZIONI!W135 | R14: =LAVORAZIONI!X135 | S14: =LAVORAZIONI!Y135 | T14: =LAVORAZIONI!Z135 | U14: =LAVORAZIONI!AA135 | V14: =LAVORAZIONI!AB135 | ... AD14: =LAVORAZIONI!AJ135
B15: =LAVORAZIONI!G136 | C15: =LAVORAZIONI!A136 | D15: =LAVORAZIONI!K136 | E15: =LAVORAZIONI!H136 | F15: =LAVORAZIONI!M136 | G15: =LAVORAZIONI!N136 | H15: =LAVORAZIONI!O136 | I15: =LAVORAZIONI!P136 | J15: =IF(LAVORAZIONI!Q136="","",LAVORAZIONI!Q136) | K15: =IF(LAVORAZIONI!R136="","",LAVORAZIONI!R136) | L15: =IF(LAVORAZIONI!S136="","",LAVORAZIONI!S136) | M15: =LAVORAZIONI!T136 | O15: =LAVORAZIONI!U136 | P15: =LAVORAZIONI!V136 | Q15: =LAVORAZIONI!W136 | R15: =LAVORAZIONI!X136 | S15: =LAVORAZIONI!Y136 | T15: =LAVORAZIONI!Z136 | U15: =LAVORAZIONI!AA136 | V15: =LAVORAZIONI!AB136 | ... AD15: =LAVORAZIONI!AJ136
... B50: =LAVORAZIONI!G171 | C50: =LAVORAZIONI!A171 | D50: =LAVORAZIONI!K171 | E50: =LAVORAZIONI!H171 | F50: =LAVORAZIONI!M171 | G50: =LAVORAZIONI!N171 | H50: =LAVORAZIONI!O171 | I50: =LAVORAZIONI!P171 | J50: =IF(LAVORAZIONI!Q171="","",LAVORAZIONI!Q171) | K50: =IF(LAVORAZIONI!R171="","",LAVORAZIONI!R171) | L50: =IF(LAVORAZIONI!S171="","",LAVORAZIONI!S171) | M50: =LAVORAZIONI!T171 | O50: =LAVORAZIONI!U171 | P50: =LAVORAZIONI!V171 | Q50: =LAVORAZIONI!W171 | R50: =LAVORAZIONI!X171 | S50: =LAVORAZIONI!Y171 | T50: =LAVORAZIONI!Z171 | U50: =LAVORAZIONI!AA171 | V50: =LAVORAZIONI!AB171 | ... AD50: =LAVORAZIONI!AJ171
D51: TOTALE EDILI SPECIALI | I51: =SUM(I4:I50) | L51: =SUM(L4:L50) | M51: =SUM(M4:M50) | P51: =SUM(P4:P50) | R51: =SUM(R4:R50) | T51: =SUM(T4:T50) | V51: =SUM(V4:V50) | X51: =SUM(X4:X50) | Z51: =SUM(Z4:Z50) | AB51: =SUM(AB4:AB50) | AD51: =SUM(AD4:AD50)

Sheet MECCANICHE
B1: DETTAGLIO SAL — OPERE MECCANICHE
B2: Nr.Ord. | C2: TARIFFA | D2: DESIGNAZIONE | E2: STEP | F2: U.M. | G2: Q.tà PREV | H2: VAL.UNIT PREV | I2: TOTALE PREV | J2: Q.tà CONS | K2: VAL.UNIT CONS | L2: TOTALE CONS | M2: VALORE PER SAL | O2: SAL 01 APRILE | Q2: SAL 02 MAGGIO | S2: SAL 03 GIUGNO | U2: SAL 04 LUGLIO | W2: SAL 05 AGOSTO | Y2: SAL 06 SETTEMBRE | AA2: SAL 07 OTTOBRE | AC2: TOTALE COMPL.
O3: % | P3: TOTALE | Q3: % | R3: TOTALE | S3: % | T3: TOTALE | U3: % | V3: TOTALE | W3: % | X3: TOTALE | Y3: % | Z3: TOTALE | AA3: % | AB3: TOTALE | AC3: % | AD3: TOTALE
B4: =LAVORAZIONI!G172 | C4: =LAVORAZIONI!A172 | D4: =LAVORAZIONI!K172 | E4: =LAVORAZIONI!H172 | F4: =LAVORAZIONI!M172 | G4: =LAVORAZIONI!N172 | H4: =LAVORAZIONI!O172 | I4: =LAVORAZIONI!P172 | J4: =IF(LAVORAZIONI!Q172="","",LAVORAZIONI!Q172) | K4: =IF(LAVORAZIONI!R172="","",LAVORAZIONI!R172) | L4: =IF(LAVORAZIONI!S172="","",LAVORAZIONI!S172) | M4: =LAVORAZIONI!T172 | O4: =LAVORAZIONI!U172 | P4: =LAVORAZIONI!V172 | Q4: =LAVORAZIONI!W172 | R4: =LAVORAZIONI!X172 | S4: =LAVORAZIONI!Y172 | T4: =LAVORAZIONI!Z172 | U4: =LAVORAZIONI!AA172 | V4: =LAVORAZIONI!AB172 | ... AD4: =LAVORAZIONI!AJ172
B5: =LAVORAZIONI!G173 | C5: =LAVORAZIONI!A173 | D5: =LAVORAZIONI!K173 | E5: =LAVORAZIONI!H173 | F5: =LAVORAZIONI!M173 | G5: =LAVORAZIONI!N173 | H5: =LAVORAZIONI!O173 | I5: =LAVORAZIONI!P173 | J5: =IF(LAVORAZIONI!Q173="","",LAVORAZIONI!Q173) | K5: =IF(LAVORAZIONI!R173="","",LAVORAZIONI!R173) | L5: =IF(LAVORAZIONI!S173="","",LAVORAZIONI!S173) | M5: =LAVORAZIONI!T173 | O5: =LAVORAZIONI!U173 | P5: =LAVORAZIONI!V173 | Q5: =LAVORAZIONI!W173 | R5: =LAVORAZIONI!X173 | S5: =LAVORAZIONI!Y173 | T5: =LAVORAZIONI!Z173 | U5: =LAVORAZIONI!AA173 | V5: =LAVORAZIONI!AB173 | ... AD5: =LAVORAZIONI!AJ173
B6: =LAVORAZIONI!G174 | C6: =LAVORAZIONI!A174 | D6: =LAVORAZIONI!K174 | E6: =LAVORAZIONI!H174 | F6: =LAVORAZIONI!M174 | G6: =LAVORAZIONI!N174 | H6: =LAVORAZIONI!O174 | I6: =LAVORAZIONI!P174 | J6: =IF(LAVORAZIONI!Q174="","",LAVORAZIONI!Q174) | K6: =IF(LAVORAZIONI!R174="","",LAVORAZIONI!R174) | L6: =IF(LAVORAZIONI!S174="","",LAVORAZIONI!S174) | M6: =LAVORAZIONI!T174 | O6: =LAVORAZIONI!U174 | P6: =LAVORAZIONI!V174 | Q6: =LAVORAZIONI!W174 | R6: =LAVORAZIONI!X174 | S6: =LAVORAZIONI!Y174 | T6: =LAVORAZIONI!Z174 | U6: =LAVORAZIONI!AA174 | V6: =LAVORAZIONI!AB174 | ... AD6: =LAVORAZIONI!AJ174
B7: =LAVORAZIONI!G175 | C7: =LAVORAZIONI!A175 | D7: =LAVORAZIONI!K175 | E7: =LAVORAZIONI!H175 | F7: =LAVORAZIONI!M175 | G7: =LAVORAZIONI!N175 | H7: =LAVORAZIONI!O175 | I7: =LAVORAZIONI!P175 | J7: =IF(LAVORAZIONI!Q175="","",LAVORAZIONI!Q175) | K7: =IF(LAVORAZIONI!R175="","",LAVORAZIONI!R175) | L7: =IF(LAVORAZIONI!S175="","",LAVORAZIONI!S175) | M7: =LAVORAZIONI!T175 | O7: =LAVORAZIONI!U175 | P7: =LAVORAZIONI!V175 | Q7: =LAVORAZIONI!W175 | R7: =LAVORAZIONI!X175 | S7: =LAVORAZIONI!Y175 | T7: =LAVORAZIONI!Z175 | U7: =LAVORAZIONI!AA175 | V7: =LAVORAZIONI!AB175 | ... AD7: =LAVORAZIONI!AJ175
B8: =LAVORAZIONI!G176 | C8: =LAVORAZIONI!A176 | D8: =LAVORAZIONI!K176 | E8: =LAVORAZIONI!H176 | F8: =LAVORAZIONI!M176 | G8: =LAVORAZIONI!N176 | H8: =LAVORAZIONI!O176 | I8: =LAVORAZIONI!P176 | J8: =IF(LAVORAZIONI!Q176="","",LAVORAZIONI!Q176) | K8: =IF(LAVORAZIONI!R176="","",LAVORAZIONI!R176) | L8: =IF(LAVORAZIONI!S176="","",LAVORAZIONI!S176) | M8: =LAVORAZIONI!T176 | O8: =LAVORAZIONI!U176 | P8: =LAVORAZIONI!V176 | Q8: =LAVORAZIONI!W176 | R8: =LAVORAZIONI!X176 | S8: =LAVORAZIONI!Y176 | T8: =LAVORAZIONI!Z176 | U8: =LAVORAZIONI!AA176 | V8: =LAVORAZIONI!AB176 | ... AD8: =LAVORAZIONI!AJ176
B9: =LAVORAZIONI!G177 | C9: =LAVORAZIONI!A177 | D9: =LAVORAZIONI!K177 | E9: =LAVORAZIONI!H177 | F9: =LAVORAZIONI!M177 | G9: =LAVORAZIONI!N177 | H9: =LAVORAZIONI!O177 | I9: =LAVORAZIONI!P177 | J9: =IF(LAVORAZIONI!Q177="","",LAVORAZIONI!Q177) | K9: =IF(LAVORAZIONI!R177="","",LAVORAZIONI!R177) | L9: =IF(LAVORAZIONI!S177="","",LAVORAZIONI!S177) | M9: =LAVORAZIONI!T177 | O9: =LAVORAZIONI!U177 | P9: =LAVORAZIONI!V177 | Q9: =LAVORAZIONI!W177 | R9: =LAVORAZIONI!X177 | S9: =LAVORAZIONI!Y177 | T9: =LAVORAZIONI!Z177 | U9: =LAVORAZIONI!AA177 | V9: =LAVORAZIONI!AB177 | ... AD9: =LAVORAZIONI!AJ177
B10: =LAVORAZIONI!G178 | C10: =LAVORAZIONI!A178 | D10: =LAVORAZIONI!K178 | E10: =LAVORAZIONI!H178 | F10: =LAVORAZIONI!M178 | G10: =LAVORAZIONI!N178 | H10: =LAVORAZIONI!O178 | I10: =LAVORAZIONI!P178 | J10: =IF(LAVORAZIONI!Q178="","",LAVORAZIONI!Q178) | K10: =IF(LAVORAZIONI!R178="","",LAVORAZIONI!R178) | L10: =IF(LAVORAZIONI!S178="","",LAVORAZIONI!S178) | M10: =LAVORAZIONI!T178 | O10: =LAVORAZIONI!U178 | P10: =LAVORAZIONI!V178 | Q10: =LAVORAZIONI!W178 | R10: =LAVORAZIONI!X178 | S10: =LAVORAZIONI!Y178 | T10: =LAVORAZIONI!Z178 | U10: =LAVORAZIONI!AA178 | V10: =LAVORAZIONI!AB178 | ... AD10: =LAVORAZIONI!AJ178
B11: =LAVORAZIONI!G179 | C11: =LAVORAZIONI!A179 | D11: =LAVORAZIONI!K179 | E11: =LAVORAZIONI!H179 | F11: =LAVORAZIONI!M179 | G11: =LAVORAZIONI!N179 | H11: =LAVORAZIONI!O179 | I11: =LAVORAZIONI!P179 | J11: =IF(LAVORAZIONI!Q179="","",LAVORAZIONI!Q179) | K11: =IF(LAVORAZIONI!R179="","",LAVORAZIONI!R179) | L11: =IF(LAVORAZIONI!S179="","",LAVORAZIONI!S179) | M11: =LAVORAZIONI!T179 | O11: =LAVORAZIONI!U179 | P11: =LAVORAZIONI!V179 | Q11: =LAVORAZIONI!W179 | R11: =LAVORAZIONI!X179 | S11: =LAVORAZIONI!Y179 | T11: =LAVORAZIONI!Z179 | U11: =LAVORAZIONI!AA179 | V11: =LAVORAZIONI!AB179 | ... AD11: =LAVORAZIONI!AJ179
B12: =LAVORAZIONI!G180 | C12: =LAVORAZIONI!A180 | D12: =LAVORAZIONI!K180 | E12: =LAVORAZIONI!H180 | F12: =LAVORAZIONI!M180 | G12: =LAVORAZIONI!N180 | H12: =LAVORAZIONI!O180 | I12: =LAVORAZIONI!P180 | J12: =IF(LAVORAZIONI!Q180="","",LAVORAZIONI!Q180) | K12: =IF(LAVORAZIONI!R180="","",LAVORAZIONI!R180) | L12: =IF(LAVORAZIONI!S180="","",LAVORAZIONI!S180) | M12: =LAVORAZIONI!T180 | O12: =LAVORAZIONI!U180 | P12: =LAVORAZIONI!V180 | Q12: =LAVORAZIONI!W180 | R12: =LAVORAZIONI!X180 | S12: =LAVORAZIONI!Y180 | T12: =LAVORAZIONI!Z180 | U12: =LAVORAZIONI!AA180 | V12: =LAVORAZIONI!AB180 | ... AD12: =LAVORAZIONI!AJ180
B13: =LAVORAZIONI!G181 | C13: =LAVORAZIONI!A181 | D13: =LAVORAZIONI!K181 | E13: =LAVORAZIONI!H181 | F13: =LAVORAZIONI!M181 | G13: =LAVORAZIONI!N181 | H13: =LAVORAZIONI!O181 | I13: =LAVORAZIONI!P181 | J13: =IF(LAVORAZIONI!Q181="","",LAVORAZIONI!Q181) | K13: =IF(LAVORAZIONI!R181="","",LAVORAZIONI!R181) | L13: =IF(LAVORAZIONI!S181="","",LAVORAZIONI!S181) | M13: =LAVORAZIONI!T181 | O13: =LAVORAZIONI!U181 | P13: =LAVORAZIONI!V181 | Q13: =LAVORAZIONI!W181 | R13: =LAVORAZIONI!X181 | S13: =LAVORAZIONI!Y181 | T13: =LAVORAZIONI!Z181 | U13: =LAVORAZIONI!AA181 | V13: =LAVORAZIONI!AB181 | ... AD13: =LAVORAZIONI!AJ181
B14: =LAVORAZIONI!G182 | C14: =LAVORAZIONI!A182 | D14: =LAVORAZIONI!K182 | E14: =LAVORAZIONI!H182 | F14: =LAVORAZIONI!M182 | G14: =LAVORAZIONI!N182 | H14: =LAVORAZIONI!O182 | I14: =LAVORAZIONI!P182 | J14: =IF(LAVORAZIONI!Q182="","",LAVORAZIONI!Q182) | K14: =IF(LAVORAZIONI!R182="","",LAVORAZIONI!R182) | L14: =IF(LAVORAZIONI!S182="","",LAVORAZIONI!S182) | M14: =LAVORAZIONI!T182 | O14: =LAVORAZIONI!U182 | P14: =LAVORAZIONI!V182 | Q14: =LAVORAZIONI!W182 | R14: =LAVORAZIONI!X182 | S14: =LAVORAZIONI!Y182 | T14: =LAVORAZIONI!Z182 | U14: =LAVORAZIONI!AA182 | V14: =LAVORAZIONI!AB182 | ... AD14: =LAVORAZIONI!AJ182
B15: =LAVORAZIONI!G183 | C15: =LAVORAZIONI!A183 | D15: =LAVORAZIONI!K183 | E15: =LAVORAZIONI!H183 | F15: =LAVORAZIONI!M183 | G15: =LAVORAZIONI!N183 | H15: =LAVORAZIONI!O183 | I15: =LAVORAZIONI!P183 | J15: =IF(LAVORAZIONI!Q183="","",LAVORAZIONI!Q183) | K15: =IF(LAVORAZIONI!R183="","",LAVORAZIONI!R183) | L15: =IF(LAVORAZIONI!S183="","",LAVORAZIONI!S183) | M15: =LAVORAZIONI!T183 | O15: =LAVORAZIONI!U183 | P15: =LAVORAZIONI!V183 | Q15: =LAVORAZIONI!W183 | R15: =LAVORAZIONI!X183 | S15: =LAVORAZIONI!Y183 | T15: =LAVORAZIONI!Z183 | U15: =LAVORAZIONI!AA183 | V15: =LAVORAZIONI!AB183 | ... AD15: =LAVORAZIONI!AJ183
... B88: =LAVORAZIONI!G256 | C88: =LAVORAZIONI!A256 | D88: =LAVORAZIONI!K256 | E88: =LAVORAZIONI!H256 | F88: =LAVORAZIONI!M256 | G88: =LAVORAZIONI!N256 | H88: =LAVORAZIONI!O256 | I88: =LAVORAZIONI!P256 | J88: =IF(LAVORAZIONI!Q256="","",LAVORAZIONI!Q256) | K88: =IF(LAVORAZIONI!R256="","",LAVORAZIONI!R256) | L88: =IF(LAVORAZIONI!S256="","",LAVORAZIONI!S256) | M88: =LAVORAZIONI!T256 | O88: =LAVORAZIONI!U256 | P88: =LAVORAZIONI!V256 | Q88: =LAVORAZIONI!W256 | R88: =LAVORAZIONI!X256 | S88: =LAVORAZIONI!Y256 | T88: =LAVORAZIONI!Z256 | U88: =LAVORAZIONI!AA256 | V88: =LAVORAZIONI!AB256 | ... AD88: =LAVORAZIONI!AJ256
D89: TOTALE MECCANICHE | I89: =SUM(I4:I88) | L89: =SUM(L4:L88) | M89: =SUM(M4:M88) | P89: =SUM(P4:P88) | R89: =SUM(R4:R88) | T89: =SUM(T4:T88) | V89: =SUM(V4:V88) | X89: =SUM(X4:X88) | Z89: =SUM(Z4:Z88) | AB89: =SUM(AB4:AB88) | AD89: =SUM(AD4:AD88)

Sheet MECCANICHE SPECIALI
B2: DETTAGLIO SAL — OPERE MECCANICHE SPECIALI A SERVIZIO DELLE APPARECCHIATURE DI LABORATORIO
B3: Nr.Ord. | C3: TARIFFA | D3: DESIGNAZIONE | E3: STEP | F3: U.M. | G3: Q.tà PREV | H3: VAL.UNIT PREV | I3: TOTALE PREV | J3: Q.tà CONS | K3: VAL.UNIT CONS | L3: TOTALE CONS | M3: VALORE PER SAL | O3: SAL 01 APRILE | Q3: SAL 02 MAGGIO | S3: SAL 03 GIUGNO | U3: SAL 04 LUGLIO | W3: SAL 05 AGOSTO | Y3: SAL 06 SETTEMBRE | AA3: SAL 07 OTTOBRE | AC3: TOTALE COMPL.
O4: % | P4: TOTALE | Q4: % | R4: TOTALE | S4: % | T4: TOTALE | U4: % | V4: TOTALE | W4: % | X4: TOTALE | Y4: % | Z4: TOTALE | AA4: % | AB4: TOTALE | AC4: % | AD4: TOTALE
B5: =LAVORAZIONI!G257 | C5: =LAVORAZIONI!A257 | D5: =LAVORAZIONI!K257 | E5: =LAVORAZIONI!H257 | F5: =LAVORAZIONI!M257 | G5: =LAVORAZIONI!N257 | H5: =LAVORAZIONI!O257 | I5: =LAVORAZIONI!P257 | J5: =IF(LAVORAZIONI!Q257="","",LAVORAZIONI!Q257) | K5: =IF(LAVORAZIONI!R257="","",LAVORAZIONI!R257) | L5: =IF(LAVORAZIONI!S257="","",LAVORAZIONI!S257) | M5: =LAVORAZIONI!T257 | O5: =LAVORAZIONI!U257 | P5: =LAVORAZIONI!V257 | Q5: =LAVORAZIONI!W257 | R5: =LAVORAZIONI!X257 | S5: =LAVORAZIONI!Y257 | T5: =LAVORAZIONI!Z257 | U5: =LAVORAZIONI!AA257 | V5: =LAVORAZIONI!AB257 | ... AD5: =LAVORAZIONI!AJ257
B6: =LAVORAZIONI!G258 | C6: =LAVORAZIONI!A258 | D6: =LAVORAZIONI!K258 | E6: =LAVORAZIONI!H258 | F6: =LAVORAZIONI!M258 | G6: =LAVORAZIONI!N258 | H6: =LAVORAZIONI!O258 | I6: =LAVORAZIONI!P258 | J6: =IF(LAVORAZIONI!Q258="","",LAVORAZIONI!Q258) | K6: =IF(LAVORAZIONI!R258="","",LAVORAZIONI!R258) | L6: =IF(LAVORAZIONI!S258="","",LAVORAZIONI!S258) | M6: =LAVORAZIONI!T258 | O6: =LAVORAZIONI!U258 | P6: =LAVORAZIONI!V258 | Q6: =LAVORAZIONI!W258 | R6: =LAVORAZIONI!X258 | S6: =LAVORAZIONI!Y258 | T6: =LAVORAZIONI!Z258 | U6: =LAVORAZIONI!AA258 | V6: =LAVORAZIONI!AB258 | ... AD6: =LAVORAZIONI!AJ258
B7: =LAVORAZIONI!G259 | C7: =LAVORAZIONI!A259 | D7: =LAVORAZIONI!K259 | E7: =LAVORAZIONI!H259 | F7: =LAVORAZIONI!M259 | G7: =LAVORAZIONI!N259 | H7: =LAVORAZIONI!O259 | I7: =LAVORAZIONI!P259 | J7: =IF(LAVORAZIONI!Q259="","",LAVORAZIONI!Q259) | K7: =IF(LAVORAZIONI!R259="","",LAVORAZIONI!R259) | L7: =IF(LAVORAZIONI!S259="","",LAVORAZIONI!S259) | M7: =LAVORAZIONI!T259 | O7: =LAVORAZIONI!U259 | P7: =LAVORAZIONI!V259 | Q7: =LAVORAZIONI!W259 | R7: =LAVORAZIONI!X259 | S7: =LAVORAZIONI!Y259 | T7: =LAVORAZIONI!Z259 | U7: =LAVORAZIONI!AA259 | V7: =LAVORAZIONI!AB259 | ... AD7: =LAVORAZIONI!AJ259
B8: =LAVORAZIONI!G260 | C8: =LAVORAZIONI!A260 | D8: =LAVORAZIONI!K260 | E8: =LAVORAZIONI!H260 | F8: =LAVORAZIONI!M260 | G8: =LAVORAZIONI!N260 | H8: =LAVORAZIONI!O260 | I8: =LAVORAZIONI!P260 | J8: =IF(LAVORAZIONI!Q260="","",LAVORAZIONI!Q260) | K8: =IF(LAVORAZIONI!R260="","",LAVORAZIONI!R260) | L8: =IF(LAVORAZIONI!S260="","",LAVORAZIONI!S260) | M8: =LAVORAZIONI!T260 | O8: =LAVORAZIONI!U260 | P8: =LAVORAZIONI!V260 | Q8: =LAVORAZIONI!W260 | R8: =LAVORAZIONI!X260 | S8: =LAVORAZIONI!Y260 | T8: =LAVORAZIONI!Z260 | U8: =LAVORAZIONI!AA260 | V8: =LAVORAZIONI!AB260 | ... AD8: =LAVORAZIONI!AJ260
B9: =LAVORAZIONI!G261 | C9: =LAVORAZIONI!A261 | D9: =LAVORAZIONI!K261 | E9: =LAVORAZIONI!H261 | F9: =LAVORAZIONI!M261 | G9: =LAVORAZIONI!N261 | H9: =LAVORAZIONI!O261 | I9: =LAVORAZIONI!P261 | J9: =IF(LAVORAZIONI!Q261="","",LAVORAZIONI!Q261) | K9: =IF(LAVORAZIONI!R261="","",LAVORAZIONI!R261) | L9: =IF(LAVORAZIONI!S261="","",LAVORAZIONI!S261) | M9: =LAVORAZIONI!T261 | O9: =LAVORAZIONI!U261 | P9: =LAVORAZIONI!V261 | Q9: =LAVORAZIONI!W261 | R9: =LAVORAZIONI!X261 | S9: =LAVORAZIONI!Y261 | T9: =LAVORAZIONI!Z261 | U9: =LAVORAZIONI!AA261 | V9: =LAVORAZIONI!AB261 | ... AD9: =LAVORAZIONI!AJ261
B10: =LAVORAZIONI!G262 | C10: =LAVORAZIONI!A262 | D10: =LAVORAZIONI!K262 | E10: =LAVORAZIONI!H262 | F10: =LAVORAZIONI!M262 | G10: =LAVORAZIONI!N262 | H10: =LAVORAZIONI!O262 | I10: =LAVORAZIONI!P262 | J10: =IF(LAVORAZIONI!Q262="","",LAVORAZIONI!Q262) | K10: =IF(LAVORAZIONI!R262="","",LAVORAZIONI!R262) | L10: =IF(LAVORAZIONI!S262="","",LAVORAZIONI!S262) | M10: =LAVORAZIONI!T262 | O10: =LAVORAZIONI!U262 | P10: =LAVORAZIONI!V262 | Q10: =LAVORAZIONI!W262 | R10: =LAVORAZIONI!X262 | S10: =LAVORAZIONI!Y262 | T10: =LAVORAZIONI!Z262 | U10: =LAVORAZIONI!AA262 | V10: =LAVORAZIONI!AB262 | ... AD10: =LAVORAZIONI!AJ262
B11: =LAVORAZIONI!G263 | C11: =LAVORAZIONI!A263 | D11: =LAVORAZIONI!K263 | E11: =LAVORAZIONI!H263 | F11: =LAVORAZIONI!M263 | G11: =LAVORAZIONI!N263 | H11: =LAVORAZIONI!O263 | I11: =LAVORAZIONI!P263 | J11: =IF(LAVORAZIONI!Q263="","",LAVORAZIONI!Q263) | K11: =IF(LAVORAZIONI!R263="","",LAVORAZIONI!R263) | L11: =IF(LAVORAZIONI!S263="","",LAVORAZIONI!S263) | M11: =LAVORAZIONI!T263 | O11: =LAVORAZIONI!U263 | P11: =LAVORAZIONI!V263 | Q11: =LAVORAZIONI!W263 | R11: =LAVORAZIONI!X263 | S11: =LAVORAZIONI!Y263 | T11: =LAVORAZIONI!Z263 | U11: =LAVORAZIONI!AA263 | V11: =LAVORAZIONI!AB263 | ... AD11: =LAVORAZIONI!AJ263
B12: =LAVORAZIONI!G264 | C12: =LAVORAZIONI!A264 | D12: =LAVORAZIONI!K264 | E12: =LAVORAZIONI!H264 | F12: =LAVORAZIONI!M264 | G12: =LAVORAZIONI!N264 | H12: =LAVORAZIONI!O264 | I12: =LAVORAZIONI!P264 | J12: =IF(LAVORAZIONI!Q264="","",LAVORAZIONI!Q264) | K12: =IF(LAVORAZIONI!R264="","",LAVORAZIONI!R264) | L12: =IF(LAVORAZIONI!S264="","",LAVORAZIONI!S264) | M12: =LAVORAZIONI!T264 | O12: =LAVORAZIONI!U264 | P12: =LAVORAZIONI!V264 | Q12: =LAVORAZIONI!W264 | R12: =LAVORAZIONI!X264 | S12: =LAVORAZIONI!Y264 | T12: =LAVORAZIONI!Z264 | U12: =LAVORAZIONI!AA264 | V12: =LAVORAZIONI!AB264 | ... AD12: =LAVORAZIONI!AJ264
B13: =LAVORAZIONI!G265 | C13: =LAVORAZIONI!A265 | D13: =LAVORAZIONI!K265 | E13: =LAVORAZIONI!H265 | F13: =LAVORAZIONI!M265 | G13: =LAVORAZIONI!N265 | H13: =LAVORAZIONI!O265 | I13: =LAVORAZIONI!P265 | J13: =IF(LAVORAZIONI!Q265="","",LAVORAZIONI!Q265) | K13: =IF(LAVORAZIONI!R265="","",LAVORAZIONI!R265) | L13: =IF(LAVORAZIONI!S265="","",LAVORAZIONI!S265) | M13: =LAVORAZIONI!T265 | O13: =LAVORAZIONI!U265 | P13: =LAVORAZIONI!V265 | Q13: =LAVORAZIONI!W265 | R13: =LAVORAZIONI!X265 | S13: =LAVORAZIONI!Y265 | T13: =LAVORAZIONI!Z265 | U13: =LAVORAZIONI!AA265 | V13: =LAVORAZIONI!AB265 | ... AD13: =LAVORAZIONI!AJ265
B14: =LAVORAZIONI!G266 | C14: =LAVORAZIONI!A266 | D14: =LAVORAZIONI!K266 | E14: =LAVORAZIONI!H266 | F14: =LAVORAZIONI!M266 | G14: =LAVORAZIONI!N266 | H14: =LAVORAZIONI!O266 | I14: =LAVORAZIONI!P266 | J14: =IF(LAVORAZIONI!Q266="","",LAVORAZIONI!Q266) | K14: =IF(LAVORAZIONI!R266="","",LAVORAZIONI!R266) | L14: =IF(LAVORAZIONI!S266="","",LAVORAZIONI!S266) | M14: =LAVORAZIONI!T266 | O14: =LAVORAZIONI!U266 | P14: =LAVORAZIONI!V266 | Q14: =LAVORAZIONI!W266 | R14: =LAVORAZIONI!X266 | S14: =LAVORAZIONI!Y266 | T14: =LAVORAZIONI!Z266 | U14: =LAVORAZIONI!AA266 | V14: =LAVORAZIONI!AB266 | ... AD14: =LAVORAZIONI!AJ266
B15: =LAVORAZIONI!G267 | C15: =LAVORAZIONI!A267 | D15: =LAVORAZIONI!K267 | E15: =LAVORAZIONI!H267 | F15: =LAVORAZIONI!M267 | G15: =LAVORAZIONI!N267 | H15: =LAVORAZIONI!O267 | I15: =LAVORAZIONI!P267 | J15: =IF(LAVORAZIONI!Q267="","",LAVORAZIONI!Q267) | K15: =IF(LAVORAZIONI!R267="","",LAVORAZIONI!R267) | L15: =IF(LAVORAZIONI!S267="","",LAVORAZIONI!S267) | M15: =LAVORAZIONI!T267 | O15: =LAVORAZIONI!U267 | P15: =LAVORAZIONI!V267 | Q15: =LAVORAZIONI!W267 | R15: =LAVORAZIONI!X267 | S15: =LAVORAZIONI!Y267 | T15: =LAVORAZIONI!Z267 | U15: =LAVORAZIONI!AA267 | V15: =LAVORAZIONI!AB267 | ... AD15: =LAVORAZIONI!AJ267
B16: =LAVORAZIONI!G268 | C16: =LAVORAZIONI!A268 | D16: =LAVORAZIONI!K268 | E16: =LAVORAZIONI!H268 | F16: =LAVORAZIONI!M268 | G16: =LAVORAZIONI!N268 | H16: =LAVORAZIONI!O268 | I16: =LAVORAZIONI!P268 | J16: =IF(LAVORAZIONI!Q268="","",LAVORAZIONI!Q268) | K16: =IF(LAVORAZIONI!R268="","",LAVORAZIONI!R268) | L16: =IF(LAVORAZIONI!S268="","",LAVORAZIONI!S268) | M16: =LAVORAZIONI!T268 | O16: =LAVORAZIONI!U268 | P16: =LAVORAZIONI!V268 | Q16: =LAVORAZIONI!W268 | R16: =LAVORAZIONI!X268 | S16: =LAVORAZIONI!Y268 | T16: =LAVORAZIONI!Z268 | U16: =LAVORAZIONI!AA268 | V16: =LAVORAZIONI!AB268 | ... AD16: =LAVORAZIONI!AJ268
... B145: =LAVORAZIONI!G397 | C145: =LAVORAZIONI!A397 | D145: =LAVORAZIONI!K397 | E145: =LAVORAZIONI!H397 | F145: =LAVORAZIONI!M397 | G145: =LAVORAZIONI!N397 | H145: =LAVORAZIONI!O397 | I145: =LAVORAZIONI!P397 | J145: =IF(LAVORAZIONI!Q397="","",LAVORAZIONI!Q397) | K145: =IF(LAVORAZIONI!R397="","",LAVORAZIONI!R397) | L145: =IF(LAVORAZIONI!S397="","",LAVORAZIONI!S397) | M145: =LAVORAZIONI!T397 | O145: =LAVORAZIONI!U397 | P145: =LAVORAZIONI!V397 | Q145: =LAVORAZIONI!W397 | R145: =LAVORAZIONI!X397 | S145: =LAVORAZIONI!Y397 | T145: =LAVORAZIONI!Z397 | U145: =LAVORAZIONI!AA397 | V145: =LAVORAZIONI!AB397 | ... AD145: =LAVORAZIONI!AJ397
D146: TOTALE MECCANICHE SPECIALI | I146: =SUM(I5:I145) | L146: =SUM(L5:L145) | M146: =SUM(M5:M145) | P146: =SUM(P5:P145) | R146: =SUM(R5:R145) | T146: =SUM(T5:T145) | V146: =SUM(V5:V145) | X146: =SUM(X5:X145) | Z146: =SUM(Z5:Z145) | AB146: =SUM(AB5:AB145) | AD146: =SUM(AD5:AD145)

Sheet ELETTRICHE
B2: DETTAGLIO SAL — OPERE ELETTRICHE
B3: Nr.Ord. | C3: TARIFFA | D3: DESIGNAZIONE | E3: STEP | F3: U.M. | G3: Q.tà PREV | H3: VAL.UNIT PREV | I3: TOTALE PREV | J3: Q.tà CONS | K3: VAL.UNIT CONS | L3: TOTALE CONS | M3: VALORE PER SAL | O3: SAL 01 APRILE | Q3: SAL 02 MAGGIO | S3: SAL 03 GIUGNO | U3: SAL 04 LUGLIO | W3: SAL 05 AGOSTO | Y3: SAL 06 SETTEMBRE | AA3: SAL 07 OTTOBRE | AC3: TOTALE COMPL.
O4: % | P4: TOTALE | Q4: % | R4: TOTALE | S4: % | T4: TOTALE | U4: % | V4: TOTALE | W4: % | X4: TOTALE | Y4: % | Z4: TOTALE | AA4: % | AB4: TOTALE | AC4: % | AD4: TOTALE
B5: =LAVORAZIONI!G398 | C5: =LAVORAZIONI!A398 | D5: =LAVORAZIONI!K398 | E5: =LAVORAZIONI!H398 | F5: =LAVORAZIONI!M398 | G5: =LAVORAZIONI!N398 | H5: =LAVORAZIONI!O398 | I5: =LAVORAZIONI!P398 | J5: =IF(LAVORAZIONI!Q398="","",LAVORAZIONI!Q398) | K5: =IF(LAVORAZIONI!R398="","",LAVORAZIONI!R398) | L5: =IF(LAVORAZIONI!S398="","",LAVORAZIONI!S398) | M5: =LAVORAZIONI!T398 | O5: =LAVORAZIONI!U398 | P5: =LAVORAZIONI!V398 | Q5: =LAVORAZIONI!W398 | R5: =LAVORAZIONI!X398 | S5: =LAVORAZIONI!Y398 | T5: =LAVORAZIONI!Z398 | U5: =LAVORAZIONI!AA398 | V5: =LAVORAZIONI!AB398 | ... AD5: =LAVORAZIONI!AJ398
B6: =LAVORAZIONI!G399 | C6: =LAVORAZIONI!A399 | D6: =LAVORAZIONI!K399 | E6: =LAVORAZIONI!H399 | F6: =LAVORAZIONI!M399 | G6: =LAVORAZIONI!N399 | H6: =LAVORAZIONI!O399 | I6: =LAVORAZIONI!P399 | J6: =IF(LAVORAZIONI!Q399="","",LAVORAZIONI!Q399) | K6: =IF(LAVORAZIONI!R399="","",LAVORAZIONI!R399) | L6: =IF(LAVORAZIONI!S399="","",LAVORAZIONI!S399) | M6: =LAVORAZIONI!T399 | O6: =LAVORAZIONI!U399 | P6: =LAVORAZIONI!V399 | Q6: =LAVORAZIONI!W399 | R6: =LAVORAZIONI!X399 | S6: =LAVORAZIONI!Y399 | T6: =LAVORAZIONI!Z399 | U6: =LAVORAZIONI!AA399 | V6: =LAVORAZIONI!AB399 | ... AD6: =LAVORAZIONI!AJ399
B7: =LAVORAZIONI!G400 | C7: =LAVORAZIONI!A400 | D7: =LAVORAZIONI!K400 | E7: =LAVORAZIONI!H400 | F7: =LAVORAZIONI!M400 | G7: =LAVORAZIONI!N400 | H7: =LAVORAZIONI!O400 | I7: =LAVORAZIONI!P400 | J7: =IF(LAVORAZIONI!Q400="","",LAVORAZIONI!Q400) | K7: =IF(LAVORAZIONI!R400="","",LAVORAZIONI!R400) | L7: =IF(LAVORAZIONI!S400="","",LAVORAZIONI!S400) | M7: =LAVORAZIONI!T400 | O7: =LAVORAZIONI!U400 | P7: =LAVORAZIONI!V400 | Q7: =LAVORAZIONI!W400 | R7: =LAVORAZIONI!X400 | S7: =LAVORAZIONI!Y400 | T7: =LAVORAZIONI!Z400 | U7: =LAVORAZIONI!AA400 | V7: =LAVORAZIONI!AB400 | ... AD7: =LAVORAZIONI!AJ400
B8: =LAVORAZIONI!G401 | C8: =LAVORAZIONI!A401 | D8: =LAVORAZIONI!K401 | E8: =LAVORAZIONI!H401 | F8: =LAVORAZIONI!M401 | G8: =LAVORAZIONI!N401 | H8: =LAVORAZIONI!O401 | I8: =LAVORAZIONI!P401 | J8: =IF(LAVORAZIONI!Q401="","",LAVORAZIONI!Q401) | K8: =IF(LAVORAZIONI!R401="","",LAVORAZIONI!R401) | L8: =IF(LAVORAZIONI!S401="","",LAVORAZIONI!S401) | M8: =LAVORAZIONI!T401 | O8: =LAVORAZIONI!U401 | P8: =LAVORAZIONI!V401 | Q8: =LAVORAZIONI!W401 | R8: =LAVORAZIONI!X401 | S8: =LAVORAZIONI!Y401 | T8: =LAVORAZIONI!Z401 | U8: =LAVORAZIONI!AA401 | V8: =LAVORAZIONI!AB401 | ... AD8: =LAVORAZIONI!AJ401
B9: =LAVORAZIONI!G402 | C9: =LAVORAZIONI!A402 | D9: =LAVORAZIONI!K402 | E9: =LAVORAZIONI!H402 | F9: =LAVORAZIONI!M402 | G9: =LAVORAZIONI!N402 | H9: =LAVORAZIONI!O402 | I9: =LAVORAZIONI!P402 | J9: =IF(LAVORAZIONI!Q402="","",LAVORAZIONI!Q402) | K9: =IF(LAVORAZIONI!R402="","",LAVORAZIONI!R402) | L9: =IF(LAVORAZIONI!S402="","",LAVORAZIONI!S402) | M9: =LAVORAZIONI!T402 | O9: =LAVORAZIONI!U402 | P9: =LAVORAZIONI!V402 | Q9: =LAVORAZIONI!W402 | R9: =LAVORAZIONI!X402 | S9: =LAVORAZIONI!Y402 | T9: =LAVORAZIONI!Z402 | U9: =LAVORAZIONI!AA402 | V9: =LAVORAZIONI!AB402 | ... AD9: =LAVORAZIONI!AJ402
B10: =LAVORAZIONI!G403 | C10: =LAVORAZIONI!A403 | D10: =LAVORAZIONI!K403 | E10: =LAVORAZIONI!H403 | F10: =LAVORAZIONI!M403 | G10: =LAVORAZIONI!N403 | H10: =LAVORAZIONI!O403 | I10: =LAVORAZIONI!P403 | J10: =IF(LAVORAZIONI!Q403="","",LAVORAZIONI!Q403) | K10: =IF(LAVORAZIONI!R403="","",LAVORAZIONI!R403) | L10: =IF(LAVORAZIONI!S403="","",LAVORAZIONI!S403) | M10: =LAVORAZIONI!T403 | O10: =LAVORAZIONI!U403 | P10: =LAVORAZIONI!V403 | Q10: =LAVORAZIONI!W403 | R10: =LAVORAZIONI!X403 | S10: =LAVORAZIONI!Y403 | T10: =LAVORAZIONI!Z403 | U10: =LAVORAZIONI!AA403 | V10: =LAVORAZIONI!AB403 | ... AD10: =LAVORAZIONI!AJ403
B11: =LAVORAZIONI!G404 | C11: =LAVORAZIONI!A404 | D11: =LAVORAZIONI!K404 | E11: =LAVORAZIONI!H404 | F11: =LAVORAZIONI!M404 | G11: =LAVORAZIONI!N404 | H11: =LAVORAZIONI!O404 | I11: =LAVORAZIONI!P404 | J11: =IF(LAVORAZIONI!Q404="","",LAVORAZIONI!Q404) | K11: =IF(LAVORAZIONI!R404="","",LAVORAZIONI!R404) | L11: =IF(LAVORAZIONI!S404="","",LAVORAZIONI!S404) | M11: =LAVORAZIONI!T404 | O11: =LAVORAZIONI!U404 | P11: =LAVORAZIONI!V404 | Q11: =LAVORAZIONI!W404 | R11: =LAVORAZIONI!X404 | S11: =LAVORAZIONI!Y404 | T11: =LAVORAZIONI!Z404 | U11: =LAVORAZIONI!AA404 | V11: =LAVORAZIONI!AB404 | ... AD11: =LAVORAZIONI!AJ404
B12: =LAVORAZIONI!G405 | C12: =LAVORAZIONI!A405 | D12: =LAVORAZIONI!K405 | E12: =LAVORAZIONI!H405 | F12: =LAVORAZIONI!M405 | G12: =LAVORAZIONI!N405 | H12: =LAVORAZIONI!O405 | I12: =LAVORAZIONI!P405 | J12: =IF(LAVORAZIONI!Q405="","",LAVORAZIONI!Q405) | K12: =IF(LAVORAZIONI!R405="","",LAVORAZIONI!R405) | L12: =IF(LAVORAZIONI!S405="","",LAVORAZIONI!S405) | M12: =LAVORAZIONI!T405 | O12: =LAVORAZIONI!U405 | P12: =LAVORAZIONI!V405 | Q12: =LAVORAZIONI!W405 | R12: =LAVORAZIONI!X405 | S12: =LAVORAZIONI!Y405 | T12: =LAVORAZIONI!Z405 | U12: =LAVORAZIONI!AA405 | V12: =LAVORAZIONI!AB405 | ... AD12: =LAVORAZIONI!AJ405
B13: =LAVORAZIONI!G406 | C13: =LAVORAZIONI!A406 | D13: =LAVORAZIONI!K406 | E13: =LAVORAZIONI!H406 | F13: =LAVORAZIONI!M406 | G13: =LAVORAZIONI!N406 | H13: =LAVORAZIONI!O406 | I13: =LAVORAZIONI!P406 | J13: =IF(LAVORAZIONI!Q406="","",LAVORAZIONI!Q406) | K13: =IF(LAVORAZIONI!R406="","",LAVORAZIONI!R406) | L13: =IF(LAVORAZIONI!S406="","",LAVORAZIONI!S406) | M13: =LAVORAZIONI!T406 | O13: =LAVORAZIONI!U406 | P13: =LAVORAZIONI!V406 | Q13: =LAVORAZIONI!W406 | R13: =LAVORAZIONI!X406 | S13: =LAVORAZIONI!Y406 | T13: =LAVORAZIONI!Z406 | U13: =LAVORAZIONI!AA406 | V13: =LAVORAZIONI!AB406 | ... AD13: =LAVORAZIONI!AJ406
B14: =LAVORAZIONI!G407 | C14: =LAVORAZIONI!A407 | D14: =LAVORAZIONI!K407 | E14: =LAVORAZIONI!H407 | F14: =LAVORAZIONI!M407 | G14: =LAVORAZIONI!N407 | H14: =LAVORAZIONI!O407 | I14: =LAVORAZIONI!P407 | J14: =IF(LAVORAZIONI!Q407="","",LAVORAZIONI!Q407) | K14: =IF(LAVORAZIONI!R407="","",LAVORAZIONI!R407) | L14: =IF(LAVORAZIONI!S407="","",LAVORAZIONI!S407) | M14: =LAVORAZIONI!T407 | O14: =LAVORAZIONI!U407 | P14: =LAVORAZIONI!V407 | Q14: =LAVORAZIONI!W407 | R14: =LAVORAZIONI!X407 | S14: =LAVORAZIONI!Y407 | T14: =LAVORAZIONI!Z407 | U14: =LAVORAZIONI!AA407 | V14: =LAVORAZIONI!AB407 | ... AD14: =LAVORAZIONI!AJ407
B15: =LAVORAZIONI!G408 | C15: =LAVORAZIONI!A408 | D15: =LAVORAZIONI!K408 | E15: =LAVORAZIONI!H408 | F15: =LAVORAZIONI!M408 | G15: =LAVORAZIONI!N408 | H15: =LAVORAZIONI!O408 | I15: =LAVORAZIONI!P408 | J15: =IF(LAVORAZIONI!Q408="","",LAVORAZIONI!Q408) | K15: =IF(LAVORAZIONI!R408="","",LAVORAZIONI!R408) | L15: =IF(LAVORAZIONI!S408="","",LAVORAZIONI!S408) | M15: =LAVORAZIONI!T408 | O15: =LAVORAZIONI!U408 | P15: =LAVORAZIONI!V408 | Q15: =LAVORAZIONI!W408 | R15: =LAVORAZIONI!X408 | S15: =LAVORAZIONI!Y408 | T15: =LAVORAZIONI!Z408 | U15: =LAVORAZIONI!AA408 | V15: =LAVORAZIONI!AB408 | ... AD15: =LAVORAZIONI!AJ408
B16: =LAVORAZIONI!G409 | C16: =LAVORAZIONI!A409 | D16: =LAVORAZIONI!K409 | E16: =LAVORAZIONI!H409 | F16: =LAVORAZIONI!M409 | G16: =LAVORAZIONI!N409 | H16: =LAVORAZIONI!O409 | I16: =LAVORAZIONI!P409 | J16: =IF(LAVORAZIONI!Q409="","",LAVORAZIONI!Q409) | K16: =IF(LAVORAZIONI!R409="","",LAVORAZIONI!R409) | L16: =IF(LAVORAZIONI!S409="","",LAVORAZIONI!S409) | M16: =LAVORAZIONI!T409 | O16: =LAVORAZIONI!U409 | P16: =LAVORAZIONI!V409 | Q16: =LAVORAZIONI!W409 | R16: =LAVORAZIONI!X409 | S16: =LAVORAZIONI!Y409 | T16: =LAVORAZIONI!Z409 | U16: =LAVORAZIONI!AA409 | V16: =LAVORAZIONI!AB409 | ... AD16: =LAVORAZIONI!AJ409
... B117: =LAVORAZIONI!G510 | C117: =LAVORAZIONI!A510 | D117: =LAVORAZIONI!K510 | E117: =LAVORAZIONI!H510 | F117: =LAVORAZIONI!M510 | G117: =LAVORAZIONI!N510 | H117: =LAVORAZIONI!O510 | I117: =LAVORAZIONI!P510 | J117: =IF(LAVORAZIONI!Q510="","",LAVORAZIONI!Q510) | K117: =IF(LAVORAZIONI!R510="","",LAVORAZIONI!R510) | L117: =IF(LAVORAZIONI!S510="","",LAVORAZIONI!S510) | M117: =LAVORAZIONI!T510 | O117: =LAVORAZIONI!U510 | P117: =LAVORAZIONI!V510 | Q117: =LAVORAZIONI!W510 | R117: =LAVORAZIONI!X510 | S117: =LAVORAZIONI!Y510 | T117: =LAVORAZIONI!Z510 | U117: =LAVORAZIONI!AA510 | V117: =LAVORAZIONI!AB510 | ... AD117: =LAVORAZIONI!AJ510
D118: TOTALE ELETTRICHE | I118: =SUM(I5:I117) | L118: =SUM(L5:L117) | M118: =SUM(M5:M117) | P118: =SUM(P5:P117) | R118: =SUM(R5:R117) | T118: =SUM(T5:T117) | V118: =SUM(V5:V117) | X118: =SUM(X5:X117) | Z118: =SUM(Z5:Z117) | AB118: =SUM(AB5:AB117) | AD118: =SUM(AD5:AD117)

Sheet ELETTRICHE SPECIALI
B2: DETTAGLIO SAL — OPERE ELETTRICHE SPECIALI A SERVIZIO DELLE APPARECCHIATURE DI LABORATORIO
B3: Nr.Ord. | C3: TARIFFA | D3: DESIGNAZIONE | E3: STEP | F3: U.M. | G3: Q.tà PREV | H3: VAL.UNIT PREV | I3: TOTALE PREV | J3: Q.tà CONS | K3: VAL.UNIT CONS | L3: TOTALE CONS | M3: VALORE PER SAL | O3: SAL 01 APRILE | Q3: SAL 02 MAGGIO | S3: SAL 03 GIUGNO | U3: SAL 04 LUGLIO | W3: SAL 05 AGOSTO | Y3: SAL 06 SETTEMBRE | AA3: SAL 07 OTTOBRE | AC3: TOTALE COMPL.
O4: % | P4: TOTALE | Q4: % | R4: TOTALE | S4: % | T4: TOTALE | U4: % | V4: TOTALE | W4: % | X4: TOTALE | Y4: % | Z4: TOTALE | AA4: % | AB4: TOTALE | AC4: % | AD4: TOTALE
B5: =LAVORAZIONI!G511 | C5: =LAVORAZIONI!A511 | D5: =LAVORAZIONI!K511 | E5: =LAVORAZIONI!H511 | F5: =LAVORAZIONI!M511 | G5: =LAVORAZIONI!N511 | H5: =LAVORAZIONI!O511 | I5: =LAVORAZIONI!P511 | J5: =IF(LAVORAZIONI!Q511="","",LAVORAZIONI!Q511) | K5: =IF(LAVORAZIONI!R511="","",LAVORAZIONI!R511) | L5: =IF(LAVORAZIONI!S511="","",LAVORAZIONI!S511) | M5: =LAVORAZIONI!T511 | O5: =LAVORAZIONI!U511 | P5: =LAVORAZIONI!V511 | Q5: =LAVORAZIONI!W511 | R5: =LAVORAZIONI!X511 | S5: =LAVORAZIONI!Y511 | T5: =LAVORAZIONI!Z511 | U5: =LAVORAZIONI!AA511 | V5: =LAVORAZIONI!AB511 | ... AD5: =LAVORAZIONI!AJ511
B6: =LAVORAZIONI!G512 | C6: =LAVORAZIONI!A512 | D6: =LAVORAZIONI!K512 | E6: =LAVORAZIONI!H512 | F6: =LAVORAZIONI!M512 | G6: =LAVORAZIONI!N512 | H6: =LAVORAZIONI!O512 | I6: =LAVORAZIONI!P512 | J6: =IF(LAVORAZIONI!Q512="","",LAVORAZIONI!Q512) | K6: =IF(LAVORAZIONI!R512="","",LAVORAZIONI!R512) | L6: =IF(LAVORAZIONI!S512="","",LAVORAZIONI!S512) | M6: =LAVORAZIONI!T512 | O6: =LAVORAZIONI!U512 | P6: =LAVORAZIONI!V512 | Q6: =LAVORAZIONI!W512 | R6: =LAVORAZIONI!X512 | S6: =LAVORAZIONI!Y512 | T6: =LAVORAZIONI!Z512 | U6: =LAVORAZIONI!AA512 | V6: =LAVORAZIONI!AB512 | ... AD6: =LAVORAZIONI!AJ512
B7: =LAVORAZIONI!G513 | C7: =LAVORAZIONI!A513 | D7: =LAVORAZIONI!K513 | E7: =LAVORAZIONI!H513 | F7: =LAVORAZIONI!M513 | G7: =LAVORAZIONI!N513 | H7: =LAVORAZIONI!O513 | I7: =LAVORAZIONI!P513 | J7: =IF(LAVORAZIONI!Q513="","",LAVORAZIONI!Q513) | K7: =IF(LAVORAZIONI!R513="","",LAVORAZIONI!R513) | L7: =IF(LAVORAZIONI!S513="","",LAVORAZIONI!S513) | M7: =LAVORAZIONI!T513 | O7: =LAVORAZIONI!U513 | P7: =LAVORAZIONI!V513 | Q7: =LAVORAZIONI!W513 | R7: =LAVORAZIONI!X513 | S7: =LAVORAZIONI!Y513 | T7: =LAVORAZIONI!Z513 | U7: =LAVORAZIONI!AA513 | V7: =LAVORAZIONI!AB513 | ... AD7: =LAVORAZIONI!AJ513
B8: =LAVORAZIONI!G514 | C8: =LAVORAZIONI!A514 | D8: =LAVORAZIONI!K514 | E8: =LAVORAZIONI!H514 | F8: =LAVORAZIONI!M514 | G8: =LAVORAZIONI!N514 | H8: =LAVORAZIONI!O514 | I8: =LAVORAZIONI!P514 | J8: =IF(LAVORAZIONI!Q514="","",LAVORAZIONI!Q514) | K8: =IF(LAVORAZIONI!R514="","",LAVORAZIONI!R514) | L8: =IF(LAVORAZIONI!S514="","",LAVORAZIONI!S514) | M8: =LAVORAZIONI!T514 | O8: =LAVORAZIONI!U514 | P8: =LAVORAZIONI!V514 | Q8: =LAVORAZIONI!W514 | R8: =LAVORAZIONI!X514 | S8: =LAVORAZIONI!Y514 | T8: =LAVORAZIONI!Z514 | U8: =LAVORAZIONI!AA514 | V8: =LAVORAZIONI!AB514 | ... AD8: =LAVORAZIONI!AJ514
B9: =LAVORAZIONI!G515 | C9: =LAVORAZIONI!A515 | D9: =LAVORAZIONI!K515 | E9: =LAVORAZIONI!H515 | F9: =LAVORAZIONI!M515 | G9: =LAVORAZIONI!N515 | H9: =LAVORAZIONI!O515 | I9: =LAVORAZIONI!P515 | J9: =IF(LAVORAZIONI!Q515="","",LAVORAZIONI!Q515) | K9: =IF(LAVORAZIONI!R515="","",LAVORAZIONI!R515) | L9: =IF(LAVORAZIONI!S515="","",LAVORAZIONI!S515) | M9: =LAVORAZIONI!T515 | O9: =LAVORAZIONI!U515 | P9: =LAVORAZIONI!V515 | Q9: =LAVORAZIONI!W515 | R9: =LAVORAZIONI!X515 | S9: =LAVORAZIONI!Y515 | T9: =LAVORAZIONI!Z515 | U9: =LAVORAZIONI!AA515 | V9: =LAVORAZIONI!AB515 | ... AD9: =LAVORAZIONI!AJ515
B10: =LAVORAZIONI!G516 | C10: =LAVORAZIONI!A516 | D10: =LAVORAZIONI!K516 | E10: =LAVORAZIONI!H516 | F10: =LAVORAZIONI!M516 | G10: =LAVORAZIONI!N516 | H10: =LAVORAZIONI!O516 | I10: =LAVORAZIONI!P516 | J10: =IF(LAVORAZIONI!Q516="","",LAVORAZIONI!Q516) | K10: =IF(LAVORAZIONI!R516="","",LAVORAZIONI!R516) | L10: =IF(LAVORAZIONI!S516="","",LAVORAZIONI!S516) | M10: =LAVORAZIONI!T516 | O10: =LAVORAZIONI!U516 | P10: =LAVORAZIONI!V516 | Q10: =LAVORAZIONI!W516 | R10: =LAVORAZIONI!X516 | S10: =LAVORAZIONI!Y516 | T10: =LAVORAZIONI!Z516 | U10: =LAVORAZIONI!AA516 | V10: =LAVORAZIONI!AB516 | ... AD10: =LAVORAZIONI!AJ516
B11: =LAVORAZIONI!G517 | C11: =LAVORAZIONI!A517 | D11: =LAVORAZIONI!K517 | E11: =LAVORAZIONI!H517 | F11: =LAVORAZIONI!M517 | G11: =LAVORAZIONI!N517 | H11: =LAVORAZIONI!O517 | I11: =LAVORAZIONI!P517 | J11: =IF(LAVORAZIONI!Q517="","",LAVORAZIONI!Q517) | K11: =IF(LAVORAZIONI!R517="","",LAVORAZIONI!R517) | L11: =IF(LAVORAZIONI!S517="","",LAVORAZIONI!S517) | M11: =LAVORAZIONI!T517 | O11: =LAVORAZIONI!U517 | P11: =LAVORAZIONI!V517 | Q11: =LAVORAZIONI!W517 | R11: =LAVORAZIONI!X517 | S11: =LAVORAZIONI!Y517 | T11: =LAVORAZIONI!Z517 | U11: =LAVORAZIONI!AA517 | V11: =LAVORAZIONI!AB517 | ... AD11: =LAVORAZIONI!AJ517
B12: =LAVORAZIONI!G518 | C12: =LAVORAZIONI!A518 | D12: =LAVORAZIONI!K518 | E12: =LAVORAZIONI!H518 | F12: =LAVORAZIONI!M518 | G12: =LAVORAZIONI!N518 | H12: =LAVORAZIONI!O518 | I12: =LAVORAZIONI!P518 | J12: =IF(LAVORAZIONI!Q518="","",LAVORAZIONI!Q518) | K12: =IF(LAVORAZIONI!R518="","",LAVORAZIONI!R518) | L12: =IF(LAVORAZIONI!S518="","",LAVORAZIONI!S518) | M12: =LAVORAZIONI!T518 | O12: =LAVORAZIONI!U518 | P12: =LAVORAZIONI!V518 | Q12: =LAVORAZIONI!W518 | R12: =LAVORAZIONI!X518 | S12: =LAVORAZIONI!Y518 | T12: =LAVORAZIONI!Z518 | U12: =LAVORAZIONI!AA518 | V12: =LAVORAZIONI!AB518 | ... AD12: =LAVORAZIONI!AJ518
B13: =LAVORAZIONI!G519 | C13: =LAVORAZIONI!A519 | D13: =LAVORAZIONI!K519 | E13: =LAVORAZIONI!H519 | F13: =LAVORAZIONI!M519 | G13: =LAVORAZIONI!N519 | H13: =LAVORAZIONI!O519 | I13: =LAVORAZIONI!P519 | J13: =IF(LAVORAZIONI!Q519="","",LAVORAZIONI!Q519) | K13: =IF(LAVORAZIONI!R519="","",LAVORAZIONI!R519) | L13: =IF(LAVORAZIONI!S519="","",LAVORAZIONI!S519) | M13: =LAVORAZIONI!T519 | O13: =LAVORAZIONI!U519 | P13: =LAVORAZIONI!V519 | Q13: =LAVORAZIONI!W519 | R13: =LAVORAZIONI!X519 | S13: =LAVORAZIONI!Y519 | T13: =LAVORAZIONI!Z519 | U13: =LAVORAZIONI!AA519 | V13: =LAVORAZIONI!AB519 | ... AD13: =LAVORAZIONI!AJ519
B14: =LAVORAZIONI!G520 | C14: =LAVORAZIONI!A520 | D14: =LAVORAZIONI!K520 | E14: =LAVORAZIONI!H520 | F14: =LAVORAZIONI!M520 | G14: =LAVORAZIONI!N520 | H14: =LAVORAZIONI!O520 | I14: =LAVORAZIONI!P520 | J14: =IF(LAVORAZIONI!Q520="","",LAVORAZIONI!Q520) | K14: =IF(LAVORAZIONI!R520="","",LAVORAZIONI!R520) | L14: =IF(LAVORAZIONI!S520="","",LAVORAZIONI!S520) | M14: =LAVORAZIONI!T520 | O14: =LAVORAZIONI!U520 | P14: =LAVORAZIONI!V520 | Q14: =LAVORAZIONI!W520 | R14: =LAVORAZIONI!X520 | S14: =LAVORAZIONI!Y520 | T14: =LAVORAZIONI!Z520 | U14: =LAVORAZIONI!AA520 | V14: =LAVORAZIONI!AB520 | ... AD14: =LAVORAZIONI!AJ520
B15: =LAVORAZIONI!G521 | C15: =LAVORAZIONI!A521 | D15: =LAVORAZIONI!K521 | E15: =LAVORAZIONI!H521 | F15: =LAVORAZIONI!M521 | G15: =LAVORAZIONI!N521 | H15: =LAVORAZIONI!O521 | I15: =LAVORAZIONI!P521 | J15: =IF(LAVORAZIONI!Q521="","",LAVORAZIONI!Q521) | K15: =IF(LAVORAZIONI!R521="","",LAVORAZIONI!R521) | L15: =IF(LAVORAZIONI!S521="","",LAVORAZIONI!S521) | M15: =LAVORAZIONI!T521 | O15: =LAVORAZIONI!U521 | P15: =LAVORAZIONI!V521 | Q15: =LAVORAZIONI!W521 | R15: =LAVORAZIONI!X521 | S15: =LAVORAZIONI!Y521 | T15: =LAVORAZIONI!Z521 | U15: =LAVORAZIONI!AA521 | V15: =LAVORAZIONI!AB521 | ... AD15: =LAVORAZIONI!AJ521
B16: =LAVORAZIONI!G522 | C16: =LAVORAZIONI!A522 | D16: =LAVORAZIONI!K522 | E16: =LAVORAZIONI!H522 | F16: =LAVORAZIONI!M522 | G16: =LAVORAZIONI!N522 | H16: =LAVORAZIONI!O522 | I16: =LAVORAZIONI!P522 | J16: =IF(LAVORAZIONI!Q522="","",LAVORAZIONI!Q522) | K16: =IF(LAVORAZIONI!R522="","",LAVORAZIONI!R522) | L16: =IF(LAVORAZIONI!S522="","",LAVORAZIONI!S522) | M16: =LAVORAZIONI!T522 | O16: =LAVORAZIONI!U522 | P16: =LAVORAZIONI!V522 | Q16: =LAVORAZIONI!W522 | R16: =LAVORAZIONI!X522 | S16: =LAVORAZIONI!Y522 | T16: =LAVORAZIONI!Z522 | U16: =LAVORAZIONI!AA522 | V16: =LAVORAZIONI!AB522 | ... AD16: =LAVORAZIONI!AJ522
... B102: =LAVORAZIONI!G608 | C102: =LAVORAZIONI!A608 | D102: =LAVORAZIONI!K608 | E102: =LAVORAZIONI!H608 | F102: =LAVORAZIONI!M608 | G102: =LAVORAZIONI!N608 | H102: =LAVORAZIONI!O608 | I102: =LAVORAZIONI!P608 | J102: =IF(LAVORAZIONI!Q608="","",LAVORAZIONI!Q608) | K102: =IF(LAVORAZIONI!R608="","",LAVORAZIONI!R608) | L102: =IF(LAVORAZIONI!S608="","",LAVORAZIONI!S608) | M102: =LAVORAZIONI!T608 | O102: =LAVORAZIONI!U608 | P102: =LAVORAZIONI!V608 | Q102: =LAVORAZIONI!W608 | R102: =LAVORAZIONI!X608 | S102: =LAVORAZIONI!Y608 | T102: =LAVORAZIONI!Z608 | U102: =LAVORAZIONI!AA608 | V102: =LAVORAZIONI!AB608 | ... AD102: =LAVORAZIONI!AJ608
D103: TOTALE ELETTRICHE SPECIALI | I103: =SUM(I5:I102) | L103: =SUM(L5:L102) | M103: =SUM(M5:M102) | P103: =SUM(P5:P102) | R103: =SUM(R5:R102) | T103: =SUM(T5:T102) | V103: =SUM(V5:V102) | X103: =SUM(X5:X102) | Z103: =SUM(Z5:Z102) | AB103: =SUM(AB5:AB102) | AD103: =SUM(AD5:AD102)

Sheet SICUREZZA
B2: ONERI DELLA SICUREZZA COME DA PSC
B3: Nr.Ord. | C3: TARIFFA | D3: DESIGNAZIONE | G3: TOTALE | I3: SAL 01 APRILE | K3: SAL 02 MAGGIO | M3: SAL 03 GIUGNO | O3: SAL 04 LUGLIO | Q3: SAL 05 AGOSTO | S3: SAL 06 SETTEMBRE | U3: SAL 07 OTTOBRE | W3: TOTALE COMPL.
I4: % | J4: TOTALE | K4: % | L4: TOTALE | M4: % | N4: TOTALE | O4: % | P4: TOTALE | Q4: % | R4: TOTALE | S4: % | T4: TOTALE | U4: % | V4: TOTALE | W4: % | X4: TOTALE
B5: 1 | C5: PSC | D5: ONERI DELLA SICUREZZA COME DA PSC | G5: 51334.15 | I5: 0.15 | J5: =$G5*I5 | K5: 0 | L5: =$G5*K5 | M5: 0 | N5: =$G5*M5 | O5: 0 | P5: =$G5*O5 | Q5: 0 | R5: =$G5*Q5 | S5: 0 | T5: =$G5*S5 | U5: 0 | V5: =$G5*U5 | W5: =I5+K5+M5+O5+Q5+S5+U5 | X5: =J5+L5+N5+P5+R5+T5+V5

Sheet TOTALE
A1: TOTALE — RIEPILOGO AVANZAMENTO PER CATEGORIA × SAL
A3: CATEGORIA SAL | B3: PREVENTIVO | C3: SAL 01 APRILE | D3: SAL 02 MAGGIO | E3: SAL 03 GIUGNO | F3: SAL 04 LUGLIO | G3: SAL 05 AGOSTO | H3: SAL 06 SETTEMBRE | I3: SAL 07 OTTOBRE | J3: TOTALE
A4: EDILI | B4: =SUMIFS(LAVORAZIONI!P:P,LAVORAZIONI!E:E,A4) | C4: =SUMIFS(LAVORAZIONI!V:V,LAVORAZIONI!E:E,A4) | D4: =SUMIFS(LAVORAZIONI!X:X,LAVORAZIONI!E:E,A4) | E4: =SUMIFS(LAVORAZIONI!Z:Z,LAVORAZIONI!E:E,A4) | F4: =SUMIFS(LAVORAZIONI!AB:AB,LAVORAZIONI!E:E,A4) | G4: =SUMIFS(LAVORAZIONI!AD:AD,LAVORAZIONI!E:E,A4) | H4: =SUMIFS(LAVORAZIONI!AF:AF,LAVORAZIONI!E:E,A4) | I4: =SUMIFS(LAVORAZIONI!AH:AH,LAVORAZIONI!E:E,A4) | J4: =SUM(C4:I4)
A5: EDILI SPECIALI | B5: =SUMIFS(LAVORAZIONI!P:P,LAVORAZIONI!E:E,A5) | C5: =SUMIFS(LAVORAZIONI!V:V,LAVORAZIONI!E:E,A5) | D5: =SUMIFS(LAVORAZIONI!X:X,LAVORAZIONI!E:E,A5) | E5: =SUMIFS(LAVORAZIONI!Z:Z,LAVORAZIONI!E:E,A5) | F5: =SUMIFS(LAVORAZIONI!AB:AB,LAVORAZIONI!E:E,A5) | G5: =SUMIFS(LAVORAZIONI!AD:AD,LAVORAZIONI!E:E,A5) | H5: =SUMIFS(LAVORAZIONI!AF:AF,LAVORAZIONI!E:E,A5) | I5: =SUMIFS(LAVORAZIONI!AH:AH,LAVORAZIONI!E:E,A5) | J5: =SUM(C5:I5)
A6: MECCANICHE | B6: =SUMIFS(LAVORAZIONI!P:P,LAVORAZIONI!E:E,A6) | C6: =SUMIFS(LAVORAZIONI!V:V,LAVORAZIONI!E:E,A6) | D6: =SUMIFS(LAVORAZIONI!X:X,LAVORAZIONI!E:E,A6) | E6: =SUMIFS(LAVORAZIONI!Z:Z,LAVORAZIONI!E:E,A6) | F6: =SUMIFS(LAVORAZIONI!AB:AB,LAVORAZIONI!E:E,A6) | G6: =SUMIFS(LAVORAZIONI!AD:AD,LAVORAZIONI!E:E,A6) | H6: =SUMIFS(LAVORAZIONI!AF:AF,LAVORAZIONI!E:E,A6) | I6: =SUMIFS(LAVORAZIONI!AH:AH,LAVORAZIONI!E:E,A6) | J6: =SUM(C6:I6)
A7: MECCANICHE SPECIALI | B7: =SUMIFS(LAVORAZIONI!P:P,LAVORAZIONI!E:E,A7) | C7: =SUMIFS(LAVORAZIONI!V:V,LAVORAZIONI!E:E,A7) | D7: =SUMIFS(LAVORAZIONI!X:X,LAVORAZIONI!E:E,A7) | E7: =SUMIFS(LAVORAZIONI!Z:Z,LAVORAZIONI!E:E,A7) | F7: =SUMIFS(LAVORAZIONI!AB:AB,LAVORAZIONI!E:E,A7) | G7: =SUMIFS(LAVORAZIONI!AD:AD,LAVORAZIONI!E:E,A7) | H7: =SUMIFS(LAVORAZIONI!AF:AF,LAVORAZIONI!E:E,A7) | I7: =SUMIFS(LAVORAZIONI!AH:AH,LAVORAZIONI!E:E,A7) | J7: =SUM(C7:I7)
A8: ELETTRICHE | B8: =SUMIFS(LAVORAZIONI!P:P,LAVORAZIONI!E:E,A8) | C8: =SUMIFS(LAVORAZIONI!V:V,LAVORAZIONI!E:E,A8) | D8: =SUMIFS(LAVORAZIONI!X:X,LAVORAZIONI!E:E,A8) | E8: =SUMIFS(LAVORAZIONI!Z:Z,LAVORAZIONI!E:E,A8) | F8: =SUMIFS(LAVORAZIONI!AB:AB,LAVORAZIONI!E:E,A8) | G8: =SUMIFS(LAVORAZIONI!AD:AD,LAVORAZIONI!E:E,A8) | H8: =SUMIFS(LAVORAZIONI!AF:AF,LAVORAZIONI!E:E,A8) | I8: =SUMIFS(LAVORAZIONI!AH:AH,LAVORAZIONI!E:E,A8) | J8: =SUM(C8:I8)
A9: ELETTRICHE SPECIALI | B9: =SUMIFS(LAVORAZIONI!P:P,LAVORAZIONI!E:E,A9) | C9: =SUMIFS(LAVORAZIONI!V:V,LAVORAZIONI!E:E,A9) | D9: =SUMIFS(LAVORAZIONI!X:X,LAVORAZIONI!E:E,A9) | E9: =SUMIFS(LAVORAZIONI!Z:Z,LAVORAZIONI!E:E,A9) | F9: =SUMIFS(LAVORAZIONI!AB:AB,LAVORAZIONI!E:E,A9) | G9: =SUMIFS(LAVORAZIONI!AD:AD,LAVORAZIONI!E:E,A9) | H9: =SUMIFS(LAVORAZIONI!AF:AF,LAVORAZIONI!E:E,A9) | I9: =SUMIFS(LAVORAZIONI!AH:AH,LAVORAZIONI!E:E,A9) | J9: =SUM(C9:I9)
A10: SICUREZZA | B10: =SICUREZZA!G5 | C10: =SICUREZZA!J5 | D10: =SICUREZZA!L5 | E10: =SICUREZZA!N5 | F10: =SICUREZZA!P5 | G10: =SICUREZZA!R5 | H10: =SICUREZZA!T5 | I10: =SICUREZZA!V5 | J10: =SUM(C10:I10)
A11: TOTALE COMPLESSIVO | B11: =SUM(B4:B10) | C11: =SUM(C4:C10) | D11: =SUM(D4:D10) | E11: =SUM(E4:E10) | F11: =SUM(F4:F10) | G11: =SUM(G4:G10) | H11: =SUM(H4:H10) | I11: =SUM(I4:I10) | J11: =SUM(J4:J10)
A13: CUMULATO % | C13: =IFERROR((C11)/$B$11,0) | D13: =IFERROR((C11+D11)/$B$11,0) | E13: =IFERROR((C11+D11+E11)/$B$11,0) | F13: =IFERROR((C11+D11+E11+F11)/$B$11,0) | G13: =IFERROR((C11+D11+E11+F11+G11)/$B$11,0) | H13: =IFERROR((C11+D11+E11+F11+G11+H11)/$B$11,0) | I13: =IFERROR((C11+D11+E11+F11+G11+H11+I11)/$B$11,0)
